Workbook
Name lstParameter: Lists!$AM$5:$AM$37
Name lstSector: Lists!$I$5:$I$27
Name lstService: 'Fee Schedule'!$A$6:$A$16
Name setLetterhead_1: Lists!$P$13
Name lstUnit: Lists!$E$5:$E$8
Name T_tblLicenceEffluent: 'Licence Effluent'!$A$5:$L$6
Name T_tSignatory: Lists!$T$5:$V$7
Name T_tOffice: Lists!$AF$5:$AI$7
Name lstClrNo: Lists!$R$5:$R$404
Name lstChemical: Lists!$G$5:$G$56
Name lstLicCategory: Lists!$A$5:$A$10
Name T_tSector: Lists!$I$5:$I$27
Name T_tblIssues: 'Notes & Issues'!$A$5:$G$26
Name lstBillNo: Lists!$X$5:$X$404
Name T_tblCorrespondence: 'Notes & Issues'!$A$31:$I$31
Name lstServiceForBill: Lists!$AK$5:$AK$40
Name lstSchedule: Lists!$AQ$5:$AQ$10
Name T_tblServices: 'Fee Schedule'!$A$6:$D$16
Name setAcctTitle: Lists!$P$11
Name setLetterhead_3: Lists!$P$15
Name T_tblBills: 'Bills & Invoices'!$A$5:$V$32
Name setAcctNo: Lists!$P$10
Name T_tChemical: Lists!$G$5:$G$56
Name setLetterhead_5: Lists!$P$17
Name lstCompanyID: Companies!$A$5:$A$74
Name setSigBillTitle: Lists!$P$8
Name lstRecordGroup: Lists!$M$5:$M$8
Name setSigLicTitle: Lists!$P$6
Name lstBillType: 'Fee Schedule'!$A$20:$A$26
Name T_tRecordGroup: Lists!$M$5:$M$8
Name lstLicType: Lists!$C$5:$C$12
Name lstEffUnit: Lists!$AO$5:$AO$13
Name setSigClrName: Lists!$P$18
Name setSigBillName: Lists!$P$7
Name lstLicID: 'Licences & Certificates'!$A$5:$A$73
Name T_tblClearances: 'Chemical Clearances'!$A$5:$Q$169
Name T_tLicType: Lists!$C$5:$C$12
Name lstPurpose: Lists!$K$5:$K$18
Name setBank: Lists!$P$9
Name T_tEffUnit: Lists!$AO$5:$AO$13
Name setSigClrTitle: Lists!$P$19
Name setLetterhead_2: Lists!$P$14
Name T_tblLicenceVehicles: 'Licence Vehicles'!$A$5:$F$67
Name lstCompanyName: Companies!$B$5:$B$74
Name T_tblCompanies: Companies!$A$5:$J$74
Name T_tblPayments: 'Payments & Receipts'!$A$5:$L$58
Name setSigLicName: Lists!$P$5
Name lstBillPick: Lists!$Y$5:$Y$404
Name lstBillID: 'Bills & Invoices'!$A$5:$A$32
Name T_tParameter: Lists!$AM$5:$AM$37
Name T_tblLicenceChemicals: 'Licence Chemicals'!$A$5:$I$167
Name T_tUnit: Lists!$E$5:$E$8
Name lstSignatory: Lists!$T$5:$T$7
Name T_tPurpose: Lists!$K$5:$K$18
Name T_tblUsers: Users!$A$4:$H$5
Name T_tblLicences: 'Licences & Certificates'!$A$5:$Q$73
Name T_tSchedule: Lists!$AQ$5:$AQ$10
Name T_tLicCategory: Lists!$A$5:$A$10
Name T_tblBillTypes: 'Fee Schedule'!$A$20:$G$26
Name setLetterhead_4: Lists!$P$16

Sheet Main Menu
A1: EPA LIBERIA – ERRS | CHEMICAL MANAGEMENT UNIT (CMU) DATABASE 2026
A2: Main Menu – click a button to open a form or register. Buttons run the Apps Script (menu: CMU Database). First time: CMU Database ▸ Setup ▸ Rebuild Everything. | F2: {=IFERROR(IF(CMU_CodeVersion()="2026.09.26-R","✔ Macros up to date","⚠ Old macros – paste the new code from Macro Setup"),"⚠ Macros not installed – follow the steps on Macro Setup")} -> ⚠ Old macros – paste the new code from Macro Setup
F3: No-login mode: full access enabled
B37: 📘 Open the User Manual
B38: QUICK FIGURES
B39: Companies | C39: =ROWS(Companies!$A$5:$A$74) -> 70 | D39: Licences | E39: =ROWS('Licences & Certificates'!$A$5:$A$73) -> 69 | F39: Clearances | G39: =ROWS('Chemical Clearances'!$A$5:$A$169) -> 165 | H39: Billed / Paid | I39: =TEXT(SUM('Bills & Invoices'!$J$5:$J$32),"$#,##0")&" / "&TEXT(SUM('Payments & Receipts'!$F$5:$F$58),"$#,##0") -> $279,151 / $434,983

Sheet CMU System Doctor
A1: Check | B1: Status | C1: Details
A2: Code version | B2: 2026.09.30-UI | C2: Current Apps Script upgrade version
A3: No-login mode | B3: ON / AVAILABLE | C3: Security is controlled by Google Sheet sharing if no-login is active.
A4: Sheets | B4: CHECK | C4: Missing: Login
A5: Named table ranges | B5: OK | C5: All table ranges found
A6: Formula errors | B6: CHECK | C6: 3 formula error(s) found

Sheet Setup Check
A1: Area | B1: Sheet | C1: Result | D1: Details
A2: Formulas | B2: Login | C2: OK
A3: Formulas | B3: Main Menu | C3: OK
A4: Formulas | B4: User Manual | C4: OK
A5: Formulas | B5: Dashboard | C5: OK
A6: Formulas | B6: Company Form | C6: OK
A7: Formulas | B7: Licence Form | C7: OK
A8: Formulas | B8: Clearance Form | C8: OK
A9: Formulas | B9: Bill Form | C9: OK
A10: Formulas | B10: Payment Form | C10: OK
A11: Formulas | B11: Print CRL | C11: OK
A12: Formulas | B12: Print CIL | C12: OK
A13: Formulas | B13: Print EDL | C13: OK
A14: Formulas | B14: Print EDL RP | C14: 3 error(s) | D14: C82 #N/A, C97 #N/A, C112 #N/A
A15: Formulas | B15: Print Clearance | C15: OK
A16: Formulas | B16: Print Bill | C16: OK
A17: Formulas | B17: Companies | C17: OK
A18: Formulas | B18: Licences & Certificates | C18: OK
A19: Formulas | B19: Licence Chemicals | C19: OK
A20: Formulas | B20: Licence Vehicles | C20: OK
A21: Formulas | B21: Licence Effluent | C21: OK
A22: Formulas | B22: Chemical Clearances | C22: OK
A23: Formulas | B23: Bills & Invoices | C23: OK
A24: Formulas | B24: Payments & Receipts | C24: OK
A25: Formulas | B25: Notes & Issues | C25: OK
A26: Formulas | B26: Fee Schedule | C26: OK
... A59: Buttons | B59: SRC CMU Receipts | C59: OK (1)
A60: Drop-down | B60: Company Form | C60: OK (23 items) | D60: C7 ← Lists!I5:I27
A61: Drop-down | B61: Licence Form | C61: OK (70 items) | D61: C6 ← Companies!B5:B74
A62: Drop-down | B62: Licence Form | C62: OK (6 items) | D62: C7 ← Lists!A5:A10
A63: Drop-down | B63: Licence Form | C63: OK (8 items) | D63: C8 ← Lists!C5:C12
A64: Drop-down | B64: Licence Form | C64: OK (52 items) | D64: C20:C34 ← Lists!G5:G56
A65: Drop-down | B65: Licence Form | C65: OK (4 items) | D65: G20:G34 ← Lists!E5:E8
A66: Drop-down | B66: Licence Form | C66: OK (33 items) | D66: C45:C64 ← Lists!AM5:AM37
A67: Drop-down | B67: Licence Form | C67: OK (9 items) | D67: D45:D64 ← Lists!AO5:AO13
A68: Drop-down | B68: Licence Form | C68: OK (6 items) | D68: G45:G64 ← Lists!AQ5:AQ10
A69: Drop-down | B69: Clearance Form | C69: OK (52 items) | D69: D13:D32 ← Lists!G5:G56
A70: Drop-down | B70: Clearance Form | C70: OK (4 items) | D70: F13:F32 ← Lists!E5:E8
A71: Drop-down | B71: Clearance Form | C71: OK (70 items) | D71: C6 ← Companies!B5:B74
... A97: Drop-down | B97: Payments & Receipts | C97: OK (70 items) | D97: B5:B58 ← Companies!A5:A74

Sheet User Manual
B2: CMU DATABASE – USER MANUAL
B3: EPA Liberia · ERRS · Chemical Management Unit (CMU) Database 2026 · Version 1.0 – 27 September 2026
B4: ← Back to Main Menu
B6: Contents
B8: 1. About this manual
B9: 2. Getting started – opening and signing in
B10: 3. How the workbook is organised
B11: 4. The Main Menu
B12: 5. Record numbers and cell colours
B13: 6. Everyday tasks – step by step
B14: 7. The registers (database)
B15: 8. Dashboard
... B24: This manual explains how to use the CMU DATABASE workbook: signing in, the Main Menu, the five data-entry forms, the registers, printing licences, clearance letters and bills, and routine administration. The screenshots were taken from the live workbook on 27 September 2026, so the records shown in them will differ from what you see as new data is added.
B25: User | C25: Main tasks | F25: Sheets used most
B26: Data-entry officer | C26: Register companies, record licences, clearances, bills and payments; print letters | F26: Forms, Print Centre, Find / Print a Record
B27: Supervisor / Unit head | C27: Monitor activity and outstanding bills; review data issues; approve letters | F27: Dashboard, Registers, Notes & Issues
B28: Administrator | C28: Manage users and passwords, fees, dropdown lists and the macro code | F28: Users & Passwords, Fee Schedule, Lists, Macro Setup
B31: 2. Getting started – opening and signing in
B33: STEP 1 | C33: Open CMU DATABASE.xlsm in the desktop version of Microsoft Excel (Windows). Excel on the web and on phones cannot run the buttons.
B35: STEP 2 | C35: If a yellow SECURITY WARNING bar appears under the ribbon, click Enable Content. Without this, none of the buttons work.
B37: STEP 3 | C37: The Sign In window opens. Type your username and password and press Enter. The first time you sign in you are asked to create your own password (at least 6 characters). After 5 wrong attempts the window closes.
B39: STEP 4 | C39: The Main Menu opens. Check the top-right corner shows ✓ Macros up to date and Signed in: <your name>.
B41: STEP 5 | C41: When you finish, click Log Out on the Main Menu, then save the file with Ctrl + S. Always keep the file as .xlsm (macro-enabled).
B43: ⚠ IMPORTANT: If the corner says 'Old macros' or the buttons do nothing, see Section 12 – Troubleshooting.
B46: 3. How the workbook is organised
B48: Every sheet belongs to one of five groups. The groups use the same colours as the Main Menu buttons, so you can always tell what kind of sheet you are on.
B49: Colour | C49: Group | D49: Sheets | F49: What you do there
C50: Data-entry forms | D50: Company Form, Licence Form, Clearance Form, Bill Form, Payment Form | F50: Add, find, update or delete records
C51: Registers (database) | D51: Companies, Licences & Certificates, Licence Chemicals, Licence Vehicles, Licence Effluent, Chemical Clearances, Bills & Invoices, Payments & Receipts, Notes & Issues | F51: Where every saved record is stored – view, filter and sort
C52: Print Centre | D52: Print CRL, Print CIL, Print EDL, Print EDL RP, Print Clearance, Print Bill | F52: Produce official licences and letters (print, PDF or Word)
C53: Reports & settings | D53: Dashboard, Fee Schedule, Lists, Macro Setup, User Manual | F53: Summaries, fees, dropdown values, macro code, this manual
C54: Source data | D54: SRC BMMC Log, SRC CMU Receipts | F54: Original logs kept for reference – do not edit
B56: A typical case moves through the workbook from left to right, as shown in Figure 1. Every record carries the Company ID, which keeps all the registers linked together.
B66: Figure 1 – The life of a case: from company registration to the printed letter
B68: 4. The Main Menu
B70: The Main Menu is the home screen. Every button opens a form, a register, a print page or a pop-up window. The numbered markers on Figure 2 match the table below it.
B106: Figure 2 – The Main Menu with its nine areas numbered
B108: No. | C108: Area | D108: What it does
B109: 1 | C109: Status | D109: Shows whether the installed macros are current and who is signed in
B110: 2 | C110: Quick Actions | D110: Create New Bill (step-by-step pop-up) and Find / Print a Record (searches every register)
B111: 3 | C111: Data Entry Forms | D111: Opens the five forms: Company, Licence / Certificate, Clearance, Bill, Payment
B112: 4 | C112: Registers | D112: Opens any register table (the database)
B113: 5 | C113: Print Centre | D113: Opens the print pages for CRL, CIL, EDL, EDL retention pond, clearance letter and bill letter
B114: 6 | C114: Reports & Settings | D114: Dashboard, Fee Schedule & Letter Wording, Dropdown Lists, Macro Setup
B115: 7 | C115: Account | D115: Users & Passwords (Admin only), Change My Password, Log Out
B116: 8 | C116: Source Data | D116: Original BMMC clearance log and CMU receipts
B117: 9 | C117: Quick Figures | D117: Live totals of companies, licences, clearances and amounts billed / paid
B119: 💡 TIP: Every form, register and print page has a dark Main Menu button (top-right or in the GO TO panel) that brings you back here.
B122: 5. Record numbers and cell colours
B124: Record numbers are issued automatically when you click Save New. Never type a new ID yourself. To change an existing record, type its ID in the ID cell (row 5 of the form) and click Find Record.
B125: Prefix | C125: Record | D125: Created by | E125: Example
B126: CMU-### | C126: Company | D126: Company Form | E126: CMU-069
B127: LIC-### | C127: Licence or certificate | D127: Licence Form | E127: LIC-070
B128: CLN-### | C128: Clearance (one letter, up to 20 chemicals) | D128: Clearance Form | E128: CLN-147
B129: CLR-### | C129: One chemical line inside a clearance | D129: Clearance Form (automatic) | E129: CLR-165
B130: BN-2026-### | C130: Bill (one letter) | D130: Create New Bill / Bill Form | E130: BN-2026-020
B131: BIL-### | C131: One service line inside a bill | D131: Bill Form (automatic) | E131: BIL-028
B132: PAY-### | C132: Payment / receipt | D132: Payment Form | E132: PAY-054
B133: ISS-### | C133: Data issue | D133: Typed on Notes & Issues | E133: ISS-022
B136: What the cell colours mean
B138: Sample | C138: Meaning
B139: Type here | C139: Input cell – type a value or pick from the dropdown arrow. Labels marked * are required.
B140: CMU-070 | C140: Record ID – leave blank for a new record; type an ID to find an existing one
B141: Guidance text | C141: Grey italic text beside a field explains what to enter
B142: ✓ Ready to save | C142: Form Status bar – ✓ green means ready; ✗ red lists what is missing
B143: Formula | C143: Calculated column in a register – filled automatically, never type over it
B146: 6. Everyday tasks – step by step
B149: 6.1 Register a new company
B163: Figure 3 – Company Registration Form
B165: STEP 1 | C165: On the Main Menu click Register Company.
B167: STEP 2 | C167: Leave Company ID blank. The grey text shows the next number (for example CMU-070).
B169: STEP 3 | C169: Type the official Company Name (required). Choose the Sector / Activity, then type the Location and any Other Names used on documents, separated by ;
B171: STEP 4 | C171: Check the Form Status bar shows ✓, then click Save New. The company is added to the Companies register with its new ID.
B173: 💡 TIP: Search first with Find / Print a Record to avoid registering the same company twice. The pop-up version of this form warns you when a similar name already exists.
B176: 6.2 Record a licence or certificate
B206: Figure 4 – Licence / Certificate Form (top part)
B208: STEP 1 | C208: Click Licence / Certificate Form. Leave the Record ID blank for a new licence.
B210: STEP 2 | C210: Choose the Company, Licence Category (CRL, CIL, EDL, Dewatering, Fumigation, Transportation…), Type and Location; enter the application and response dates.
B212: STEP 3 | C212: When the licence is issued, enter the Licence / Certificate No., Date Issued and Expiry Date. Without a number the licence shows as Pending.
B214: STEP 4 | C214: For CIL / CRL licences list the approved chemicals in the chemical grid; for EDL licences complete the effluent sections further down the form.
B216: STEP 5 | C216: Click Save New. Chemicals are saved to Licence Chemicals and effluent details to Licence Effluent automatically.
B219: 6.3 Record a chemical clearance
B251: Figure 5 – Chemical Clearance Form – A status, B letter details, C chemical lines, D record buttons, E output and navigation
B253: Marker | C253: Part of the form | D253: Notes
B254: A | C254: Form Status | D254: Shows ✓ Ready to save and the number of chemical lines, or what is missing
B255: B | C255: Letter details | D255: Company, clearance date, EPA ref. no. (e.g. ED/EPA-01/388/26/RL), default B/L, remarks, ETA
B256: C | C256: Chemical lines | D256: Up to 20 chemicals: name as written, standard name, quantity, unit, and B/L if different from the default. The total in kg and MT is shown at the bottom.
B257: D | C257: RECORD buttons | D257: Save New, Find Record, Update Record, Delete Record, Clear Form
B258: E | C258: OUTPUT / GO TO | D258: Open the clearance letter, create a bill, open the register or return to the Main Menu
B260: STEP 1 | C260: Click Chemical Clearance Form, then Clear Form.
B262: STEP 2 | C262: Fill the letter details (B). Pick the company from the dropdown.
B264: STEP 3 | C264: List each chemical on its own line (C). Choose the unit (kg, MT, L…) – quantities are converted to kg in the register.
B266: STEP 4 | C266: Click Save New. The clearance gets a CLN number and each line a CLR number.
B268: STEP 5 | C268: To print the letter click the OUTPUT button or go to Print Clearance (Section 6.7).
B271: 6.4 Create a bill
B298: Figure 6 – Bill / Invoice Form
B300: Fastest way: click + CREATE NEW BILL on the Main Menu. The pop-up walks you through three steps – 1) bill type, 2) company, 3) services and amounts. Suggested fees come from the Fee Schedule, the total and the amount in words update as you type, and Save stays disabled until everything required is filled. You can also fill the Bill / Invoice Form directly. Each bill gets a number BN-2026-### and prints from the Print Bill page.
B302: 6.5 Record a payment
B319: Figure 7 – Payment / Receipt Form
B321: STEP 1 | C321: Click Record Payment / Receipt.
...

Sheet Dashboard
A1: ERRS – CHEMICAL MANAGEMENT UNIT (CMU) | 2026 DATABASE DASHBOARD
A2: All figures are live formulas from the registers (Companies, Licences & Certificates, Chemical Clearances, Payments & Receipts, Bills & Invoices, Data Issues).
A4: Companies | B4: Licences / Certs Numbered | C4: Licences Pending | D4: Clearances (No.) | E4: Total Cleared (MT) | F4: Total Billed (USD) | G4: Total Paid (USD) | H4: Open Data Issues
A5: =ROWS(Companies!$A$5:$A$74) -> 70 | B5: =COUNTIFS('Licences & Certificates'!$K$5:$K$73,"<>") -> 60 | C5: =COUNTIFS('Licences & Certificates'!$N$5:$N$73,"Pending*") -> 9 | D5: =ROWS('Chemical Clearances'!$A$5:$A$169) -> 165 | E5: =SUM('Chemical Clearances'!$J$5:$J$169) -> 15779.981 | F5: =SUM('Bills & Invoices'!$J$5:$J$32) -> 279151 | G5: =SUM('Payments & Receipts'!$F$5:$F$58) -> 434983 | H5: =COUNTIFS('Notes & Issues'!$G$5:$G$26,"Open") -> 8
A7: MONTHLY ACTIVITY 2026 | J7: LICENCES & CERTIFICATES BY CATEGORY
A8: Month | B8: Clearances (No.) | C8: Cleared (MT) | D8: Payments (No.) | E8: Amount Paid (USD) | F8: Amount Billed (USD) | G8: Licences Issued | J8: Licence Category | K8: Total | L8: Active | M8: Issued – expiry not recorded | N8: Pending – no licence no. | P8: OUTSTANDING BILLS (Unpaid / Part paid)
A9: 46023 | B9: =COUNTIFS('Chemical Clearances'!$M$5:$M$169,">="&$A9,'Chemical Clearances'!$M$5:$M$169,"<="&EOMONTH($A9,0)) -> 7 | C9: =SUMIFS('Chemical Clearances'!$J$5:$J$169,'Chemical Clearances'!$M$5:$M$169,">="&$A9,'Chemical Clearances'!$M$5:$M$169,"<="&EOMONTH($A9,0)) -> 655.223 | D9: =COUNTIFS('Payments & Receipts'!$G$5:$G$58,">="&$A9,'Payments & Receipts'!$G$5:$G$58,"<="&EOMONTH($A9,0)) -> 14 | E9: =SUMIFS('Payments & Receipts'!$F$5:$F$58,'Payments & Receipts'!$G$5:$G$58,">="&$A9,'Payments & Receipts'!$G$5:$G$58,"<="&EOMONTH($A9,0)) -> 254776 | F9: =SUMIFS('Bills & Invoices'!$J$5:$J$32,'Bills & Invoices'!$K$5:$K$32,">="&$A9,'Bills & Invoices'!$K$5:$K$32,"<="&EOMONTH($A9,0)) -> 267376 | G9: =COUNTIFS('Licences & Certificates'!$L$5:$L$73,">="&$A9,'Licences & Certificates'!$L$5:$L$73,"<="&EOMONTH($A9,0)) -> 33 | J9: Chemical Registration (CRL) | K9: =COUNTIFS('Licences & Certificates'!$E$5:$E$73,$J9) -> 25 | L9: =COUNTIFS('Licences & Certificates'!$E$5:$E$73,$J9,'Licences & Certificates'!$N$5:$N$73,L$8) -> 5 | M9: =COUNTIFS('Licences & Certificates'!$E$5:$E$73,$J9,'Licences & Certificates'!$N$5:$N$73,M$8) -> 14 | N9: =COUNTIFS('Licences & Certificates'!$E$5:$E$73,$J9,'Licences & Certificates'!$N$5:$N$73,N$8) -> 6 | P9: Bill No. | Q9: Company | R9: Bill Date | S9: Billed (USD) | T9: Paid on bill | U9: Status
A10: =EDATE(A9,1) -> 46054 | B10: =COUNTIFS('Chemical Clearances'!$M$5:$M$169,">="&$A10,'Chemical Clearances'!$M$5:$M$169,"<="&EOMONTH($A10,0)) -> 54 | C10: =SUMIFS('Chemical Clearances'!$J$5:$J$169,'Chemical Clearances'!$M$5:$M$169,">="&$A10,'Chemical Clearances'!$M$5:$M$169,"<="&EOMONTH($A10,0)) -> 3232.8228 | D10: =COUNTIFS('Payments & Receipts'!$G$5:$G$58,">="&$A10,'Payments & Receipts'!$G$5:$G$58,"<="&EOMONTH($A10,0)) -> 8 | E10: =SUMIFS('Payments & Receipts'!$F$5:$F$58,'Payments & Receipts'!$G$5:$G$58,">="&$A10,'Payments & Receipts'!$G$5:$G$58,"<="&EOMONTH($A10,0)) -> 88790 | F10: =SUMIFS('Bills & Invoices'!$J$5:$J$32,'Bills & Invoices'!$K$5:$K$32,">="&$A10,'Bills & Invoices'!$K$5:$K$32,"<="&EOMONTH($A10,0)) -> 6450 | G10: =COUNTIFS('Licences & Certificates'!$L$5:$L$73,">="&$A10,'Licences & Certificates'!$L$5:$L$73,"<="&EOMONTH($A10,0)) -> 0 | J10: Chemical Importation (CIL) | K10: =COUNTIFS('Licences & Certificates'!$E$5:$E$73,$J10) -> 23 | L10: =COUNTIFS('Licences & Certificates'!$E$5:$E$73,$J10,'Licences & Certificates'!$N$5:$N$73,L$8) -> 17 | M10: =COUNTIFS('Licences & Certificates'!$E$5:$E$73,$J10,'Licences & Certificates'!$N$5:$N$73,M$8) -> 5 | N10: =COUNTIFS('Licences & Certificates'!$E$5:$E$73,$J10,'Licences & Certificates'!$N$5:$N$73,N$8) -> 1 | P10: =IFERROR(__xludf.DUMMYFUNCTION("IFERROR(FILTER(CHOOSECOLS(Lists!X5:AD404,1,3,4,5,6,7),(Lists!AD5:AD404=""Unpaid"")+(Lists!AD5:AD404=""Part paid"")),""No outstanding bills"")"),"BN-2026-019") -> BN-2026-019 | Q10: =IFERROR(__xludf.DUMMYFUNCTION("""COMPUTED_VALUE"""),"REAT Liberia") -> REAT Liberia | R10: =IFERROR(__xludf.DUMMYFUNCTION("""COMPUTED_VALUE"""),46064.0) -> 46064 | S10: =IFERROR(__xludf.DUMMYFUNCTION("""COMPUTED_VALUE"""),1500.0) -> 1500 | T10: =IFERROR(__xludf.DUMMYFUNCTION("""COMPUTED_VALUE"""),0.0) -> 0 | U10: =IFERROR(__xludf.DUMMYFUNCTION("""COMPUTED_VALUE"""),"Unpaid") -> Unpaid
A11: =EDATE(A10,1) -> 46082 | B11: =COUNTIFS('Chemical Clearances'!$M$5:$M$169,">="&$A11,'Chemical Clearances'!$M$5:$M$169,"<="&EOMONTH($A11,0)) -> 13 | C11: =SUMIFS('Chemical Clearances'!$J$5:$J$169,'Chemical Clearances'!$M$5:$M$169,">="&$A11,'Chemical Clearances'!$M$5:$M$169,"<="&EOMONTH($A11,0)) -> 2135.476 | D11: =COUNTIFS('Payments & Receipts'!$G$5:$G$58,">="&$A11,'Payments & Receipts'!$G$5:$G$58,"<="&EOMONTH($A11,0)) -> 8 | E11: =SUMIFS('Payments & Receipts'!$F$5:$F$58,'Payments & Receipts'!$G$5:$G$58,">="&$A11,'Payments & Receipts'!$G$5:$G$58,"<="&EOMONTH($A11,0)) -> 22311 | F11: =SUMIFS('Bills & Invoices'!$J$5:$J$32,'Bills & Invoices'!$K$5:$K$32,">="&$A11,'Bills & Invoices'!$K$5:$K$32,"<="&EOMONTH($A11,0)) -> 0 | G11: =COUNTIFS('Licences & Certificates'!$L$5:$L$73,">="&$A11,'Licences & Certificates'!$L$5:$L$73,"<="&EOMONTH($A11,0)) -> 0 | J11: Effluent Discharge (EDL) | K11: =COUNTIFS('Licences & Certificates'!$E$5:$E$73,$J11) -> 12 | L11: =COUNTIFS('Licences & Certificates'!$E$5:$E$73,$J11,'Licences & Certificates'!$N$5:$N$73,L$8) -> 1 | M11: =COUNTIFS('Licences & Certificates'!$E$5:$E$73,$J11,'Licences & Certificates'!$N$5:$N$73,M$8) -> 9 | N11: =COUNTIFS('Licences & Certificates'!$E$5:$E$73,$J11,'Licences & Certificates'!$N$5:$N$73,N$8) -> 2 | P11: =IFERROR(__xludf.DUMMYFUNCTION("""COMPUTED_VALUE"""),"BN-2026-017") -> BN-2026-017 | Q11: =IFERROR(__xludf.DUMMYFUNCTION("""COMPUTED_VALUE"""),"Kwado Energy") -> Kwado Energy | R11: =IFERROR(__xludf.DUMMYFUNCTION("""COMPUTED_VALUE"""),46065.0) -> 46065 | S11: =IFERROR(__xludf.DUMMYFUNCTION("""COMPUTED_VALUE"""),1500.0) -> 1500 | T11: =IFERROR(__xludf.DUMMYFUNCTION("""COMPUTED_VALUE"""),0.0) -> 0 | U11: =IFERROR(__xludf.DUMMYFUNCTION("""COMPUTED_VALUE"""),"Unpaid") -> Unpaid
A12: =EDATE(A11,1) -> 46113 | B12: =COUNTIFS('Chemical Clearances'!$M$5:$M$169,">="&$A12,'Chemical Clearances'!$M$5:$M$169,"<="&EOMONTH($A12,0)) -> 24 | C12: =SUMIFS('Chemical Clearances'!$J$5:$J$169,'Chemical Clearances'!$M$5:$M$169,">="&$A12,'Chemical Clearances'!$M$5:$M$169,"<="&EOMONTH($A12,0)) -> 1286.378 | D12: =COUNTIFS('Payments & Receipts'!$G$5:$G$58,">="&$A12,'Payments & Receipts'!$G$5:$G$58,"<="&EOMONTH($A12,0)) -> 4 | E12: =SUMIFS('Payments & Receipts'!$F$5:$F$58,'Payments & Receipts'!$G$5:$G$58,">="&$A12,'Payments & Receipts'!$G$5:$G$58,"<="&EOMONTH($A12,0)) -> 4925 | F12: =SUMIFS('Bills & Invoices'!$J$5:$J$32,'Bills & Invoices'!$K$5:$K$32,">="&$A12,'Bills & Invoices'!$K$5:$K$32,"<="&EOMONTH($A12,0)) -> 0 | G12: =COUNTIFS('Licences & Certificates'!$L$5:$L$73,">="&$A12,'Licences & Certificates'!$L$5:$L$73,"<="&EOMONTH($A12,0)) -> 0 | J12: Dewatering & Sedimentation Pond | K12: =COUNTIFS('Licences & Certificates'!$E$5:$E$73,$J12) -> 2 | L12: =COUNTIFS('Licences & Certificates'!$E$5:$E$73,$J12,'Licences & Certificates'!$N$5:$N$73,L$8) -> 2 | M12: =COUNTIFS('Licences & Certificates'!$E$5:$E$73,$J12,'Licences & Certificates'!$N$5:$N$73,M$8) -> 0 | N12: =COUNTIFS('Licences & Certificates'!$E$5:$E$73,$J12,'Licences & Certificates'!$N$5:$N$73,N$8) -> 0 | P12: =IFERROR(__xludf.DUMMYFUNCTION("""COMPUTED_VALUE"""),"BN-2026-011") -> BN-2026-011 | Q12: =IFERROR(__xludf.DUMMYFUNCTION("""COMPUTED_VALUE"""),"Liberia Soap and Detergent Company") -> Liberia Soap and Detergent Company | R12: =IFERROR(__xludf.DUMMYFUNCTION("""COMPUTED_VALUE"""),46048.0) -> 46048 | S12: =IFERROR(__xludf.DUMMYFUNCTION("""COMPUTED_VALUE"""),7550.0) -> 7550 | T12: =IFERROR(__xludf.DUMMYFUNCTION("""COMPUTED_VALUE"""),0.0) -> 0 | U12: =IFERROR(__xludf.DUMMYFUNCTION("""COMPUTED_VALUE"""),"Unpaid") -> Unpaid
A13: =EDATE(A12,1) -> 46143 | B13: =COUNTIFS('Chemical Clearances'!$M$5:$M$169,">="&$A13,'Chemical Clearances'!$M$5:$M$169,"<="&EOMONTH($A13,0)) -> 18 | C13: =SUMIFS('Chemical Clearances'!$J$5:$J$169,'Chemical Clearances'!$M$5:$M$169,">="&$A13,'Chemical Clearances'!$M$5:$M$169,"<="&EOMONTH($A13,0)) -> 653.9035 | D13: =COUNTIFS('Payments & Receipts'!$G$5:$G$58,">="&$A13,'Payments & Receipts'!$G$5:$G$58,"<="&EOMONTH($A13,0)) -> 6 | E13: =SUMIFS('Payments & Receipts'!$F$5:$F$58,'Payments & Receipts'!$G$5:$G$58,">="&$A13,'Payments & Receipts'!$G$5:$G$58,"<="&EOMONTH($A13,0)) -> 13325 | F13: =SUMIFS('Bills & Invoices'!$J$5:$J$32,'Bills & Invoices'!$K$5:$K$32,">="&$A13,'Bills & Invoices'!$K$5:$K$32,"<="&EOMONTH($A13,0)) -> 0 | G13: =COUNTIFS('Licences & Certificates'!$L$5:$L$73,">="&$A13,'Licences & Certificates'!$L$5:$L$73,"<="&EOMONTH($A13,0)) -> 0 | J13: Fumigation | K13: =COUNTIFS('Licences & Certificates'!$E$5:$E$73,$J13) -> 1 | L13: =COUNTIFS('Licences & Certificates'!$E$5:$E$73,$J13,'Licences & Certificates'!$N$5:$N$73,L$8) -> 1 | M13: =COUNTIFS('Licences & Certificates'!$E$5:$E$73,$J13,'Licences & Certificates'!$N$5:$N$73,M$8) -> 0 | N13: =COUNTIFS('Licences & Certificates'!$E$5:$E$73,$J13,'Licences & Certificates'!$N$5:$N$73,N$8) -> 0 | P13: =IFERROR(__xludf.DUMMYFUNCTION("""COMPUTED_VALUE"""),"BN-2026-010") -> BN-2026-010 | Q13: =IFERROR(__xludf.DUMMYFUNCTION("""COMPUTED_VALUE"""),"Fouani Brothers") -> Fouani Brothers | R13: =IFERROR(__xludf.DUMMYFUNCTION("""COMPUTED_VALUE"""),46048.0) -> 46048 | S13: =IFERROR(__xludf.DUMMYFUNCTION("""COMPUTED_VALUE"""),3000.0) -> 3000 | T13: =IFERROR(__xludf.DUMMYFUNCTION("""COMPUTED_VALUE"""),0.0) -> 0 | U13: =IFERROR(__xludf.DUMMYFUNCTION("""COMPUTED_VALUE"""),"Unpaid") -> Unpaid
A14: =EDATE(A13,1) -> 46174 | B14: =COUNTIFS('Chemical Clearances'!$M$5:$M$169,">="&$A14,'Chemical Clearances'!$M$5:$M$169,"<="&EOMONTH($A14,0)) -> 7 | C14: =SUMIFS('Chemical Clearances'!$J$5:$J$169,'Chemical Clearances'!$M$5:$M$169,">="&$A14,'Chemical Clearances'!$M$5:$M$169,"<="&EOMONTH($A14,0)) -> 457.264 | D14: =COUNTIFS('Payments & Receipts'!$G$5:$G$58,">="&$A14,'Payments & Receipts'!$G$5:$G$58,"<="&EOMONTH($A14,0)) -> 3 | E14: =SUMIFS('Payments & Receipts'!$F$5:$F$58,'Payments & Receipts'!$G$5:$G$58,">="&$A14,'Payments & Receipts'!$G$5:$G$58,"<="&EOMONTH($A14,0)) -> 10275 | F14: =SUMIFS('Bills & Invoices'!$J$5:$J$32,'Bills & Invoices'!$K$5:$K$32,">="&$A14,'Bills & Invoices'!$K$5:$K$32,"<="&EOMONTH($A14,0)) -> 0 | G14: =COUNTIFS('Licences & Certificates'!$L$5:$L$73,">="&$A14,'Licences & Certificates'!$L$5:$L$73,"<="&EOMONTH($A14,0)) -> 0 | J14: Chemical Transportation | K14: =COUNTIFS('Licences & Certificates'!$E$5:$E$73,$J14) -> 6 | L14: =COUNTIFS('Licences & Certificates'!$E$5:$E$73,$J14,'Licences & Certificates'!$N$5:$N$73,L$8) -> 6 | M14: =COUNTIFS('Licences & Certificates'!$E$5:$E$73,$J14,'Licences & Certificates'!$N$5:$N$73,M$8) -> 0 | N14: =COUNTIFS('Licences & Certificates'!$E$5:$E$73,$J14,'Licences & Certificates'!$N$5:$N$73,N$8) -> 0 | P14: =IFERROR(__xludf.DUMMYFUNCTION("""COMPUTED_VALUE"""),"BN-2026-006") -> BN-2026-006 | Q14: =IFERROR(__xludf.DUMMYFUNCTION("""COMPUTED_VALUE"""),"T Waste Recycling & Fumigation Inc.") -> T Waste Recycling & Fumigation Inc. | R14: =IFERROR(__xludf.DUMMYFUNCTION("""COMPUTED_VALUE"""),46036.0) -> 46036 | S14: =IFERROR(__xludf.DUMMYFUNCTION("""COMPUTED_VALUE"""),275.0) -> 275 | T14: =IFERROR(__xludf.DUMMYFUNCTION("""COMPUTED_VALUE"""),0.0) -> 0 | U14: =IFERROR(__xludf.DUMMYFUNCTION("""COMPUTED_VALUE"""),"Unpaid") -> Unpaid
A15: =EDATE(A14,1) -> 46204 | B15: =COUNTIFS('Chemical Clearances'!$M$5:$M$169,">="&$A15,'Chemical Clearances'!$M$5:$M$169,"<="&EOMONTH($A15,0)) -> 10 | C15: =SUMIFS('Chemical Clearances'!$J$5:$J$169,'Chemical Clearances'!$M$5:$M$169,">="&$A15,'Chemical Clearances'!$M$5:$M$169,"<="&EOMONTH($A15,0)) -> 1015.841 | D15: =COUNTIFS('Payments & Receipts'!$G$5:$G$58,">="&$A15,'Payments & Receipts'!$G$5:$G$58,"<="&EOMONTH($A15,0)) -> 4 | E15: =SUMIFS('Payments & Receipts'!$F$5:$F$58,'Payments & Receipts'!$G$5:$G$58,">="&$A15,'Payments & Receipts'!$G$5:$G$58,"<="&EOMONTH($A15,0)) -> 8435 | F15: =SUMIFS('Bills & Invoices'!$J$5:$J$32,'Bills & Invoices'!$K$5:$K$32,">="&$A15,'Bills & Invoices'!$K$5:$K$32,"<="&EOMONTH($A15,0)) -> 0 | G15: =COUNTIFS('Licences & Certificates'!$L$5:$L$73,">="&$A15,'Licences & Certificates'!$L$5:$L$73,"<="&EOMONTH($A15,0)) -> 0 | J15: TOTAL | K15: =SUM(K9:K14) -> 69 | L15: =SUM(L9:L14) -> 32 | M15: =SUM(M9:M14) -> 28 | N15: =SUM(N9:N14) -> 9 | P15: =IFERROR(__xludf.DUMMYFUNCTION("""COMPUTED_VALUE"""),"BN-2026-005") -> BN-2026-005 | Q15: =IFERROR(__xludf.DUMMYFUNCTION("""COMPUTED_VALUE"""),"Efficient Professional Services Inc.") -> Efficient Professional Services Inc. | R15: =IFERROR(__xludf.DUMMYFUNCTION("""COMPUTED_VALUE"""),46043.0) -> 46043 | S15: =IFERROR(__xludf.DUMMYFUNCTION("""COMPUTED_VALUE"""),275.0) -> 275 | T15: =IFERROR(__xludf.DUMMYFUNCTION("""COMPUTED_VALUE"""),0.0) -> 0 | U15: =IFERROR(__xludf.DUMMYFUNCTION("""COMPUTED_VALUE"""),"Unpaid") -> Unpaid
A16: =EDATE(A15,1) -> 46235 | B16: =COUNTIFS('Chemical Clearances'!$M$5:$M$169,">="&$A16,'Chemical Clearances'!$M$5:$M$169,"<="&EOMONTH($A16,0)) -> 3 | C16: =SUMIFS('Chemical Clearances'!$J$5:$J$169,'Chemical Clearances'!$M$5:$M$169,">="&$A16,'Chemical Clearances'!$M$5:$M$169,"<="&EOMONTH($A16,0)) -> 764.158 | D16: =COUNTIFS('Payments & Receipts'!$G$5:$G$58,">="&$A16,'Payments & Receipts'!$G$5:$G$58,"<="&EOMONTH($A16,0)) -> 2 | E16: =SUMIFS('Payments & Receipts'!$F$5:$F$58,'Payments & Receipts'!$G$5:$G$58,">="&$A16,'Payments & Receipts'!$G$5:$G$58,"<="&EOMONTH($A16,0)) -> 12455 | F16: =SUMIFS('Bills & Invoices'!$J$5:$J$32,'Bills & Invoices'!$K$5:$K$32,">="&$A16,'Bills & Invoices'!$K$5:$K$32,"<="&EOMONTH($A16,0)) -> 0 | G16: =COUNTIFS('Licences & Certificates'!$L$5:$L$73,">="&$A16,'Licences & Certificates'!$L$5:$L$73,"<="&EOMONTH($A16,0)) -> 0 | P16: =IFERROR(__xludf.DUMMYFUNCTION("""COMPUTED_VALUE"""),"BN-2026-003") -> BN-2026-003 | Q16: =IFERROR(__xludf.DUMMYFUNCTION("""COMPUTED_VALUE"""),"Mano Manufacturing Company (MANCO)") -> Mano Manufacturing Company (MANCO) | R16: =IFERROR(__xludf.DUMMYFUNCTION("""COMPUTED_VALUE"""),46030.0) -> 46030 | S16: =IFERROR(__xludf.DUMMYFUNCTION("""COMPUTED_VALUE"""),1500.0) -> 1500 | T16: =IFERROR(__xludf.DUMMYFUNCTION("""COMPUTED_VALUE"""),0.0) -> 0 | U16: =IFERROR(__xludf.DUMMYFUNCTION("""COMPUTED_VALUE"""),"Unpaid") -> Unpaid
A17: =EDATE(A16,1) -> 46266 | B17: =COUNTIFS('Chemical Clearances'!$M$5:$M$169,">="&$A17,'Chemical Clearances'!$M$5:$M$169,"<="&EOMONTH($A17,0)) -> 11 | C17: =SUMIFS('Chemical Clearances'!$J$5:$J$169,'Chemical Clearances'!$M$5:$M$169,">="&$A17,'Chemical Clearances'!$M$5:$M$169,"<="&EOMONTH($A17,0)) -> 2482.2512 | D17: =COUNTIFS('Payments & Receipts'!$G$5:$G$58,">="&$A17,'Payments & Receipts'!$G$5:$G$58,"<="&EOMONTH($A17,0)) -> 3 | E17: =SUMIFS('Payments & Receipts'!$F$5:$F$58,'Payments & Receipts'!$G$5:$G$58,">="&$A17,'Payments & Receipts'!$G$5:$G$58,"<="&EOMONTH($A17,0)) -> 7541 | F17: =SUMIFS('Bills & Invoices'!$J$5:$J$32,'Bills & Invoices'!$K$5:$K$32,">="&$A17,'Bills & Invoices'!$K$5:$K$32,"<="&EOMONTH($A17,0)) -> 0 | G17: =COUNTIFS('Licences & Certificates'!$L$5:$L$73,">="&$A17,'Licences & Certificates'!$L$5:$L$73,"<="&EOMONTH($A17,0)) -> 0 | J17: BILLS – PAYMENT STATUS | P17: =IFERROR(__xludf.DUMMYFUNCTION("""COMPUTED_VALUE"""),"BN-2026-001") -> BN-2026-001 | Q17: =IFERROR(__xludf.DUMMYFUNCTION("""COMPUTED_VALUE"""),"Delta Plastics Inc.") -> Delta Plastics Inc. | R17: =IFERROR(__xludf.DUMMYFUNCTION("""COMPUTED_VALUE"""),46030.0) -> 46030 | S17: =IFERROR(__xludf.DUMMYFUNCTION("""COMPUTED_VALUE"""),1500.0) -> 1500 | T17: =IFERROR(__xludf.DUMMYFUNCTION("""COMPUTED_VALUE"""),0.0) -> 0 | U17: =IFERROR(__xludf.DUMMYFUNCTION("""COMPUTED_VALUE"""),"Unpaid") -> Unpaid
A18: =EDATE(A17,1) -> 46296 | B18: =COUNTIFS('Chemical Clearances'!$M$5:$M$169,">="&$A18,'Chemical Clearances'!$M$5:$M$169,"<="&EOMONTH($A18,0)) -> 0 | C18: =SUMIFS('Chemical Clearances'!$J$5:$J$169,'Chemical Clearances'!$M$5:$M$169,">="&$A18,'Chemical Clearances'!$M$5:$M$169,"<="&EOMONTH($A18,0)) -> 0 | D18: =COUNTIFS('Payments & Receipts'!$G$5:$G$58,">="&$A18,'Payments & Receipts'!$G$5:$G$58,"<="&EOMONTH($A18,0)) -> 0 | E18: =SUMIFS('Payments & Receipts'!$F$5:$F$58,'Payments & Receipts'!$G$5:$G$58,">="&$A18,'Payments & Receipts'!$G$5:$G$58,"<="&EOMONTH($A18,0)) -> 0 | F18: =SUMIFS('Bills & Invoices'!$J$5:$J$32,'Bills & Invoices'!$K$5:$K$32,">="&$A18,'Bills & Invoices'!$K$5:$K$32,"<="&EOMONTH($A18,0)) -> 0 | G18: =COUNTIFS('Licences & Certificates'!$L$5:$L$73,">="&$A18,'Licences & Certificates'!$L$5:$L$73,"<="&EOMONTH($A18,0)) -> 0 | J18: Payment Status | K18: Bills (No.) | L18: Amount Billed (USD)
A19: =EDATE(A18,1) -> 46327 | B19: =COUNTIFS('Chemical Clearances'!$M$5:$M$169,">="&$A19,'Chemical Clearances'!$M$5:$M$169,"<="&EOMONTH($A19,0)) -> 0 | C19: =SUMIFS('Chemical Clearances'!$J$5:$J$169,'Chemical Clearances'!$M$5:$M$169,">="&$A19,'Chemical Clearances'!$M$5:$M$169,"<="&EOMONTH($A19,0)) -> 0 | D19: =COUNTIFS('Payments & Receipts'!$G$5:$G$58,">="&$A19,'Payments & Receipts'!$G$5:$G$58,"<="&EOMONTH($A19,0)) -> 0 | E19: =SUMIFS('Payments & Receipts'!$F$5:$F$58,'Payments & Receipts'!$G$5:$G$58,">="&$A19,'Payments & Receipts'!$G$5:$G$58,"<="&EOMONTH($A19,0)) -> 0 | F19: =SUMIFS('Bills & Invoices'!$J$5:$J$32,'Bills & Invoices'!$K$5:$K$32,">="&$A19,'Bills & Invoices'!$K$5:$K$32,"<="&EOMONTH($A19,0)) -> 0 | G19: =COUNTIFS('Licences & Certificates'!$L$5:$L$73,">="&$A19,'Licences & Certificates'!$L$5:$L$73,"<="&EOMONTH($A19,0)) -> 0 | J19: Paid | K19: =COUNTIFS('Bills & Invoices'!$N$5:$N$32,$J19) -> 15 | L19: =SUMIFS('Bills & Invoices'!$J$5:$J$32,'Bills & Invoices'!$N$5:$N$32,$J19) -> 257501
A20: =EDATE(A19,1) -> 46357 | B20: =COUNTIFS('Chemical Clearances'!$M$5:$M$169,">="&$A20,'Chemical Clearances'!$M$5:$M$169,"<="&EOMONTH($A20,0)) -> 0 | C20: =SUMIFS('Chemical Clearances'!$J$5:$J$169,'Chemical Clearances'!$M$5:$M$169,">="&$A20,'Chemical Clearances'!$M$5:$M$169,"<="&EOMONTH($A20,0)) -> 0 | D20: =COUNTIFS('Payments & Receipts'!$G$5:$G$58,">="&$A20,'Payments & Receipts'!$G$5:$G$58,"<="&EOMONTH($A20,0)) -> 0 | E20: =SUMIFS('Payments & Receipts'!$F$5:$F$58,'Payments & Receipts'!$G$5:$G$58,">="&$A20,'Payments & Receipts'!$G$5:$G$58,"<="&EOMONTH($A20,0)) -> 0 | F20: =SUMIFS('Bills & Invoices'!$J$5:$J$32,'Bills & Invoices'!$K$5:$K$32,">="&$A20,'Bills & Invoices'!$K$5:$K$32,"<="&EOMONTH($A20,0)) -> 0 | G20: =COUNTIFS('Licences & Certificates'!$L$5:$L$73,">="&$A20,'Licences & Certificates'!$L$5:$L$73,"<="&EOMONTH($A20,0)) -> 0 | J20: Part paid | K20: =COUNTIFS('Bills & Invoices'!$N$5:$N$32,$J20) -> 2 | L20: =SUMIFS('Bills & Invoices'!$J$5:$J$32,'Bills & Invoices'!$N$5:$N$32,$J20) -> 4550
A21: Date not recorded | B21: =COUNTIFS('Chemical Clearances'!$M$5:$M$169,"") -> 18 | C21: =SUMIFS('Chemical Clearances'!$J$5:$J$169,'Chemical Clearances'!$M$5:$M$169,"") -> 3096.664 | D21: =COUNTIFS('Payments & Receipts'!$G$5:$G$58,"") -> 2 | E21: =SUMIFS('Payments & Receipts'!$F$5:$F$58,'Payments & Receipts'!$G$5:$G$58,"") -> 12150 | F21: =SUMIFS('Bills & Invoices'!$J$5:$J$32,'Bills & Invoices'!$K$5:$K$32,"") -> 5325 | G21: =COUNTIFS('Licences & Certificates'!$L$5:$L$73,"",'Licences & Certificates'!$K$5:$K$73,"<>") -> 27 | J21: No payment on record | K21: =COUNTIFS('Bills & Invoices'!$N$5:$N$32,$J21) -> 11 | L21: =SUMIFS('Bills & Invoices'!$J$5:$J$32,'Bills & Invoices'!$N$5:$N$32,$J21) -> 17100
A22: TOTAL | B22: =SUM(B9:B21) -> 165 | C22: =SUM(C9:C21) -> 15779.981 | D22: =SUM(D9:D21) -> 54 | E22: =SUM(E9:E21) -> 434983 | F22: =SUM(F9:F21) -> 279151 | G22: =SUM(G9:G21) -> 60 | J22: TOTAL | K22: =SUM(K19:K21) -> 28 | L22: =SUM(L19:L21) -> 279151
A23: Check vs registers (should be 0) | B23: =B22-ROWS('Chemical Clearances'!$A$5:$A$169) -> 0 | C23: =ROUND(C22-SUM('Chemical Clearances'!$J$5:$J$169),3) -> 0 | D23: =D22-ROWS('Payments & Receipts'!$A$5:$A$58) -> 0 | E23: =E22-SUM('Payments & Receipts'!$F$5:$F$58) -> 0 | F23: =F22-SUM('Bills & Invoices'!$J$5:$J$32) -> 0
A25: CLEARANCES BY CHEMICAL (standardised names)
A26: Chemical (Standard) | B26: Shipments (No.) | C26: Qty (kg) | D26: Qty (MT) | E26: % of Total kg
A27: Ferric Chloride | B27: =COUNTIFS('Chemical Clearances'!$F$5:$F$169,$A27) -> 10 | C27: =SUMIFS('Chemical Clearances'!$I$5:$I$169,'Chemical Clearances'!$F$5:$F$169,$A27) -> 3308166 | D27: =C27/1000 -> 3308.166 | E27: =IF(SUM('Chemical Clearances'!$I$5:$I$169)=0,0,C27/SUM('Chemical Clearances'!$I$5:$I$169)) -> 0.20964321
A28: Explosives (Emulsion) | B28: =COUNTIFS('Chemical Clearances'!$F$5:$F$169,$A28) -> 6 | C28: =SUMIFS('Chemical Clearances'!$I$5:$I$169,'Chemical Clearances'!$F$5:$F$169,$A28) -> 2338291 | D28: =C28/1000 -> 2338.291 | E28: =IF(SUM('Chemical Clearances'!$I$5:$I$169)=0,0,C28/SUM('Chemical Clearances'!$I$5:$I$169)) -> 0.14818085
A29: Sodium Cyanide | B29: =COUNTIFS('Chemical Clearances'!$F$5:$F$169,$A29) -> 4 | C29: =SUMIFS('Chemical Clearances'!$I$5:$I$169,'Chemical Clearances'!$F$5:$F$169,$A29) -> 1937500 | D29: =C29/1000 -> 1937.5 | E29: =IF(SUM('Chemical Clearances'!$I$5:$I$169)=0,0,C29/SUM('Chemical Clearances'!$I$5:$I$169)) -> 0.12278215
A30: Akshot 160 (Alkali Curing Accelerator) | B30: =COUNTIFS('Chemical Clearances'!$F$5:$F$169,$A30) -> 10 | C30: =SUMIFS('Chemical Clearances'!$I$5:$I$169,'Chemical Clearances'!$F$5:$F$169,$A30) -> 1211138 | D30: =C30/1000 -> 1211.138 | E30: =IF(SUM('Chemical Clearances'!$I$5:$I$169)=0,0,C30/SUM('Chemical Clearances'!$I$5:$I$169)) -> 0.076751548
A31: Sodium Metabisulphite (SMBS) | B31: =COUNTIFS('Chemical Clearances'!$F$5:$F$169,$A31) -> 9 | C31: =SUMIFS('Chemical Clearances'!$I$5:$I$169,'Chemical Clearances'!$F$5:$F$169,$A31) -> 1146800 | D31: =C31/1000 -> 1146.8 | E31: =IF(SUM('Chemical Clearances'!$I$5:$I$169)=0,0,C31/SUM('Chemical Clearances'!$I$5:$I$169)) -> 0.072674357
A32: Polymers (PE / PP) | B32: =COUNTIFS('Chemical Clearances'!$F$5:$F$169,$A32) -> 10 | C32: =SUMIFS('Chemical Clearances'!$I$5:$I$169,'Chemical Clearances'!$F$5:$F$169,$A32) -> 1013149 | D32: =C32/1000 -> 1013.149 | E32: =IF(SUM('Chemical Clearances'!$I$5:$I$169)=0,0,C32/SUM('Chemical Clearances'!$I$5:$I$169)) -> 0.064204702
A33: Methyltrialkyl Ammonium Chloride | B33: =COUNTIFS('Chemical Clearances'!$F$5:$F$169,$A33) -> 1 | C33: =SUMIFS('Chemical Clearances'!$I$5:$I$169,'Chemical Clearances'!$F$5:$F$169,$A33) -> 860000 | D33: =C33/1000 -> 860 | E33: =IF(SUM('Chemical Clearances'!$I$5:$I$169)=0,0,C33/SUM('Chemical Clearances'!$I$5:$I$169)) -> 0.05449943
A34: Paint & Coatings | B34: =COUNTIFS('Chemical Clearances'!$F$5:$F$169,$A34) -> 4 | C34: =SUMIFS('Chemical Clearances'!$I$5:$I$169,'Chemical Clearances'!$F$5:$F$169,$A34) -> 628256.8 | D34: =C34/1000 -> 628.2568 | E34: =IF(SUM('Chemical Clearances'!$I$5:$I$169)=0,0,C34/SUM('Chemical Clearances'!$I$5:$I$169)) -> 0.039813532
A35: Caustic Soda (Sodium Hydroxide) | B35: =COUNTIFS('Chemical Clearances'!$F$5:$F$169,$A35) -> 14 | C35: =SUMIFS('Chemical Clearances'!$I$5:$I$169,'Chemical Clearances'!$F$5:$F$169,$A35) -> 744260 | D35: =C35/1000 -> 744.26 | E35: =IF(SUM('Chemical Clearances'!$I$5:$I$169)=0,0,C35/SUM('Chemical Clearances'!$I$5:$I$169)) -> 0.047164821
A36: Activated Carbon | B36: =COUNTIFS('Chemical Clearances'!$F$5:$F$169,$A36) -> 4 | C36: =SUMIFS('Chemical Clearances'!$I$5:$I$169,'Chemical Clearances'!$F$5:$F$169,$A36) -> 568175.7 | D36: =C36/1000 -> 568.1757 | E36: =IF(SUM('Chemical Clearances'!$I$5:$I$169)=0,0,C36/SUM('Chemical Clearances'!$I$5:$I$169)) -> 0.036006107
A37: Hydrated Lime | B37: =COUNTIFS('Chemical Clearances'!$F$5:$F$169,$A37) -> 2 | C37: =SUMIFS('Chemical Clearances'!$I$5:$I$169,'Chemical Clearances'!$F$5:$F$169,$A37) -> 501960 | D37: =C37/1000 -> 501.96 | E37: =IF(SUM('Chemical Clearances'!$I$5:$I$169)=0,0,C37/SUM('Chemical Clearances'!$I$5:$I$169)) -> 0.031809923
A38: Akhidralin (Shotcrete Fluidifier) | B38: =COUNTIFS('Chemical Clearances'!$F$5:$F$169,$A38) -> 3 | C38: =SUMIFS('Chemical Clearances'!$I$5:$I$169,'Chemical Clearances'!$F$5:$F$169,$A38) -> 191380 | D38: =C38/1000 -> 191.38 | E38: =IF(SUM('Chemical Clearances'!$I$5:$I$169)=0,0,C38/SUM('Chemical Clearances'!$I$5:$I$169)) -> 0.012128024
... A73: Magnesium Perchlorate | B73: =COUNTIFS('Chemical Clearances'!$F$5:$F$169,$A73) -> 1 | C73: =SUMIFS('Chemical Clearances'!$I$5:$I$169,'Chemical Clearances'!$F$5:$F$169,$A73) -> 6 | D73: =C73/1000 -> 0.006 | E73: =IF(SUM('Chemical Clearances'!$I$5:$I$169)=0,0,C73/SUM('Chemical Clearances'!$I$5:$I$169)) -> 3.8022858e-07
A74: TOTAL | B74: =SUM(B27:B73) -> 155 | C74: =SUM(C27:C73) -> 15406054 | D74: =SUM(D27:D73) -> 15406.054 | E74: =SUM(E27:E73) -> 0.97630371

Sheet Company Form
A1: ERRS – CHEMICAL MANAGEMENT UNIT | COMPANY REGISTRATION FORM
A2: Yellow cells are inputs. * = required. To edit: type the ID in row 5 and click Find, change fields, then click Update. Leave the ID blank and click Save New for a new record.
B4: FORM STATUS | C4: =IF(IF(C6="","Company Name; ","")="","✔ Ready to save","✖ Missing: "&IF(C6="","Company Name; ","")) -> ✖ Missing: Company Name;
B5: Company ID | D5: {="Leave blank for a NEW record (next ID: "&"CMU-"&TEXT(SUMPRODUCT(MAX(--MID(Companies!$A$5:$A$74,5,4)))+1,"000")&"). Type an existing ID and click Find to edit."} -> Leave blank for a NEW record (next ID: CMU-071). Type an existing ID and click Find to edit.
B6: Company Name * | D6: =IF(C6="","Enter the official company name",IF(COUNTIF(Companies!$B$5:$B$74,C6)>0,"⚠ Already in register (OK only if updating)","✔ New company")) -> Enter the official company name
B7: Sector / Activity | D7: Choose from list (add new sectors on the Lists sheet)
B8: Location | D8: Street / town, county
B9: Other Names Recorded | C9: =IFERROR(__xludf.DUMMYFUNCTION("AI(""Fill an appropriate value for this cell based on the table context"")"),"") | D9: Other spellings used on documents, separated by ;

Sheet Licence Form
A1: ERRS – CHEMICAL MANAGEMENT UNIT | LICENCE & CERTIFICATE FORM
A2: Yellow cells are inputs. * = required. To edit: type the ID in row 5 and click Find, change fields, then click Update. Leave the ID blank and click Save New for a new record.
B4: FORM STATUS | C4: =IF(IF(C6="","Company; ","")&IF(C7="","Licence Category; ","")&IF(C8="","Licence / Certificate Type; ","")&IF(AND(C6<>"",COUNTIF(Companies!$B$5:$B$74,C6)=0),"Company not in register; ","")="","✔ Ready to save","✖ Missing: "&IF(C6="","Company; ","")&IF(C7="","Licence Category; ","")&IF(C8="","Licence / Certificate Type; ","")&IF(AND(C6<>"",COUNTIF(Companies!$B$5:$B$74,C6)=0),"Company not in register; ","")) -> ✖ Missing: Company; Licence Category; Licence / Certificate Type;
B5: Record ID | D5: {="Leave blank for a NEW record (next ID: "&"LIC-"&TEXT(SUMPRODUCT(MAX(--MID('Licences & Certificates'!$A$5:$A$73,5,4)))+1,"000")&"). Type an existing ID and click Find to edit."} -> Leave blank for a NEW record (next ID: LIC-071). Type an existing ID and click Find to edit.
B6: Company * | D6: {=IF(C6="","",IFERROR("ID: "&INDEX(Companies!$A$5:$A$74,MATCH(C6,Companies!$B$5:$B$74,0)),"⚠ Not in Company register – add it on the Company Form first"))}
B7: Licence Category * | D7: CRL / CIL / EDL / Dewatering / Fumigation / Transport
B8: Licence / Certificate Type * | D8: Choose the specific licence
B9: Location | D9: Site address
B10: Application Date | D10: dd-mmm-yyyy
B11: Response Date | D11: Date EPA responded
B12: Reference Code | D12: e.g. ED/EPA-01/075/26/RL
B13: Licence / Certificate No. | D13: =IF(C13="","Leave blank if not yet issued (status = Pending)",IF(COUNTIF('Licences & Certificates'!$K$5:$K$73,C13)>0,"⚠ This number already exists in the register","✔ Number not used before")) -> Leave blank if not yet issued (status = Pending)
B14: Date Issued | D14: dd-mmm-yyyy
B15: Expiry Date | D15: =IF(AND(C14<>"",C15<>"",C15<C14),"⚠ Expiry is before issue date","Usually 31-Dec-2026 for annual licences") -> Usually 31-Dec-2026 for annual licences
B16: Remarks
B18: CHEMICALS ON THIS LICENCE (CRL / CIL) – up to 15 lines, saved with Save New / Update and loaded by Find
B19: No. | C19: Trade or IUPAC Name | D19: EPA Registration No. | E19: Type | F19: Stipulated Qty (CIL) | G19: Unit (CIL) | H19: Consignment Ref. BL/IPD (CIL)
B20: 1
B21: 2
B22: 3
B23: 4
B24: 5
B25: 6
B26: 7
B27: 8
B28: 9
B29: 10
B30: 11
B31: 12
... B34: 15
B35: Lines | C35: =IF(COUNTA(C20:C34)=0,"No chemical lines entered",COUNTA(C20:C34)&" chemical line(s) will be saved with this licence")&IF(AND(COUNTA(C20:C34)>0,ISERROR(SEARCH("(CRL)",C7)),ISERROR(SEARCH("(CIL)",C7)))," ⚠ Category is not CRL or CIL","") -> No chemical lines entered | D35: CRL: Name, EPA Reg. No., Type. CIL: also Qty, Unit, Consignment Ref.
B37: EDL format ▶ | C37: =IF(ISERROR(SEARCH("EDL",C7)),"(only for Effluent Discharge licences)",IF(ISNUMBER(SEARCH("Retention",C8)),"EDL & RETENTION POND → prints on Print EDL RP (all tables below are used)","STANDARD EDL → prints on Print EDL (Retention Pond tables below are not used)"))&" To switch, change Licence / Certificate Type (C8): Effluent Discharge ⇄ Effluent Discharge & Retention Pond" -> (only for Effluent Discharge licences) To switch, change Licence / Certificate Type (C8): Effluent Discharge ⇄ Effluent Discharge & Retention Pond
B38: EFFLUENT DETAILS (EDL) – fill only for Effluent Discharge licences; saved with Save New / Update and loaded by Find
B39: Receiving water | E39: Used in Conditions 1–2 of the printed EDL, e.g. receiving water “the estuary”, volume “10”, discharge point “in a containment tank”.
B40: Max. volume (m³/day)
B41: Discharge point / facility
B43: DISCHARGE LIMITS – up to 20 lines. List ONLY the parameters this licence requires (pick from the list or type your own)
B44: No. | C44: Parameter | D44: Unit | E44: Limit | F44: Sample Type | G44: Testing Schedule | H44: Discharge Stage (Retention Pond only) e.g. Detox Unit I & II to TSF-II
B45: 1
B46: 2
B47: 3
B48: 4
B49: 5
B50: 6
B51: 7
B52: 8
B53: 9
B54: 10
B55: 11
B56: 12
... B64: 20
B65: Lines | C65: =IF(COUNTA(C45:C64)=0,"No limit lines entered",COUNTA(C45:C64)&" limit line(s)")&" | "&COUNTA(C69:C88)&" coordinate line(s) | "&COUNTA(C92:C97)&" source line(s)"&IF(AND(COUNTA(C39:C41,C45:C64,C69:C88,C92:C97)>0,ISERROR(SEARCH("EDL",C7)),ISERROR(SEARCH("Effluent",C7)))," ⚠ Category is not EDL – these details will still be saved","") -> No limit lines entered | 0 coordinate line(s) | 0 source line(s)
B67: RETENTION POND LICENCES ONLY – GEO-REFERENCE (Tables 1A / 1B): type 1A or 1B in the Table column, up to 20 lines
B68: No. | C68: Table (1A or 1B) | D68: Vertex | E68: Easting | F68: Northing
B69: 1
B70: 2
B71: 3
B72: 4
B73: 5
B74: 6
B75: 7
B76: 8
B77: 9
B78: 10
B79: 11
B80: 12
... B88: 20
B90: RETENTION POND LICENCES ONLY – DISCHARGE SOURCES (Table 1B source list & Table 2), up to 6 lines
B91: No. | C91: Discharge source | D91: Receiving unit | E91: X (Table 1B) | F91: Y (Table 1B)
B92: 1
B93: 2
B94: 3
B95: 4
B96: 5
B97: 6

Sheet Clearance Form
A1: ERRS – CHEMICAL MANAGEMENT UNIT | CHEMICAL CLEARANCE FORM (MULTI-CHEMICAL)
A2: One clearance = one Clearance No. (automatic) with up to 20 chemicals. Fill the details once, list the chemicals, click Save New. To edit: type the Clearance No., EPA Ref. No. or a CLR- ID in C5 and click Find.
B4: FORM STATUS | C4: {=IF(IF(C6="","Company; ","")&IF(AND(C6<>"",COUNTIF(Companies!$B$5:$B$74,C6)=0),"Company not in register; ","")&IF(C7="","Clearance Date; ","")&IF(SUMPRODUCT(--((C13:C32<>"")+(D13:D32<>"")>0))=0,"at least one chemical line; ","")&IF(SUMPRODUCT(((C13:C32<>"")+(D13:D32<>"")>0)*(((E13:E32="")+(F13:F32=""))>0))>0,"quantity or unit on "&SUMPRODUCT(((C13:C32<>"")+(D13:D32<>"")>0)*(((E13:E32="")+(F13:F32=""))>0))&" line(s); ","")&IF(SUMPRODUCT((1-((C13:C32<>"")+(D13:D32<>"")>0))*(((E13:E32<>"")+(F13:F32<>""))>0))>0,"chemical name on "&SUMPRODUCT((1-((C13:C32<>"")+(D13:D32<>"")>0))*(((E13:E32<>"")+(F13:F32<>""))>0))&" line(s); ","")&IF(SUMPRODUCT((E13:E32<>"")*NOT(ISNUMBER(E13:E32)))>0,"quantity not a number on "&SUMPRODUCT((E13:E32<>"")*NOT(ISNUMBER(E13:E32)))&" line(s); ","")="","✔ Ready to save – "&SUMPRODUCT(--((C13:C32<>"")+(D13:D32<>"")>0))&" chemical line(s)","✖ Missing: "&IF(C6="","Company; ","")&IF(AND(C6<>"",COUNTIF(Companies!$B$5:$B$74,C6)=0),"Company not in register; ","")&IF(C7="","Clearance Date; ","")&IF(SUMPRODUCT(--((C13:C32<>"")+(D13:D32<>"")>0))=0,"at least one chemical line; ","")&IF(SUMPRODUCT(((C13:C32<>"")+(D13:D32<>"")>0)*(((E13:E32="")+(F13:F32=""))>0))>0,"quantity or unit on "&SUMPRODUCT(((C13:C32<>"")+(D13:D32<>"")>0)*(((E13:E32="")+(F13:F32=""))>0))&" line(s); ","")&IF(SUMPRODUCT((1-((C13:C32<>"")+(D13:D32<>"")>0))*(((E13:E32<>"")+(F13:F32<>""))>0))>0,"chemical name on "&SUMPRODUCT((1-((C13:C32<>"")+(D13:D32<>"")>0))*(((E13:E32<>"")+(F13:F32<>""))>0))&" line(s); ","")&IF(SUMPRODUCT((E13:E32<>"")*NOT(ISNUMBER(E13:E32)))>0,"quantity not a number on "&SUMPRODUCT((E13:E32<>"")*NOT(ISNUMBER(E13:E32)))&" line(s); ",""))} -> ✖ Missing: Company; Clearance Date; at least one chemical line;
B5: Clearance No. | D5: {=IF(C5="","AUTO – leave blank for a new clearance (next: CLN-"&TEXT(MAX(IFERROR(--MID('Chemical Clearances'!$B$5:$B$169,5,4),0))+1,"000")&"). To edit, type a Clearance No. / EPA Ref. / CLR- ID and click Find.",IF(COUNTA(H13:H32)>0,"Loaded "&COUNTA(H13:H32)&" saved line(s) – edit, then click Update","Click Find by ID to load this clearance"))} -> AUTO – leave blank for a new clearance (next: CLN-148). To edit, type a Clearance No. / EPA Ref. / CLR- ID and click Find.
B6: Company * | D6: {=IF(C6="","Choose the company",IFERROR("ID: "&INDEX(Companies!$A$5:$A$74,MATCH(C6,Companies!$B$5:$B$74,0)),"⚠ Not in Company register – add it on the Company Form first"))} -> Choose the company
B7: Clearance Date * | D7: dd-mmm-yyyy
B8: EPA Ref. No. | D8: =IF(OR(C8="",COUNTA(H13:H32)>0),"EPA letter number, e.g. ED/EPA-01/388/26/RL (optional)",IF(COUNTIF('Chemical Clearances'!$L$5:$L$169,C8)>0,"⚠ This EPA Ref. No. is already in the register – check for duplicate","✔ New ref. no.")) -> EPA letter number, e.g. ED/EPA-01/388/26/RL (optional)
B9: B/L / Invoice / AWB No. | D9: =IF(OR(C9="",COUNTA(H13:H32)>0),"Default B/L for all lines – type a different one on a line in column G if needed",IF(COUNTIF('Chemical Clearances'!$K$5:$K$169,C9)>0,"⚠ This B/L is already in the register – check for duplicate","✔ New B/L")) -> Default B/L for all lines – type a different one on a line in column G if needed
B10: Remarks | D10: Applies to all lines
B11: ETA | D11: Estimated arrival – date or text (e.g. N/A). Printed on the clearance letter.
B12: Line | C12: Chemical as Recorded | D12: Chemical (Standard) | E12: Quantity * | F12: Unit * | G12: B/L / Invoice No. (blank = same as C9) | H12: Record ID
B13: 1
B14: 2
B15: 3
B16: 4
B17: 5
B18: 6
B19: 7
B20: 8
B21: 9
B22: 10
B23: 11
B24: 12
... B32: 20
F33: TOTAL kg | G33: {=SUMPRODUCT(--ISNUMBER(E13:E32),N(+E13:E32),(F13:F32="kg")+(F13:F32="MT")*1000)} -> 0 | H33: =TEXT(G33/1000,"#,##0.000")&" MT" -> 0.000 MT
B35: Tip: if Chemical as Recorded is blank, the Standard name is saved in its place. To remove a saved chemical, Find it, clear that whole line (C to F), then click Update.

Sheet Bill Form
A1: ERRS – CHEMICAL MANAGEMENT UNIT | BILL / INVOICE FORM (MULTI-SERVICE)
A2: One bill = one Bill No. (automatic) with up to 10 services. Fill the bill details once, list the services and type each amount, click Save New. To edit: type the Bill No., Bill Ref. No. or a BIL- line ID in C5 and click Find.
B4: FORM STATUS | C4: {=IF(IF(C6="","Company; ","")&IF(AND(C6<>"",COUNTIF(Companies!$B$5:$B$74,C6)=0),"Company not in register; ","")&IF(C7="","Bill Date; ","")&IF(C8="","Bill Type; ","")&IF(AND(C8<>"",SUMPRODUCT((C17:C26<>"")*(COUNTIFS('Fee Schedule'!$A$6:$A$16,C17:C26,'Fee Schedule'!$B$6:$B$16,IFERROR(INDEX('Fee Schedule'!$B$20:$B$26,MATCH(C8,'Fee Schedule'!$A$20:$A$26,0)),"#"))=0))>0),"services not allowed for this Bill Type; ","")&IF(COUNTA(C17:C26)=0,"at least one service line; ","")&IF(SUMPRODUCT((C17:C26<>"")*(E17:E26=""))>0,"amount on "&SUMPRODUCT((C17:C26<>"")*(E17:E26=""))&" line(s); ","")&IF(SUMPRODUCT((C17:C26="")*(E17:E26<>""))>0,"service on "&SUMPRODUCT((C17:C26="")*(E17:E26<>""))&" line(s); ","")&IF(SUMPRODUCT((E17:E26<>"")*NOT(ISNUMBER(E17:E26)))>0,"amount not a number; ","")="","✔ Ready to save – "&C8&" bill, "&COUNTA(C17:C26)&" line(s), total $"&TEXT(SUM(E17:E26),"#,##0.00"),"✖ Missing: "&IF(C6="","Company; ","")&IF(AND(C6<>"",COUNTIF(Companies!$B$5:$B$74,C6)=0),"Company not in register; ","")&IF(C7="","Bill Date; ","")&IF(C8="","Bill Type; ","")&IF(AND(C8<>"",SUMPRODUCT((C17:C26<>"")*(COUNTIFS('Fee Schedule'!$A$6:$A$16,C17:C26,'Fee Schedule'!$B$6:$B$16,IFERROR(INDEX('Fee Schedule'!$B$20:$B$26,MATCH(C8,'Fee Schedule'!$A$20:$A$26,0)),"#"))=0))>0),"services not allowed for this Bill Type; ","")&IF(COUNTA(C17:C26)=0,"at least one service line; ","")&IF(SUMPRODUCT((C17:C26<>"")*(E17:E26=""))>0,"amount on "&SUMPRODUCT((C17:C26<>"")*(E17:E26=""))&" line(s); ","")&IF(SUMPRODUCT((C17:C26="")*(E17:E26<>""))>0,"service on "&SUMPRODUCT((C17:C26="")*(E17:E26<>""))&" line(s); ","")&IF(SUMPRODUCT((E17:E26<>"")*NOT(ISNUMBER(E17:E26)))>0,"amount not a number; ",""))} -> ✖ Missing: Company; Bill Date; Bill Type; at least one service line;
B5: Bill No. | D5: {=IF(C5="","AUTO – leave blank for a new bill (next: BN-"&TEXT(MAX(IFERROR(--MID('Bills & Invoices'!$B$5:$B$32,4,4),0))+1,"000")&"). To edit, type a Bill No. / Bill Ref. No. / BIL- ID and click Find.",IF(COUNTA(G17:G26)>0,"Loaded "&COUNTA(G17:G26)&" saved line(s) – edit, then click Update","Click Find by ID to load this bill"))} -> AUTO – leave blank for a new bill (next: BN-2027). To edit, type a Bill No. / Bill Ref. No. / BIL- ID and click Find.
B6: Company * | D6: {=IF(C6="","Choose the company",IFERROR("ID: "&INDEX(Companies!$A$5:$A$74,MATCH(C6,Companies!$B$5:$B$74,0)),"⚠ Not in Company register – add it on the Company Form first"))} -> Choose the company
B7: Bill Date * | D7: dd-mmm-yyyy
B8: Bill Type * | D8: {=IF(C8="","Choose the Bill Type first – it decides the allowed services and the exact letter wording",IF(SUMPRODUCT((C17:C26<>"")*(COUNTIFS('Fee Schedule'!$A$6:$A$16,C17:C26,'Fee Schedule'!$B$6:$B$16,IFERROR(INDEX('Fee Schedule'!$B$20:$B$26,MATCH(C8,'Fee Schedule'!$A$20:$A$26,0)),"#"))=0))>0,"⚠ "&SUMPRODUCT((C17:C26<>"")*(COUNTIFS('Fee Schedule'!$A$6:$A$16,C17:C26,'Fee Schedule'!$B$6:$B$16,IFERROR(INDEX('Fee Schedule'!$B$20:$B$26,MATCH(C8,'Fee Schedule'!$A$20:$A$26,0)),"#"))=0))&" line(s) are not allowed on a "&C8&" bill – change them or make a separate bill","✔ Letter: "&C8&" wording (see Fee Schedule)"))} -> Choose the Bill Type first – it decides the allowed services and the exact letter wording
B9: Bill Ref. No. | D9: =IF(OR(C9="",COUNTA(G17:G26)>0),"EPA letter reference, e.g. ED/EPA-01/03336/26/RL",IF(COUNTIF('Bills & Invoices'!$P$5:$P$32,C9)>0,"⚠ This Bill Ref. No. is already used – check for duplicate","✔ New reference")) -> EPA letter reference, e.g. ED/EPA-01/03336/26/RL
B10: Contact Person | D10: Name as it should appear, e.g. Mr. Isaac Bestman (or just Isaac Bestman)
B11: Position / Title | D11: Job title, e.g. General Manager, CEO – or Mr./Mrs./Dr. if you typed only the name above
B12: Location | D12: {=IF(C12<>"","",IFERROR("Leave blank to use: "&INDEX(Companies!$D$5:$D$74,MATCH(C6,Companies!$B$5:$B$74,0)),""))}
B13: Activity
B14: Linked Record(s) | D14: Filled by 'Create Bill' (LIC-### / CLN-###) – links this bill to the licence or clearance
B15: BILL LINES (up to 10 services)
B16: Line | C16: Service * | D16: Details / Chemical(s) | E16: Amount (USD) * | F16: Suggested fee | G16: Line ID
B17: 1 | F17: {=IF(C17="","",IFERROR(IF(INDEX('Fee Schedule'!$C$6:$C$16,MATCH(C17,'Fee Schedule'!$A$6:$A$16,0))="","case by case",INDEX('Fee Schedule'!$C$6:$C$16,MATCH(C17,'Fee Schedule'!$A$6:$A$16,0))),""))}
B18: 2 | F18: {=IF(C18="","",IFERROR(IF(INDEX('Fee Schedule'!$C$6:$C$16,MATCH(C18,'Fee Schedule'!$A$6:$A$16,0))="","case by case",INDEX('Fee Schedule'!$C$6:$C$16,MATCH(C18,'Fee Schedule'!$A$6:$A$16,0))),""))}
B19: 3 | F19: {=IF(C19="","",IFERROR(IF(INDEX('Fee Schedule'!$C$6:$C$16,MATCH(C19,'Fee Schedule'!$A$6:$A$16,0))="","case by case",INDEX('Fee Schedule'!$C$6:$C$16,MATCH(C19,'Fee Schedule'!$A$6:$A$16,0))),""))}
B20: 4 | F20: {=IF(C20="","",IFERROR(IF(INDEX('Fee Schedule'!$C$6:$C$16,MATCH(C20,'Fee Schedule'!$A$6:$A$16,0))="","case by case",INDEX('Fee Schedule'!$C$6:$C$16,MATCH(C20,'Fee Schedule'!$A$6:$A$16,0))),""))}
B21: 5 | F21: {=IF(C21="","",IFERROR(IF(INDEX('Fee Schedule'!$C$6:$C$16,MATCH(C21,'Fee Schedule'!$A$6:$A$16,0))="","case by case",INDEX('Fee Schedule'!$C$6:$C$16,MATCH(C21,'Fee Schedule'!$A$6:$A$16,0))),""))}
B22: 6 | F22: {=IF(C22="","",IFERROR(IF(INDEX('Fee Schedule'!$C$6:$C$16,MATCH(C22,'Fee Schedule'!$A$6:$A$16,0))="","case by case",INDEX('Fee Schedule'!$C$6:$C$16,MATCH(C22,'Fee Schedule'!$A$6:$A$16,0))),""))}
B23: 7 | F23: {=IF(C23="","",IFERROR(IF(INDEX('Fee Schedule'!$C$6:$C$16,MATCH(C23,'Fee Schedule'!$A$6:$A$16,0))="","case by case",INDEX('Fee Schedule'!$C$6:$C$16,MATCH(C23,'Fee Schedule'!$A$6:$A$16,0))),""))}
B24: 8 | F24: {=IF(C24="","",IFERROR(IF(INDEX('Fee Schedule'!$C$6:$C$16,MATCH(C24,'Fee Schedule'!$A$6:$A$16,0))="","case by case",INDEX('Fee Schedule'!$C$6:$C$16,MATCH(C24,'Fee Schedule'!$A$6:$A$16,0))),""))}
B25: 9 | F25: {=IF(C25="","",IFERROR(IF(INDEX('Fee Schedule'!$C$6:$C$16,MATCH(C25,'Fee Schedule'!$A$6:$A$16,0))="","case by case",INDEX('Fee Schedule'!$C$6:$C$16,MATCH(C25,'Fee Schedule'!$A$6:$A$16,0))),""))}
B26: 10 | F26: {=IF(C26="","",IFERROR(IF(INDEX('Fee Schedule'!$C$6:$C$16,MATCH(C26,'Fee Schedule'!$A$6:$A$16,0))="","case by case",INDEX('Fee Schedule'!$C$6:$C$16,MATCH(C26,'Fee Schedule'!$A$6:$A$16,0))),""))}
D27: TOTAL | E27: =SUM(E17:E26) -> 0
B29: Company account | C29: {=IF(C6="","",IFERROR("Billed $"&TEXT(SUMIFS('Bills & Invoices'!$J$5:$J$32,'Bills & Invoices'!$C$5:$C$32,INDEX(Companies!$A$5:$A$74,MATCH(C6,Companies!$B$5:$B$74,0))),"#,##0")&" | Paid $"&TEXT(SUMIFS('Payments & Receipts'!$F$5:$F$58,'Payments & Receipts'!$B$5:$B$58,INDEX(Companies!$A$5:$A$74,MATCH(C6,Companies!$B$5:$B$74,0))),"#,##0")&" | Outstanding $"&TEXT(MAX(0,SUMIFS('Bills & Invoices'!$J$5:$J$32,'Bills & Invoices'!$C$5:$C$32,INDEX(Companies!$A$5:$A$74,MATCH(C6,Companies!$B$5:$B$74,0)))-SUMIFS('Payments & Receipts'!$F$5:$F$58,'Payments & Receipts'!$B$5:$B$58,INDEX(Companies!$A$5:$A$74,MATCH(C6,Companies!$B$5:$B$74,0)))),"#,##0"),""))}
B31: Tip: to remove a saved service from a bill, Find the bill, clear that line's Service and Amount, then click Update.

Sheet Payment Form
A1: ERRS – CHEMICAL MANAGEMENT UNIT | PAYMENT / RECEIPT FORM
A2: Yellow cells are inputs. * = required. To edit: type the ID in row 5 and click Find, change fields, then click Update. Leave the ID blank and click Save New for a new record.
B4: FORM STATUS | C4: =IF(IF(C6="","Company; ","")&IF(C7="","Purpose / Services; ","")&IF(C8="","Amount (USD); ","")&IF(C9="","Payment Date; ","")&IF(AND(C6<>"",COUNTIF(Companies!$B$5:$B$74,C6)=0),"Company not in register; ","")&IF(AND(C8<>"",NOT(ISNUMBER(C8))),"Amount (USD) not a number; ","")="","✔ Ready to save","✖ Missing: "&IF(C6="","Company; ","")&IF(C7="","Purpose / Services; ","")&IF(C8="","Amount (USD); ","")&IF(C9="","Payment Date; ","")&IF(AND(C6<>"",COUNTIF(Companies!$B$5:$B$74,C6)=0),"Company not in register; ","")&IF(AND(C8<>"",NOT(ISNUMBER(C8))),"Amount (USD) not a number; ","")) -> ✖ Missing: Company; Purpose / Services; Amount (USD); Payment Date;
B5: Record ID | D5: {="Leave blank for a NEW record (next ID: "&"PAY-"&TEXT(SUMPRODUCT(MAX(--MID('Payments & Receipts'!$A$5:$A$58,5,4)))+1,"000")&"). Type an existing ID and click Find to edit."} -> Leave blank for a NEW record (next ID: PAY-055). Type an existing ID and click Find to edit.
B6: Company * | D6: {=IF(C6="","",IFERROR("ID: "&INDEX(Companies!$A$5:$A$74,MATCH(C6,Companies!$B$5:$B$74,0)),"⚠ Not in Company register – add it on the Company Form first"))}
B7: Purpose / Services * | D7: What the payment is for
B8: Amount (USD) * | D8: US dollars
B9: Payment Date * | D9: dd-mmm-yyyy
B10: Receipt No. | D10: =IF(C10="","Receipt number from the payment slip",IF(COUNTIF('Payments & Receipts'!$H$5:$H$58,C10)>0,"⚠ Receipt already recorded – check for duplicate","✔ New receipt")) -> Receipt number from the payment slip
B11: Remarks
B12: Bill No. (paying for) | D12: {=IF(C12="","Link this payment to a bill so the bill shows Paid / Part paid",IFERROR(INDEX('Bills & Invoices'!$D$5:$D$32,MATCH(C12,'Bills & Invoices'!$B$5:$B$32,0))&": billed $"&TEXT(SUMIFS('Bills & Invoices'!$J$5:$J$32,'Bills & Invoices'!$B$5:$B$32,C12),"#,##0.00")&", paid $"&TEXT(SUMIFS('Payments & Receipts'!$F$5:$F$58,'Payments & Receipts'!$L$5:$L$58,C12),"#,##0.00")&IF(AND(C6<>"",INDEX('Bills & Invoices'!$D$5:$D$32,MATCH(C12,'Bills & Invoices'!$B$5:$B$32,0))<>C6)," ⚠ bill belongs to another company",""),"⚠ Bill not found"))} -> Link this payment to a bill so the bill shows Paid / Part paid
B13: Company account | C13: {=IF(C6="","",IFERROR("Billed $"&TEXT(SUMIFS('Bills & Invoices'!$J$5:$J$32,'Bills & Invoices'!$C$5:$C$32,INDEX(Companies!$A$5:$A$74,MATCH(C6,Companies!$B$5:$B$74,0))),"#,##0")&" | Paid $"&TEXT(SUMIFS('Payments & Receipts'!$F$5:$F$58,'Payments & Receipts'!$B$5:$B$58,INDEX(Companies!$A$5:$A$74,MATCH(C6,Companies!$B$5:$B$74,0))),"#,##0")&" | Outstanding $"&TEXT(MAX(0,SUMIFS('Bills & Invoices'!$J$5:$J$32,'Bills & Invoices'!$C$5:$C$32,INDEX(Companies!$A$5:$A$74,MATCH(C6,Companies!$B$5:$B$74,0)))-SUMIFS('Payments & Receipts'!$F$5:$F$58,'Payments & Receipts'!$B$5:$B$58,INDEX(Companies!$A$5:$A$74,MATCH(C6,Companies!$B$5:$B$74,0)))),"#,##0"),""))}

Sheet Print CRL
B2: =IF($J$3="No","",setLetterhead_1) -> REPUBLIC OF LIBERIA | I2: PRINT – ANNUAL CHEMICAL REGISTRATION LICENSE
B3: =IF($J$3="No","",setLetterhead_2) -> ENVIRONMENTAL PROTECTION AGENCY | I3: Print letterhead ▶ | J3: Yes
B4: =IF($J$3="No","",setLetterhead_3) -> P.O. Box 4024 | I4: Licence Record ID ▶
B5: =IF($J$3="No","",setLetterhead_4) -> Bright Building 302-A, Sekou Toure Avenue, Mamba Point | I5: Check | J5: {=IF($J$4="","Choose a licence record",IF($J$6="","⚠ Record not found",IF(ISNUMBER(SEARCH("CRL",INDEX('Licences & Certificates'!$E$5:$E$73,$J$6))),IF(INDEX('Licences & Certificates'!$K$5:$K$73,$J$6)="","⚠ No licence number yet","✔ Ready to print"),"⚠ This record is "&INDEX('Licences & Certificates'!$E$5:$E$73,$J$6))))} -> Choose a licence record
B6: =IF($J$3="No","",setLetterhead_5) -> 1000 Monrovia, 10 Liberia | I6: (row in register) | J6: =IFERROR(MATCH($J$4,'Licences & Certificates'!$A$5:$A$73,0),"")
I7: Licence No. | J7: {=IF($J$6="","",INDEX('Licences & Certificates'!$K$5:$K$73,$J$6)&"")}
I8: Company | J8: {=IF($J$6="","",INDEX('Licences & Certificates'!$C$5:$C$73,$J$6))}
B9: =IF($J$7="","License No. ________","License No. "&$J$7) -> License No. ________ | I9: Location | J9: {=IF($J$6="","",IF(INDEX('Licences & Certificates'!$G$5:$G$73,$J$6)<>"",INDEX('Licences & Certificates'!$G$5:$G$73,$J$6),IFERROR(INDEX(Companies!$D$5:$D$74,MATCH(INDEX('Licences & Certificates'!$B$5:$B$73,$J$6),Companies!$A$5:$A$74,0))&"","")))}
I10: Date Issued | J10: {=IF($J$6="","",IF(INDEX('Licences & Certificates'!$L$5:$L$73,$J$6)="","",INDEX('Licences & Certificates'!$L$5:$L$73,$J$6)))}
B11: ANNUAL CHEMICAL REGISTRATION LICENSE | I11: Expiry Date | J11: {=IF($J$6="","",IF(INDEX('Licences & Certificates'!$M$5:$M$73,$J$6)="","",INDEX('Licences & Certificates'!$M$5:$M$73,$J$6)))}
B12: (Issued under Part II Section VI of the EPA Act) | I12: Chemical lines found | J12: =COUNTIF('Licence Chemicals'!$A$5:$A$167,$J$4) -> 0
I13: Signed by ▶ | J13: Executive Director
B14: This is to certify that | I14: How to use: pick the Licence Record ID in J4 and choose who signs. Add the chemicals for that licence on the 'Licence Chemicals' sheet. Then use the OUTPUT buttons on the right – empty table rows are left out automatically. Set 'Print letterhead' (J3) to No when printing on pre-printed EPA letterhead paper – the letterhead text and logos are left off, keeping the same space at the top.
B15: =UPPER($J$8)
B16: =IF($J$9="","","(Located at "&$J$9&")")
B18: Is hereby granted this Annual Chemical Registration License, pursuant to Part 5 Section 51-53 of the Environmental Protection and Management Law of Liberia and Section 5.5 & 5.6 of the National Environmental Policy of Liberia, for the registration of Industrial Chemicals, subject to the EPA Act, the Chemical Guideline of Liberia and conditions specified in this license.
B20: PRODUCT INFORMATION
B21: No. | C21: Trade or IUPAC Name | D21: EPA Registration #. | E21: Types | L21: helper
B22: =IF($L22="","",ROWS($L$22:L22)) | C22: {=IF($L22="","",INDEX('Licence Chemicals'!$D$5:$D$167,$L22)&"")} | D22: {=IF($L22="","",INDEX('Licence Chemicals'!$E$5:$E$167,$L22)&"")} | E22: {=IF($L22="","",IF(INDEX('Licence Chemicals'!$F$5:$F$167,$L22)="","Industrial Chemical",INDEX('Licence Chemicals'!$F$5:$F$167,$L22)&""))} | L22: =IFERROR(__xludf.DUMMYFUNCTION("ARRAY_CONSTRAIN(ARRAYFORMULA(IFERROR(SMALL(FILTER((ROW('Licence Chemicals'!$A$5:$A$167)-ROW('Licence Chemicals'!$A$4:$I$4)),IFERROR(('Licence Chemicals'!$A$5:$A$167=$J$4),FALSE)),ROWS($L$22:L22)),"""")), 1, 1)"),"")
B23: =IF($L23="","",ROWS($L$22:L23)) | C23: {=IF($L23="","",INDEX('Licence Chemicals'!$D$5:$D$167,$L23)&"")} | D23: {=IF($L23="","",INDEX('Licence Chemicals'!$E$5:$E$167,$L23)&"")} | E23: {=IF($L23="","",IF(INDEX('Licence Chemicals'!$F$5:$F$167,$L23)="","Industrial Chemical",INDEX('Licence Chemicals'!$F$5:$F$167,$L23)&""))} | L23: =IFERROR(__xludf.DUMMYFUNCTION("ARRAY_CONSTRAIN(ARRAYFORMULA(IFERROR(SMALL(FILTER((ROW('Licence Chemicals'!$A$5:$A$167)-ROW('Licence Chemicals'!$A$4:$I$4)),IFERROR(('Licence Chemicals'!$A$5:$A$167=$J$4),FALSE)),ROWS($L$22:L23)),"""")), 1, 1)"),"")
B24: =IF($L24="","",ROWS($L$22:L24)) | C24: {=IF($L24="","",INDEX('Licence Chemicals'!$D$5:$D$167,$L24)&"")} | D24: {=IF($L24="","",INDEX('Licence Chemicals'!$E$5:$E$167,$L24)&"")} | E24: {=IF($L24="","",IF(INDEX('Licence Chemicals'!$F$5:$F$167,$L24)="","Industrial Chemical",INDEX('Licence Chemicals'!$F$5:$F$167,$L24)&""))} | L24: =IFERROR(__xludf.DUMMYFUNCTION("ARRAY_CONSTRAIN(ARRAYFORMULA(IFERROR(SMALL(FILTER((ROW('Licence Chemicals'!$A$5:$A$167)-ROW('Licence Chemicals'!$A$4:$I$4)),IFERROR(('Licence Chemicals'!$A$5:$A$167=$J$4),FALSE)),ROWS($L$22:L24)),"""")), 1, 1)"),"")
B25: =IF($L25="","",ROWS($L$22:L25)) | C25: {=IF($L25="","",INDEX('Licence Chemicals'!$D$5:$D$167,$L25)&"")} | D25: {=IF($L25="","",INDEX('Licence Chemicals'!$E$5:$E$167,$L25)&"")} | E25: {=IF($L25="","",IF(INDEX('Licence Chemicals'!$F$5:$F$167,$L25)="","Industrial Chemical",INDEX('Licence Chemicals'!$F$5:$F$167,$L25)&""))} | L25: =IFERROR(__xludf.DUMMYFUNCTION("ARRAY_CONSTRAIN(ARRAYFORMULA(IFERROR(SMALL(FILTER((ROW('Licence Chemicals'!$A$5:$A$167)-ROW('Licence Chemicals'!$A$4:$I$4)),IFERROR(('Licence Chemicals'!$A$5:$A$167=$J$4),FALSE)),ROWS($L$22:L25)),"""")), 1, 1)"),"")
B26: =IF($L26="","",ROWS($L$22:L26)) | C26: {=IF($L26="","",INDEX('Licence Chemicals'!$D$5:$D$167,$L26)&"")} | D26: {=IF($L26="","",INDEX('Licence Chemicals'!$E$5:$E$167,$L26)&"")} | E26: {=IF($L26="","",IF(INDEX('Licence Chemicals'!$F$5:$F$167,$L26)="","Industrial Chemical",INDEX('Licence Chemicals'!$F$5:$F$167,$L26)&""))} | L26: =IFERROR(__xludf.DUMMYFUNCTION("ARRAY_CONSTRAIN(ARRAYFORMULA(IFERROR(SMALL(FILTER((ROW('Licence Chemicals'!$A$5:$A$167)-ROW('Licence Chemicals'!$A$4:$I$4)),IFERROR(('Licence Chemicals'!$A$5:$A$167=$J$4),FALSE)),ROWS($L$22:L26)),"""")), 1, 1)"),"")
B27: =IF($L27="","",ROWS($L$22:L27)) | C27: {=IF($L27="","",INDEX('Licence Chemicals'!$D$5:$D$167,$L27)&"")} | D27: {=IF($L27="","",INDEX('Licence Chemicals'!$E$5:$E$167,$L27)&"")} | E27: {=IF($L27="","",IF(INDEX('Licence Chemicals'!$F$5:$F$167,$L27)="","Industrial Chemical",INDEX('Licence Chemicals'!$F$5:$F$167,$L27)&""))} | L27: =IFERROR(__xludf.DUMMYFUNCTION("ARRAY_CONSTRAIN(ARRAYFORMULA(IFERROR(SMALL(FILTER((ROW('Licence Chemicals'!$A$5:$A$167)-ROW('Licence Chemicals'!$A$4:$I$4)),IFERROR(('Licence Chemicals'!$A$5:$A$167=$J$4),FALSE)),ROWS($L$22:L27)),"""")), 1, 1)"),"")
B28: =IF($L28="","",ROWS($L$22:L28)) | C28: {=IF($L28="","",INDEX('Licence Chemicals'!$D$5:$D$167,$L28)&"")} | D28: {=IF($L28="","",INDEX('Licence Chemicals'!$E$5:$E$167,$L28)&"")} | E28: {=IF($L28="","",IF(INDEX('Licence Chemicals'!$F$5:$F$167,$L28)="","Industrial Chemical",INDEX('Licence Chemicals'!$F$5:$F$167,$L28)&""))} | L28: =IFERROR(__xludf.DUMMYFUNCTION("ARRAY_CONSTRAIN(ARRAYFORMULA(IFERROR(SMALL(FILTER((ROW('Licence Chemicals'!$A$5:$A$167)-ROW('Licence Chemicals'!$A$4:$I$4)),IFERROR(('Licence Chemicals'!$A$5:$A$167=$J$4),FALSE)),ROWS($L$22:L28)),"""")), 1, 1)"),"")
B29: =IF($L29="","",ROWS($L$22:L29)) | C29: {=IF($L29="","",INDEX('Licence Chemicals'!$D$5:$D$167,$L29)&"")} | D29: {=IF($L29="","",INDEX('Licence Chemicals'!$E$5:$E$167,$L29)&"")} | E29: {=IF($L29="","",IF(INDEX('Licence Chemicals'!$F$5:$F$167,$L29)="","Industrial Chemical",INDEX('Licence Chemicals'!$F$5:$F$167,$L29)&""))} | L29: =IFERROR(__xludf.DUMMYFUNCTION("ARRAY_CONSTRAIN(ARRAYFORMULA(IFERROR(SMALL(FILTER((ROW('Licence Chemicals'!$A$5:$A$167)-ROW('Licence Chemicals'!$A$4:$I$4)),IFERROR(('Licence Chemicals'!$A$5:$A$167=$J$4),FALSE)),ROWS($L$22:L29)),"""")), 1, 1)"),"")
B30: =IF($L30="","",ROWS($L$22:L30)) | C30: {=IF($L30="","",INDEX('Licence Chemicals'!$D$5:$D$167,$L30)&"")} | D30: {=IF($L30="","",INDEX('Licence Chemicals'!$E$5:$E$167,$L30)&"")} | E30: {=IF($L30="","",IF(INDEX('Licence Chemicals'!$F$5:$F$167,$L30)="","Industrial Chemical",INDEX('Licence Chemicals'!$F$5:$F$167,$L30)&""))} | L30: =IFERROR(__xludf.DUMMYFUNCTION("ARRAY_CONSTRAIN(ARRAYFORMULA(IFERROR(SMALL(FILTER((ROW('Licence Chemicals'!$A$5:$A$167)-ROW('Licence Chemicals'!$A$4:$I$4)),IFERROR(('Licence Chemicals'!$A$5:$A$167=$J$4),FALSE)),ROWS($L$22:L30)),"""")), 1, 1)"),"")
B31: =IF($L31="","",ROWS($L$22:L31)) | C31: {=IF($L31="","",INDEX('Licence Chemicals'!$D$5:$D$167,$L31)&"")} | D31: {=IF($L31="","",INDEX('Licence Chemicals'!$E$5:$E$167,$L31)&"")} | E31: {=IF($L31="","",IF(INDEX('Licence Chemicals'!$F$5:$F$167,$L31)="","Industrial Chemical",INDEX('Licence Chemicals'!$F$5:$F$167,$L31)&""))} | L31: =IFERROR(__xludf.DUMMYFUNCTION("ARRAY_CONSTRAIN(ARRAYFORMULA(IFERROR(SMALL(FILTER((ROW('Licence Chemicals'!$A$5:$A$167)-ROW('Licence Chemicals'!$A$4:$I$4)),IFERROR(('Licence Chemicals'!$A$5:$A$167=$J$4),FALSE)),ROWS($L$22:L31)),"""")), 1, 1)"),"")
B32: =IF($L32="","",ROWS($L$22:L32)) | C32: {=IF($L32="","",INDEX('Licence Chemicals'!$D$5:$D$167,$L32)&"")} | D32: {=IF($L32="","",INDEX('Licence Chemicals'!$E$5:$E$167,$L32)&"")} | E32: {=IF($L32="","",IF(INDEX('Licence Chemicals'!$F$5:$F$167,$L32)="","Industrial Chemical",INDEX('Licence Chemicals'!$F$5:$F$167,$L32)&""))} | L32: =IFERROR(__xludf.DUMMYFUNCTION("ARRAY_CONSTRAIN(ARRAYFORMULA(IFERROR(SMALL(FILTER((ROW('Licence Chemicals'!$A$5:$A$167)-ROW('Licence Chemicals'!$A$4:$I$4)),IFERROR(('Licence Chemicals'!$A$5:$A$167=$J$4),FALSE)),ROWS($L$22:L32)),"""")), 1, 1)"),"")
B33: =IF($L33="","",ROWS($L$22:L33)) | C33: {=IF($L33="","",INDEX('Licence Chemicals'!$D$5:$D$167,$L33)&"")} | D33: {=IF($L33="","",INDEX('Licence Chemicals'!$E$5:$E$167,$L33)&"")} | E33: {=IF($L33="","",IF(INDEX('Licence Chemicals'!$F$5:$F$167,$L33)="","Industrial Chemical",INDEX('Licence Chemicals'!$F$5:$F$167,$L33)&""))} | L33: =IFERROR(__xludf.DUMMYFUNCTION("ARRAY_CONSTRAIN(ARRAYFORMULA(IFERROR(SMALL(FILTER((ROW('Licence Chemicals'!$A$5:$A$167)-ROW('Licence Chemicals'!$A$4:$I$4)),IFERROR(('Licence Chemicals'!$A$5:$A$167=$J$4),FALSE)),ROWS($L$22:L33)),"""")), 1, 1)"),"")
B34: =IF($L34="","",ROWS($L$22:L34)) | C34: {=IF($L34="","",INDEX('Licence Chemicals'!$D$5:$D$167,$L34)&"")} | D34: {=IF($L34="","",INDEX('Licence Chemicals'!$E$5:$E$167,$L34)&"")} | E34: {=IF($L34="","",IF(INDEX('Licence Chemicals'!$F$5:$F$167,$L34)="","Industrial Chemical",INDEX('Licence Chemicals'!$F$5:$F$167,$L34)&""))} | L34: =IFERROR(__xludf.DUMMYFUNCTION("ARRAY_CONSTRAIN(ARRAYFORMULA(IFERROR(SMALL(FILTER((ROW('Licence Chemicals'!$A$5:$A$167)-ROW('Licence Chemicals'!$A$4:$I$4)),IFERROR(('Licence Chemicals'!$A$5:$A$167=$J$4),FALSE)),ROWS($L$22:L34)),"""")), 1, 1)"),"")
B35: =IF($L35="","",ROWS($L$22:L35)) | C35: {=IF($L35="","",INDEX('Licence Chemicals'!$D$5:$D$167,$L35)&"")} | D35: {=IF($L35="","",INDEX('Licence Chemicals'!$E$5:$E$167,$L35)&"")} | E35: {=IF($L35="","",IF(INDEX('Licence Chemicals'!$F$5:$F$167,$L35)="","Industrial Chemical",INDEX('Licence Chemicals'!$F$5:$F$167,$L35)&""))} | L35: =IFERROR(__xludf.DUMMYFUNCTION("ARRAY_CONSTRAIN(ARRAYFORMULA(IFERROR(SMALL(FILTER((ROW('Licence Chemicals'!$A$5:$A$167)-ROW('Licence Chemicals'!$A$4:$I$4)),IFERROR(('Licence Chemicals'!$A$5:$A$167=$J$4),FALSE)),ROWS($L$22:L35)),"""")), 1, 1)"),"")
B36: =IF($L36="","",ROWS($L$22:L36)) | C36: {=IF($L36="","",INDEX('Licence Chemicals'!$D$5:$D$167,$L36)&"")} | D36: {=IF($L36="","",INDEX('Licence Chemicals'!$E$5:$E$167,$L36)&"")} | E36: {=IF($L36="","",IF(INDEX('Licence Chemicals'!$F$5:$F$167,$L36)="","Industrial Chemical",INDEX('Licence Chemicals'!$F$5:$F$167,$L36)&""))} | L36: =IFERROR(__xludf.DUMMYFUNCTION("ARRAY_CONSTRAIN(ARRAYFORMULA(IFERROR(SMALL(FILTER((ROW('Licence Chemicals'!$A$5:$A$167)-ROW('Licence Chemicals'!$A$4:$I$4)),IFERROR(('Licence Chemicals'!$A$5:$A$167=$J$4),FALSE)),ROWS($L$22:L36)),"""")), 1, 1)"),"")
B37: =IF($L37="","",ROWS($L$22:L37)) | C37: {=IF($L37="","",INDEX('Licence Chemicals'!$D$5:$D$167,$L37)&"")} | D37: {=IF($L37="","",INDEX('Licence Chemicals'!$E$5:$E$167,$L37)&"")} | E37: {=IF($L37="","",IF(INDEX('Licence Chemicals'!$F$5:$F$167,$L37)="","Industrial Chemical",INDEX('Licence Chemicals'!$F$5:$F$167,$L37)&""))} | L37: =IFERROR(__xludf.DUMMYFUNCTION("ARRAY_CONSTRAIN(ARRAYFORMULA(IFERROR(SMALL(FILTER((ROW('Licence Chemicals'!$A$5:$A$167)-ROW('Licence Chemicals'!$A$4:$I$4)),IFERROR(('Licence Chemicals'!$A$5:$A$167=$J$4),FALSE)),ROWS($L$22:L37)),"""")), 1, 1)"),"")
B38: =IF($L38="","",ROWS($L$22:L38)) | C38: {=IF($L38="","",INDEX('Licence Chemicals'!$D$5:$D$167,$L38)&"")} | D38: {=IF($L38="","",INDEX('Licence Chemicals'!$E$5:$E$167,$L38)&"")} | E38: {=IF($L38="","",IF(INDEX('Licence Chemicals'!$F$5:$F$167,$L38)="","Industrial Chemical",INDEX('Licence Chemicals'!$F$5:$F$167,$L38)&""))} | L38: =IFERROR(__xludf.DUMMYFUNCTION("ARRAY_CONSTRAIN(ARRAYFORMULA(IFERROR(SMALL(FILTER((ROW('Licence Chemicals'!$A$5:$A$167)-ROW('Licence Chemicals'!$A$4:$I$4)),IFERROR(('Licence Chemicals'!$A$5:$A$167=$J$4),FALSE)),ROWS($L$22:L38)),"""")), 1, 1)"),"")
B39: =IF($L39="","",ROWS($L$22:L39)) | C39: {=IF($L39="","",INDEX('Licence Chemicals'!$D$5:$D$167,$L39)&"")} | D39: {=IF($L39="","",INDEX('Licence Chemicals'!$E$5:$E$167,$L39)&"")} | E39: {=IF($L39="","",IF(INDEX('Licence Chemicals'!$F$5:$F$167,$L39)="","Industrial Chemical",INDEX('Licence Chemicals'!$F$5:$F$167,$L39)&""))} | L39: =IFERROR(__xludf.DUMMYFUNCTION("ARRAY_CONSTRAIN(ARRAYFORMULA(IFERROR(SMALL(FILTER((ROW('Licence Chemicals'!$A$5:$A$167)-ROW('Licence Chemicals'!$A$4:$I$4)),IFERROR(('Licence Chemicals'!$A$5:$A$167=$J$4),FALSE)),ROWS($L$22:L39)),"""")), 1, 1)"),"")
B40: =IF($L40="","",ROWS($L$22:L40)) | C40: {=IF($L40="","",INDEX('Licence Chemicals'!$D$5:$D$167,$L40)&"")} | D40: {=IF($L40="","",INDEX('Licence Chemicals'!$E$5:$E$167,$L40)&"")} | E40: {=IF($L40="","",IF(INDEX('Licence Chemicals'!$F$5:$F$167,$L40)="","Industrial Chemical",INDEX('Licence Chemicals'!$F$5:$F$167,$L40)&""))} | L40: =IFERROR(__xludf.DUMMYFUNCTION("ARRAY_CONSTRAIN(ARRAYFORMULA(IFERROR(SMALL(FILTER((ROW('Licence Chemicals'!$A$5:$A$167)-ROW('Licence Chemicals'!$A$4:$I$4)),IFERROR(('Licence Chemicals'!$A$5:$A$167=$J$4),FALSE)),ROWS($L$22:L40)),"""")), 1, 1)"),"")
B41: =IF($L41="","",ROWS($L$22:L41)) | C41: {=IF($L41="","",INDEX('Licence Chemicals'!$D$5:$D$167,$L41)&"")} | D41: {=IF($L41="","",INDEX('Licence Chemicals'!$E$5:$E$167,$L41)&"")} | E41: {=IF($L41="","",IF(INDEX('Licence Chemicals'!$F$5:$F$167,$L41)="","Industrial Chemical",INDEX('Licence Chemicals'!$F$5:$F$167,$L41)&""))} | L41: =IFERROR(__xludf.DUMMYFUNCTION("ARRAY_CONSTRAIN(ARRAYFORMULA(IFERROR(SMALL(FILTER((ROW('Licence Chemicals'!$A$5:$A$167)-ROW('Licence Chemicals'!$A$4:$I$4)),IFERROR(('Licence Chemicals'!$A$5:$A$167=$J$4),FALSE)),ROWS($L$22:L41)),"""")), 1, 1)"),"")
B42: =IF($L42="","",ROWS($L$22:L42)) | C42: {=IF($L42="","",INDEX('Licence Chemicals'!$D$5:$D$167,$L42)&"")} | D42: {=IF($L42="","",INDEX('Licence Chemicals'!$E$5:$E$167,$L42)&"")} | E42: {=IF($L42="","",IF(INDEX('Licence Chemicals'!$F$5:$F$167,$L42)="","Industrial Chemical",INDEX('Licence Chemicals'!$F$5:$F$167,$L42)&""))} | L42: =IFERROR(__xludf.DUMMYFUNCTION("ARRAY_CONSTRAIN(ARRAYFORMULA(IFERROR(SMALL(FILTER((ROW('Licence Chemicals'!$A$5:$A$167)-ROW('Licence Chemicals'!$A$4:$I$4)),IFERROR(('Licence Chemicals'!$A$5:$A$167=$J$4),FALSE)),ROWS($L$22:L42)),"""")), 1, 1)"),"")
B43: =IF($L43="","",ROWS($L$22:L43)) | C43: {=IF($L43="","",INDEX('Licence Chemicals'!$D$5:$D$167,$L43)&"")} | D43: {=IF($L43="","",INDEX('Licence Chemicals'!$E$5:$E$167,$L43)&"")} | E43: {=IF($L43="","",IF(INDEX('Licence Chemicals'!$F$5:$F$167,$L43)="","Industrial Chemical",INDEX('Licence Chemicals'!$F$5:$F$167,$L43)&""))} | L43: =IFERROR(__xludf.DUMMYFUNCTION("ARRAY_CONSTRAIN(ARRAYFORMULA(IFERROR(SMALL(FILTER((ROW('Licence Chemicals'!$A$5:$A$167)-ROW('Licence Chemicals'!$A$4:$I$4)),IFERROR(('Licence Chemicals'!$A$5:$A$167=$J$4),FALSE)),ROWS($L$22:L43)),"""")), 1, 1)"),"")
B44: =IF($L44="","",ROWS($L$22:L44)) | C44: {=IF($L44="","",INDEX('Licence Chemicals'!$D$5:$D$167,$L44)&"")} | D44: {=IF($L44="","",INDEX('Licence Chemicals'!$E$5:$E$167,$L44)&"")} | E44: {=IF($L44="","",IF(INDEX('Licence Chemicals'!$F$5:$F$167,$L44)="","Industrial Chemical",INDEX('Licence Chemicals'!$F$5:$F$167,$L44)&""))} | L44: =IFERROR(__xludf.DUMMYFUNCTION("ARRAY_CONSTRAIN(ARRAYFORMULA(IFERROR(SMALL(FILTER((ROW('Licence Chemicals'!$A$5:$A$167)-ROW('Licence Chemicals'!$A$4:$I$4)),IFERROR(('Licence Chemicals'!$A$5:$A$167=$J$4),FALSE)),ROWS($L$22:L44)),"""")), 1, 1)"),"")
B45: =IF($L45="","",ROWS($L$22:L45)) | C45: {=IF($L45="","",INDEX('Licence Chemicals'!$D$5:$D$167,$L45)&"")} | D45: {=IF($L45="","",INDEX('Licence Chemicals'!$E$5:$E$167,$L45)&"")} | E45: {=IF($L45="","",IF(INDEX('Licence Chemicals'!$F$5:$F$167,$L45)="","Industrial Chemical",INDEX('Licence Chemicals'!$F$5:$F$167,$L45)&""))} | L45: =IFERROR(__xludf.DUMMYFUNCTION("ARRAY_CONSTRAIN(ARRAYFORMULA(IFERROR(SMALL(FILTER((ROW('Licence Chemicals'!$A$5:$A$167)-ROW('Licence Chemicals'!$A$4:$I$4)),IFERROR(('Licence Chemicals'!$A$5:$A$167=$J$4),FALSE)),ROWS($L$22:L45)),"""")), 1, 1)"),"")
B46: =IF($L46="","",ROWS($L$22:L46)) | C46: {=IF($L46="","",INDEX('Licence Chemicals'!$D$5:$D$167,$L46)&"")} | D46: {=IF($L46="","",INDEX('Licence Chemicals'!$E$5:$E$167,$L46)&"")} | E46: {=IF($L46="","",IF(INDEX('Licence Chemicals'!$F$5:$F$167,$L46)="","Industrial Chemical",INDEX('Licence Chemicals'!$F$5:$F$167,$L46)&""))} | L46: =IFERROR(__xludf.DUMMYFUNCTION("ARRAY_CONSTRAIN(ARRAYFORMULA(IFERROR(SMALL(FILTER((ROW('Licence Chemicals'!$A$5:$A$167)-ROW('Licence Chemicals'!$A$4:$I$4)),IFERROR(('Licence Chemicals'!$A$5:$A$167=$J$4),FALSE)),ROWS($L$22:L46)),"""")), 1, 1)"),"")
B47: =IF($L47="","",ROWS($L$22:L47)) | C47: {=IF($L47="","",INDEX('Licence Chemicals'!$D$5:$D$167,$L47)&"")} | D47: {=IF($L47="","",INDEX('Licence Chemicals'!$E$5:$E$167,$L47)&"")} | E47: {=IF($L47="","",IF(INDEX('Licence Chemicals'!$F$5:$F$167,$L47)="","Industrial Chemical",INDEX('Licence Chemicals'!$F$5:$F$167,$L47)&""))} | L47: =IFERROR(__xludf.DUMMYFUNCTION("ARRAY_CONSTRAIN(ARRAYFORMULA(IFERROR(SMALL(FILTER((ROW('Licence Chemicals'!$A$5:$A$167)-ROW('Licence Chemicals'!$A$4:$I$4)),IFERROR(('Licence Chemicals'!$A$5:$A$167=$J$4),FALSE)),ROWS($L$22:L47)),"""")), 1, 1)"),"")
B48: =IF($L48="","",ROWS($L$22:L48)) | C48: {=IF($L48="","",INDEX('Licence Chemicals'!$D$5:$D$167,$L48)&"")} | D48: {=IF($L48="","",INDEX('Licence Chemicals'!$E$5:$E$167,$L48)&"")} | E48: {=IF($L48="","",IF(INDEX('Licence Chemicals'!$F$5:$F$167,$L48)="","Industrial Chemical",INDEX('Licence Chemicals'!$F$5:$F$167,$L48)&""))} | L48: =IFERROR(__xludf.DUMMYFUNCTION("ARRAY_CONSTRAIN(ARRAYFORMULA(IFERROR(SMALL(FILTER((ROW('Licence Chemicals'!$A$5:$A$167)-ROW('Licence Chemicals'!$A$4:$I$4)),IFERROR(('Licence Chemicals'!$A$5:$A$167=$J$4),FALSE)),ROWS($L$22:L48)),"""")), 1, 1)"),"")
B49: =IF($L49="","",ROWS($L$22:L49)) | C49: {=IF($L49="","",INDEX('Licence Chemicals'!$D$5:$D$167,$L49)&"")} | D49: {=IF($L49="","",INDEX('Licence Chemicals'!$E$5:$E$167,$L49)&"")} | E49: {=IF($L49="","",IF(INDEX('Licence Chemicals'!$F$5:$F$167,$L49)="","Industrial Chemical",INDEX('Licence Chemicals'!$F$5:$F$167,$L49)&""))} | L49: =IFERROR(__xludf.DUMMYFUNCTION("ARRAY_CONSTRAIN(ARRAYFORMULA(IFERROR(SMALL(FILTER((ROW('Licence Chemicals'!$A$5:$A$167)-ROW('Licence Chemicals'!$A$4:$I$4)),IFERROR(('Licence Chemicals'!$A$5:$A$167=$J$4),FALSE)),ROWS($L$22:L49)),"""")), 1, 1)"),"")
B50: =IF($L50="","",ROWS($L$22:L50)) | C50: {=IF($L50="","",INDEX('Licence Chemicals'!$D$5:$D$167,$L50)&"")} | D50: {=IF($L50="","",INDEX('Licence Chemicals'!$E$5:$E$167,$L50)&"")} | E50: {=IF($L50="","",IF(INDEX('Licence Chemicals'!$F$5:$F$167,$L50)="","Industrial Chemical",INDEX('Licence Chemicals'!$F$5:$F$167,$L50)&""))} | L50: =IFERROR(__xludf.DUMMYFUNCTION("ARRAY_CONSTRAIN(ARRAYFORMULA(IFERROR(SMALL(FILTER((ROW('Licence Chemicals'!$A$5:$A$167)-ROW('Licence Chemicals'!$A$4:$I$4)),IFERROR(('Licence Chemicals'!$A$5:$A$167=$J$4),FALSE)),ROWS($L$22:L50)),"""")), 1, 1)"),"")
B51: =IF($L51="","",ROWS($L$22:L51)) | C51: {=IF($L51="","",INDEX('Licence Chemicals'!$D$5:$D$167,$L51)&"")} | D51: {=IF($L51="","",INDEX('Licence Chemicals'!$E$5:$E$167,$L51)&"")} | E51: {=IF($L51="","",IF(INDEX('Licence Chemicals'!$F$5:$F$167,$L51)="","Industrial Chemical",INDEX('Licence Chemicals'!$F$5:$F$167,$L51)&""))} | L51: =IFERROR(__xludf.DUMMYFUNCTION("ARRAY_CONSTRAIN(ARRAYFORMULA(IFERROR(SMALL(FILTER((ROW('Licence Chemicals'!$A$5:$A$167)-ROW('Licence Chemicals'!$A$4:$I$4)),IFERROR(('Licence Chemicals'!$A$5:$A$167=$J$4),FALSE)),ROWS($L$22:L51)),"""")), 1, 1)"),"")
B52: =IF($L52="","",ROWS($L$22:L52)) | C52: {=IF($L52="","",INDEX('Licence Chemicals'!$D$5:$D$167,$L52)&"")} | D52: {=IF($L52="","",INDEX('Licence Chemicals'!$E$5:$E$167,$L52)&"")} | E52: {=IF($L52="","",IF(INDEX('Licence Chemicals'!$F$5:$F$167,$L52)="","Industrial Chemical",INDEX('Licence Chemicals'!$F$5:$F$167,$L52)&""))} | L52: =IFERROR(__xludf.DUMMYFUNCTION("ARRAY_CONSTRAIN(ARRAYFORMULA(IFERROR(SMALL(FILTER((ROW('Licence Chemicals'!$A$5:$A$167)-ROW('Licence Chemicals'!$A$4:$I$4)),IFERROR(('Licence Chemicals'!$A$5:$A$167=$J$4),FALSE)),ROWS($L$22:L52)),"""")), 1, 1)"),"")
B53: =IF($L53="","",ROWS($L$22:L53)) | C53: {=IF($L53="","",INDEX('Licence Chemicals'!$D$5:$D$167,$L53)&"")} | D53: {=IF($L53="","",INDEX('Licence Chemicals'!$E$5:$E$167,$L53)&"")} | E53: {=IF($L53="","",IF(INDEX('Licence Chemicals'!$F$5:$F$167,$L53)="","Industrial Chemical",INDEX('Licence Chemicals'!$F$5:$F$167,$L53)&""))} | L53: =IFERROR(__xludf.DUMMYFUNCTION("ARRAY_CONSTRAIN(ARRAYFORMULA(IFERROR(SMALL(FILTER((ROW('Licence Chemicals'!$A$5:$A$167)-ROW('Licence Chemicals'!$A$4:$I$4)),IFERROR(('Licence Chemicals'!$A$5:$A$167=$J$4),FALSE)),ROWS($L$22:L53)),"""")), 1, 1)"),"")
B54: =IF($L54="","",ROWS($L$22:L54)) | C54: {=IF($L54="","",INDEX('Licence Chemicals'!$D$5:$D$167,$L54)&"")} | D54: {=IF($L54="","",INDEX('Licence Chemicals'!$E$5:$E$167,$L54)&"")} | E54: {=IF($L54="","",IF(INDEX('Licence Chemicals'!$F$5:$F$167,$L54)="","Industrial Chemical",INDEX('Licence Chemicals'!$F$5:$F$167,$L54)&""))} | L54: =IFERROR(__xludf.DUMMYFUNCTION("ARRAY_CONSTRAIN(ARRAYFORMULA(IFERROR(SMALL(FILTER((ROW('Licence Chemicals'!$A$5:$A$167)-ROW('Licence Chemicals'!$A$4:$I$4)),IFERROR(('Licence Chemicals'!$A$5:$A$167=$J$4),FALSE)),ROWS($L$22:L54)),"""")), 1, 1)"),"")
B55: =IF($L55="","",ROWS($L$22:L55)) | C55: {=IF($L55="","",INDEX('Licence Chemicals'!$D$5:$D$167,$L55)&"")} | D55: {=IF($L55="","",INDEX('Licence Chemicals'!$E$5:$E$167,$L55)&"")} | E55: {=IF($L55="","",IF(INDEX('Licence Chemicals'!$F$5:$F$167,$L55)="","Industrial Chemical",INDEX('Licence Chemicals'!$F$5:$F$167,$L55)&""))} | L55: =IFERROR(__xludf.DUMMYFUNCTION("ARRAY_CONSTRAIN(ARRAYFORMULA(IFERROR(SMALL(FILTER((ROW('Licence Chemicals'!$A$5:$A$167)-ROW('Licence Chemicals'!$A$4:$I$4)),IFERROR(('Licence Chemicals'!$A$5:$A$167=$J$4),FALSE)),ROWS($L$22:L55)),"""")), 1, 1)"),"")
B56: =IF($L56="","",ROWS($L$22:L56)) | C56: {=IF($L56="","",INDEX('Licence Chemicals'!$D$5:$D$167,$L56)&"")} | D56: {=IF($L56="","",INDEX('Licence Chemicals'!$E$5:$E$167,$L56)&"")} | E56: {=IF($L56="","",IF(INDEX('Licence Chemicals'!$F$5:$F$167,$L56)="","Industrial Chemical",INDEX('Licence Chemicals'!$F$5:$F$167,$L56)&""))} | L56: =IFERROR(__xludf.DUMMYFUNCTION("ARRAY_CONSTRAIN(ARRAYFORMULA(IFERROR(SMALL(FILTER((ROW('Licence Chemicals'!$A$5:$A$167)-ROW('Licence Chemicals'!$A$4:$I$4)),IFERROR(('Licence Chemicals'!$A$5:$A$167=$J$4),FALSE)),ROWS($L$22:L56)),"""")), 1, 1)"),"")
B57: =IF($L57="","",ROWS($L$22:L57)) | C57: {=IF($L57="","",INDEX('Licence Chemicals'!$D$5:$D$167,$L57)&"")} | D57: {=IF($L57="","",INDEX('Licence Chemicals'!$E$5:$E$167,$L57)&"")} | E57: {=IF($L57="","",IF(INDEX('Licence Chemicals'!$F$5:$F$167,$L57)="","Industrial Chemical",INDEX('Licence Chemicals'!$F$5:$F$167,$L57)&""))} | L57: =IFERROR(__xludf.DUMMYFUNCTION("ARRAY_CONSTRAIN(ARRAYFORMULA(IFERROR(SMALL(FILTER((ROW('Licence Chemicals'!$A$5:$A$167)-ROW('Licence Chemicals'!$A$4:$I$4)),IFERROR(('Licence Chemicals'!$A$5:$A$167=$J$4),FALSE)),ROWS($L$22:L57)),"""")), 1, 1)"),"")
B58: =IF($L58="","",ROWS($L$22:L58)) | C58: {=IF($L58="","",INDEX('Licence Chemicals'!$D$5:$D$167,$L58)&"")} | D58: {=IF($L58="","",INDEX('Licence Chemicals'!$E$5:$E$167,$L58)&"")} | E58: {=IF($L58="","",IF(INDEX('Licence Chemicals'!$F$5:$F$167,$L58)="","Industrial Chemical",INDEX('Licence Chemicals'!$F$5:$F$167,$L58)&""))} | L58: =IFERROR(__xludf.DUMMYFUNCTION("ARRAY_CONSTRAIN(ARRAYFORMULA(IFERROR(SMALL(FILTER((ROW('Licence Chemicals'!$A$5:$A$167)-ROW('Licence Chemicals'!$A$4:$I$4)),IFERROR(('Licence Chemicals'!$A$5:$A$167=$J$4),FALSE)),ROWS($L$22:L58)),"""")), 1, 1)"),"")
B59: =IF($L59="","",ROWS($L$22:L59)) | C59: {=IF($L59="","",INDEX('Licence Chemicals'!$D$5:$D$167,$L59)&"")} | D59: {=IF($L59="","",INDEX('Licence Chemicals'!$E$5:$E$167,$L59)&"")} | E59: {=IF($L59="","",IF(INDEX('Licence Chemicals'!$F$5:$F$167,$L59)="","Industrial Chemical",INDEX('Licence Chemicals'!$F$5:$F$167,$L59)&""))} | L59: =IFERROR(__xludf.DUMMYFUNCTION("ARRAY_CONSTRAIN(ARRAYFORMULA(IFERROR(SMALL(FILTER((ROW('Licence Chemicals'!$A$5:$A$167)-ROW('Licence Chemicals'!$A$4:$I$4)),IFERROR(('Licence Chemicals'!$A$5:$A$167=$J$4),FALSE)),ROWS($L$22:L59)),"""")), 1, 1)"),"")
B60: =IF($L60="","",ROWS($L$22:L60)) | C60: {=IF($L60="","",INDEX('Licence Chemicals'!$D$5:$D$167,$L60)&"")} | D60: {=IF($L60="","",INDEX('Licence Chemicals'!$E$5:$E$167,$L60)&"")} | E60: {=IF($L60="","",IF(INDEX('Licence Chemicals'!$F$5:$F$167,$L60)="","Industrial Chemical",INDEX('Licence Chemicals'!$F$5:$F$167,$L60)&""))} | L60: =IFERROR(__xludf.DUMMYFUNCTION("ARRAY_CONSTRAIN(ARRAYFORMULA(IFERROR(SMALL(FILTER((ROW('Licence Chemicals'!$A$5:$A$167)-ROW('Licence Chemicals'!$A$4:$I$4)),IFERROR(('Licence Chemicals'!$A$5:$A$167=$J$4),FALSE)),ROWS($L$22:L60)),"""")), 1, 1)"),"")
B61: =IF($L61="","",ROWS($L$22:L61)) | C61: {=IF($L61="","",INDEX('Licence Chemicals'!$D$5:$D$167,$L61)&"")} | D61: {=IF($L61="","",INDEX('Licence Chemicals'!$E$5:$E$167,$L61)&"")} | E61: {=IF($L61="","",IF(INDEX('Licence Chemicals'!$F$5:$F$167,$L61)="","Industrial Chemical",INDEX('Licence Chemicals'!$F$5:$F$167,$L61)&""))} | L61: =IFERROR(__xludf.DUMMYFUNCTION("ARRAY_CONSTRAIN(ARRAYFORMULA(IFERROR(SMALL(FILTER((ROW('Licence Chemicals'!$A$5:$A$167)-ROW('Licence Chemicals'!$A$4:$I$4)),IFERROR(('Licence Chemicals'!$A$5:$A$167=$J$4),FALSE)),ROWS($L$22:L61)),"""")), 1, 1)"),"")
B62: =IF($L62="","",ROWS($L$22:L62)) | C62: {=IF($L62="","",INDEX('Licence Chemicals'!$D$5:$D$167,$L62)&"")} | D62: {=IF($L62="","",INDEX('Licence Chemicals'!$E$5:$E$167,$L62)&"")} | E62: {=IF($L62="","",IF(INDEX('Licence Chemicals'!$F$5:$F$167,$L62)="","Industrial Chemical",INDEX('Licence Chemicals'!$F$5:$F$167,$L62)&""))} | L62: =IFERROR(__xludf.DUMMYFUNCTION("ARRAY_CONSTRAIN(ARRAYFORMULA(IFERROR(SMALL(FILTER((ROW('Licence Chemicals'!$A$5:$A$167)-ROW('Licence Chemicals'!$A$4:$I$4)),IFERROR(('Licence Chemicals'!$A$5:$A$167=$J$4),FALSE)),ROWS($L$22:L62)),"""")), 1, 1)"),"")
B63: =IF($L63="","",ROWS($L$22:L63)) | C63: {=IF($L63="","",INDEX('Licence Chemicals'!$D$5:$D$167,$L63)&"")} | D63: {=IF($L63="","",INDEX('Licence Chemicals'!$E$5:$E$167,$L63)&"")} | E63: {=IF($L63="","",IF(INDEX('Licence Chemicals'!$F$5:$F$167,$L63)="","Industrial Chemical",INDEX('Licence Chemicals'!$F$5:$F$167,$L63)&""))} | L63: =IFERROR(__xludf.DUMMYFUNCTION("ARRAY_CONSTRAIN(ARRAYFORMULA(IFERROR(SMALL(FILTER((ROW('Licence Chemicals'!$A$5:$A$167)-ROW('Licence Chemicals'!$A$4:$I$4)),IFERROR(('Licence Chemicals'!$A$5:$A$167=$J$4),FALSE)),ROWS($L$22:L63)),"""")), 1, 1)"),"")
B64: =IF($L64="","",ROWS($L$22:L64)) | C64: {=IF($L64="","",INDEX('Licence Chemicals'!$D$5:$D$167,$L64)&"")} | D64: {=IF($L64="","",INDEX('Licence Chemicals'!$E$5:$E$167,$L64)&"")} | E64: {=IF($L64="","",IF(INDEX('Licence Chemicals'!$F$5:$F$167,$L64)="","Industrial Chemical",INDEX('Licence Chemicals'!$F$5:$F$167,$L64)&""))} | L64: =IFERROR(__xludf.DUMMYFUNCTION("ARRAY_CONSTRAIN(ARRAYFORMULA(IFERROR(SMALL(FILTER((ROW('Licence Chemicals'!$A$5:$A$167)-ROW('Licence Chemicals'!$A$4:$I$4)),IFERROR(('Licence Chemicals'!$A$5:$A$167=$J$4),FALSE)),ROWS($L$22:L64)),"""")), 1, 1)"),"")
B65: =IF($L65="","",ROWS($L$22:L65)) | C65: {=IF($L65="","",INDEX('Licence Chemicals'!$D$5:$D$167,$L65)&"")} | D65: {=IF($L65="","",INDEX('Licence Chemicals'!$E$5:$E$167,$L65)&"")} | E65: {=IF($L65="","",IF(INDEX('Licence Chemicals'!$F$5:$F$167,$L65)="","Industrial Chemical",INDEX('Licence Chemicals'!$F$5:$F$167,$L65)&""))} | L65: =IFERROR(__xludf.DUMMYFUNCTION("ARRAY_CONSTRAIN(ARRAYFORMULA(IFERROR(SMALL(FILTER((ROW('Licence Chemicals'!$A$5:$A$167)-ROW('Licence Chemicals'!$A$4:$I$4)),IFERROR(('Licence Chemicals'!$A$5:$A$167=$J$4),FALSE)),ROWS($L$22:L65)),"""")), 1, 1)"),"")
B66: =IF($L66="","",ROWS($L$22:L66)) | C66: {=IF($L66="","",INDEX('Licence Chemicals'!$D$5:$D$167,$L66)&"")} | D66: {=IF($L66="","",INDEX('Licence Chemicals'!$E$5:$E$167,$L66)&"")} | E66: {=IF($L66="","",IF(INDEX('Licence Chemicals'!$F$5:$F$167,$L66)="","Industrial Chemical",INDEX('Licence Chemicals'!$F$5:$F$167,$L66)&""))} | L66: =IFERROR(__xludf.DUMMYFUNCTION("ARRAY_CONSTRAIN(ARRAYFORMULA(IFERROR(SMALL(FILTER((ROW('Licence Chemicals'!$A$5:$A$167)-ROW('Licence Chemicals'!$A$4:$I$4)),IFERROR(('Licence Chemicals'!$A$5:$A$167=$J$4),FALSE)),ROWS($L$22:L66)),"""")), 1, 1)"),"")
B67: =IF($L67="","",ROWS($L$22:L67)) | C67: {=IF($L67="","",INDEX('Licence Chemicals'!$D$5:$D$167,$L67)&"")} | D67: {=IF($L67="","",INDEX('Licence Chemicals'!$E$5:$E$167,$L67)&"")} | E67: {=IF($L67="","",IF(INDEX('Licence Chemicals'!$F$5:$F$167,$L67)="","Industrial Chemical",INDEX('Licence Chemicals'!$F$5:$F$167,$L67)&""))} | L67: =IFERROR(__xludf.DUMMYFUNCTION("ARRAY_CONSTRAIN(ARRAYFORMULA(IFERROR(SMALL(FILTER((ROW('Licence Chemicals'!$A$5:$A$167)-ROW('Licence Chemicals'!$A$4:$I$4)),IFERROR(('Licence Chemicals'!$A$5:$A$167=$J$4),FALSE)),ROWS($L$22:L67)),"""")), 1, 1)"),"")
B68: =IF($L68="","",ROWS($L$22:L68)) | C68: {=IF($L68="","",INDEX('Licence Chemicals'!$D$5:$D$167,$L68)&"")} | D68: {=IF($L68="","",INDEX('Licence Chemicals'!$E$5:$E$167,$L68)&"")} | E68: {=IF($L68="","",IF(INDEX('Licence Chemicals'!$F$5:$F$167,$L68)="","Industrial Chemical",INDEX('Licence Chemicals'!$F$5:$F$167,$L68)&""))} | L68: =IFERROR(__xludf.DUMMYFUNCTION("ARRAY_CONSTRAIN(ARRAYFORMULA(IFERROR(SMALL(FILTER((ROW('Licence Chemicals'!$A$5:$A$167)-ROW('Licence Chemicals'!$A$4:$I$4)),IFERROR(('Licence Chemicals'!$A$5:$A$167=$J$4),FALSE)),ROWS($L$22:L68)),"""")), 1, 1)"),"")
B69: =IF($L69="","",ROWS($L$22:L69)) | C69: {=IF($L69="","",INDEX('Licence Chemicals'!$D$5:$D$167,$L69)&"")} | D69: {=IF($L69="","",INDEX('Licence Chemicals'!$E$5:$E$167,$L69)&"")} | E69: {=IF($L69="","",IF(INDEX('Licence Chemicals'!$F$5:$F$167,$L69)="","Industrial Chemical",INDEX('Licence Chemicals'!$F$5:$F$167,$L69)&""))} | L69: =IFERROR(__xludf.DUMMYFUNCTION("ARRAY_CONSTRAIN(ARRAYFORMULA(IFERROR(SMALL(FILTER((ROW('Licence Chemicals'!$A$5:$A$167)-ROW('Licence Chemicals'!$A$4:$I$4)),IFERROR(('Licence Chemicals'!$A$5:$A$167=$J$4),FALSE)),ROWS($L$22:L69)),"""")), 1, 1)"),"")
B70: =IF($L70="","",ROWS($L$22:L70)) | C70: {=IF($L70="","",INDEX('Licence Chemicals'!$D$5:$D$167,$L70)&"")} | D70: {=IF($L70="","",INDEX('Licence Chemicals'!$E$5:$E$167,$L70)&"")} | E70: {=IF($L70="","",IF(INDEX('Licence Chemicals'!$F$5:$F$167,$L70)="","Industrial Chemical",INDEX('Licence Chemicals'!$F$5:$F$167,$L70)&""))} | L70: =IFERROR(__xludf.DUMMYFUNCTION("ARRAY_CONSTRAIN(ARRAYFORMULA(IFERROR(SMALL(FILTER((ROW('Licence Chemicals'!$A$5:$A$167)-ROW('Licence Chemicals'!$A$4:$I$4)),IFERROR(('Licence Chemicals'!$A$5:$A$167=$J$4),FALSE)),ROWS($L$22:L70)),"""")), 1, 1)"),"")
B71: =IF($L71="","",ROWS($L$22:L71)) | C71: {=IF($L71="","",INDEX('Licence Chemicals'!$D$5:$D$167,$L71)&"")} | D71: {=IF($L71="","",INDEX('Licence Chemicals'!$E$5:$E$167,$L71)&"")} | E71: {=IF($L71="","",IF(INDEX('Licence Chemicals'!$F$5:$F$167,$L71)="","Industrial Chemical",INDEX('Licence Chemicals'!$F$5:$F$167,$L71)&""))} | L71: =IFERROR(__xludf.DUMMYFUNCTION("ARRAY_CONSTRAIN(ARRAYFORMULA(IFERROR(SMALL(FILTER((ROW('Licence Chemicals'!$A$5:$A$167)-ROW('Licence Chemicals'!$A$4:$I$4)),IFERROR(('Licence Chemicals'!$A$5:$A$167=$J$4),FALSE)),ROWS($L$22:L71)),"""")), 1, 1)"),"")
B72: =IF($L72="","",ROWS($L$22:L72)) | C72: {=IF($L72="","",INDEX('Licence Chemicals'!$D$5:$D$167,$L72)&"")} | D72: {=IF($L72="","",INDEX('Licence Chemicals'!$E$5:$E$167,$L72)&"")} | E72: {=IF($L72="","",IF(INDEX('Licence Chemicals'!$F$5:$F$167,$L72)="","Industrial Chemical",INDEX('Licence Chemicals'!$F$5:$F$167,$L72)&""))} | L72: =IFERROR(__xludf.DUMMYFUNCTION("ARRAY_CONSTRAIN(ARRAYFORMULA(IFERROR(SMALL(FILTER((ROW('Licence Chemicals'!$A$5:$A$167)-ROW('Licence Chemicals'!$A$4:$I$4)),IFERROR(('Licence Chemicals'!$A$5:$A$167=$J$4),FALSE)),ROWS($L$22:L72)),"""")), 1, 1)"),"")
B73: =IF($L73="","",ROWS($L$22:L73)) | C73: {=IF($L73="","",INDEX('Licence Chemicals'!$D$5:$D$167,$L73)&"")} | D73: {=IF($L73="","",INDEX('Licence Chemicals'!$E$5:$E$167,$L73)&"")} | E73: {=IF($L73="","",IF(INDEX('Licence Chemicals'!$F$5:$F$167,$L73)="","Industrial Chemical",INDEX('Licence Chemicals'!$F$5:$F$167,$L73)&""))} | L73: =IFERROR(__xludf.DUMMYFUNCTION("ARRAY_CONSTRAIN(ARRAYFORMULA(IFERROR(SMALL(FILTER((ROW('Licence Chemicals'!$A$5:$A$167)-ROW('Licence Chemicals'!$A$4:$I$4)),IFERROR(('Licence Chemicals'!$A$5:$A$167=$J$4),FALSE)),ROWS($L$22:L73)),"""")), 1, 1)"),"")
B74: =IF($L74="","",ROWS($L$22:L74)) | C74: {=IF($L74="","",INDEX('Licence Chemicals'!$D$5:$D$167,$L74)&"")} | D74: {=IF($L74="","",INDEX('Licence Chemicals'!$E$5:$E$167,$L74)&"")} | E74: {=IF($L74="","",IF(INDEX('Licence Chemicals'!$F$5:$F$167,$L74)="","Industrial Chemical",INDEX('Licence Chemicals'!$F$5:$F$167,$L74)&""))} | L74: =IFERROR(__xludf.DUMMYFUNCTION("ARRAY_CONSTRAIN(ARRAYFORMULA(IFERROR(SMALL(FILTER((ROW('Licence Chemicals'!$A$5:$A$167)-ROW('Licence Chemicals'!$A$4:$I$4)),IFERROR(('Licence Chemicals'!$A$5:$A$167=$J$4),FALSE)),ROWS($L$22:L74)),"""")), 1, 1)"),"")
B75: =IF($L75="","",ROWS($L$22:L75)) | C75: {=IF($L75="","",INDEX('Licence Chemicals'!$D$5:$D$167,$L75)&"")} | D75: {=IF($L75="","",INDEX('Licence Chemicals'!$E$5:$E$167,$L75)&"")} | E75: {=IF($L75="","",IF(INDEX('Licence Chemicals'!$F$5:$F$167,$L75)="","Industrial Chemical",INDEX('Licence Chemicals'!$F$5:$F$167,$L75)&""))} | L75: =IFERROR(__xludf.DUMMYFUNCTION("ARRAY_CONSTRAIN(ARRAYFORMULA(IFERROR(SMALL(FILTER((ROW('Licence Chemicals'!$A$5:$A$167)-ROW('Licence Chemicals'!$A$4:$I$4)),IFERROR(('Licence Chemicals'!$A$5:$A$167=$J$4),FALSE)),ROWS($L$22:L75)),"""")), 1, 1)"),"")
B76: =IF($L76="","",ROWS($L$22:L76)) | C76: {=IF($L76="","",INDEX('Licence Chemicals'!$D$5:$D$167,$L76)&"")} | D76: {=IF($L76="","",INDEX('Licence Chemicals'!$E$5:$E$167,$L76)&"")} | E76: {=IF($L76="","",IF(INDEX('Licence Chemicals'!$F$5:$F$167,$L76)="","Industrial Chemical",INDEX('Licence Chemicals'!$F$5:$F$167,$L76)&""))} | L76: =IFERROR(__xludf.DUMMYFUNCTION("ARRAY_CONSTRAIN(ARRAYFORMULA(IFERROR(SMALL(FILTER((ROW('Licence Chemicals'!$A$5:$A$167)-ROW('Licence Chemicals'!$A$4:$I$4)),IFERROR(('Licence Chemicals'!$A$5:$A$167=$J$4),FALSE)),ROWS($L$22:L76)),"""")), 1, 1)"),"")
B77: =IF($L77="","",ROWS($L$22:L77)) | C77: {=IF($L77="","",INDEX('Licence Chemicals'!$D$5:$D$167,$L77)&"")} | D77: {=IF($L77="","",INDEX('Licence Chemicals'!$E$5:$E$167,$L77)&"")} | E77: {=IF($L77="","",IF(INDEX('Licence Chemicals'!$F$5:$F$167,$L77)="","Industrial Chemical",INDEX('Licence Chemicals'!$F$5:$F$167,$L77)&""))} | L77: =IFERROR(__xludf.DUMMYFUNCTION("ARRAY_CONSTRAIN(ARRAYFORMULA(IFERROR(SMALL(FILTER((ROW('Licence Chemicals'!$A$5:$A$167)-ROW('Licence Chemicals'!$A$4:$I$4)),IFERROR(('Licence Chemicals'!$A$5:$A$167=$J$4),FALSE)),ROWS($L$22:L77)),"""")), 1, 1)"),"")
B78: =IF($L78="","",ROWS($L$22:L78)) | C78: {=IF($L78="","",INDEX('Licence Chemicals'!$D$5:$D$167,$L78)&"")} | D78: {=IF($L78="","",INDEX('Licence Chemicals'!$E$5:$E$167,$L78)&"")} | E78: {=IF($L78="","",IF(INDEX('Licence Chemicals'!$F$5:$F$167,$L78)="","Industrial Chemical",INDEX('Licence Chemicals'!$F$5:$F$167,$L78)&""))} | L78: =IFERROR(__xludf.DUMMYFUNCTION("ARRAY_CONSTRAIN(ARRAYFORMULA(IFERROR(SMALL(FILTER((ROW('Licence Chemicals'!$A$5:$A$167)-ROW('Licence Chemicals'!$A$4:$I$4)),IFERROR(('Licence Chemicals'!$A$5:$A$167=$J$4),FALSE)),ROWS($L$22:L78)),"""")), 1, 1)"),"")
B79: =IF($L79="","",ROWS($L$22:L79)) | C79: {=IF($L79="","",INDEX('Licence Chemicals'!$D$5:$D$167,$L79)&"")} | D79: {=IF($L79="","",INDEX('Licence Chemicals'!$E$5:$E$167,$L79)&"")} | E79: {=IF($L79="","",IF(INDEX('Licence Chemicals'!$F$5:$F$167,$L79)="","Industrial Chemical",INDEX('Licence Chemicals'!$F$5:$F$167,$L79)&""))} | L79: =IFERROR(__xludf.DUMMYFUNCTION("ARRAY_CONSTRAIN(ARRAYFORMULA(IFERROR(SMALL(FILTER((ROW('Licence Chemicals'!$A$5:$A$167)-ROW('Licence Chemicals'!$A$4:$I$4)),IFERROR(('Licence Chemicals'!$A$5:$A$167=$J$4),FALSE)),ROWS($L$22:L79)),"""")), 1, 1)"),"")
B80: =IF($L80="","",ROWS($L$22:L80)) | C80: {=IF($L80="","",INDEX('Licence Chemicals'!$D$5:$D$167,$L80)&"")} | D80: {=IF($L80="","",INDEX('Licence Chemicals'!$E$5:$E$167,$L80)&"")} | E80: {=IF($L80="","",IF(INDEX('Licence Chemicals'!$F$5:$F$167,$L80)="","Industrial Chemical",INDEX('Licence Chemicals'!$F$5:$F$167,$L80)&""))} | L80: =IFERROR(__xludf.DUMMYFUNCTION("ARRAY_CONSTRAIN(ARRAYFORMULA(IFERROR(SMALL(FILTER((ROW('Licence Chemicals'!$A$5:$A$167)-ROW('Licence Chemicals'!$A$4:$I$4)),IFERROR(('Licence Chemicals'!$A$5:$A$167=$J$4),FALSE)),ROWS($L$22:L80)),"""")), 1, 1)"),"")
B81: =IF($L81="","",ROWS($L$22:L81)) | C81: {=IF($L81="","",INDEX('Licence Chemicals'!$D$5:$D$167,$L81)&"")} | D81: {=IF($L81="","",INDEX('Licence Chemicals'!$E$5:$E$167,$L81)&"")} | E81: {=IF($L81="","",IF(INDEX('Licence Chemicals'!$F$5:$F$167,$L81)="","Industrial Chemical",INDEX('Licence Chemicals'!$F$5:$F$167,$L81)&""))} | L81: =IFERROR(__xludf.DUMMYFUNCTION("ARRAY_CONSTRAIN(ARRAYFORMULA(IFERROR(SMALL(FILTER((ROW('Licence Chemicals'!$A$5:$A$167)-ROW('Licence Chemicals'!$A$4:$I$4)),IFERROR(('Licence Chemicals'!$A$5:$A$167=$J$4),FALSE)),ROWS($L$22:L81)),"""")), 1, 1)"),"")
B83: CONDITIONS
B84: 1 | C84: This license does not apply to the importation of chemicals, it applies only to the registration of the chemicals listed in the application letter;
B85: 2 | C85: Issuance of this license does not authorize the licensee to import any of the listed chemicals without obtaining chemical importation licenses from the EPA. A chemical importation license must be obtained from the Agency prior to the importation of any of the listed chemicals;
B86: 3 | C86: Any importation without prior approval from the Agency is a violation of this license condition and will incur a penalty consistent with Section 112 of the Environmental Protection and Management Law of Liberia;
B87: 4 | C87: This license only applies to the chemicals specified in the application, additional chemicals must be declared and registered with the EPA.
B89: ="Issued Date: "&IF($J$10="","________",DAY($J$10)&IF(AND(DAY($J$10)>=11,DAY($J$10)<=13),"th",CHOOSE(MIN(MOD(DAY($J$10),10)+1,5),"th","st","nd","rd","th"))&" "&TEXT($J$10,"mmmm, yyyy")) -> Issued Date: ________ | D89: ="Expired Date: "&IF($J$11="","________",DAY($J$11)&IF(AND(DAY($J$11)>=11,DAY($J$11)<=13),"th",CHOOSE(MIN(MOD(DAY($J$11),10)+1,5),"th","st","nd","rd","th"))&" "&TEXT($J$11,"mmmm, yyyy")) -> Expired Date: ________
B91: _____________________________________________
B92: {=IFERROR(INDEX(Lists!$U$5:$U$7,MATCH($J$13,Lists!$T$5:$T$7,0)),"")} -> Dr. Emmanuel K. Urey Yarkpawolo
B93: {=IFERROR(INDEX(Lists!$V$5:$V$7,MATCH($J$13,Lists!$T$5:$T$7,0)),"")} -> EXECUTIVE DIRECTOR/CEO

Sheet Print CIL
B2: =IF($J$3="No","",setLetterhead_1) -> REPUBLIC OF LIBERIA | I2: PRINT – CHEMICAL IMPORTATION LICENSE
B3: =IF($J$3="No","",setLetterhead_2) -> ENVIRONMENTAL PROTECTION AGENCY | I3: Print letterhead ▶ | J3: Yes
B4: =IF($J$3="No","",setLetterhead_3) -> P.O. Box 4024 | I4: Licence Record ID ▶ | J4: LIC-027
B5: =IF($J$3="No","",setLetterhead_4) -> Bright Building 302-A, Sekou Toure Avenue, Mamba Point | I5: Check | J5: {=IF($J$4="","Choose a licence record",IF($J$6="","⚠ Record not found",IF(ISNUMBER(SEARCH("CIL",INDEX('Licences & Certificates'!$E$5:$E$73,$J$6))),IF(INDEX('Licences & Certificates'!$K$5:$K$73,$J$6)="","⚠ No licence number yet","✔ Ready to print"),"⚠ This record is "&INDEX('Licences & Certificates'!$E$5:$E$73,$J$6))))} -> ✔ Ready to print
B6: =IF($J$3="No","",setLetterhead_5) -> 1000 Monrovia, 10 Liberia | I6: (row in register) | J6: =IFERROR(MATCH($J$4,'Licences & Certificates'!$A$5:$A$73,0),"") -> 26
I7: Licence No.
I8: Company | J8: {=IF($J$6="","",INDEX('Licences & Certificates'!$C$5:$C$73,$J$6))} -> Bea Mountain Mining Corporation (BMMC)
B9: =IF($J$7="","License No. ________","License No. "&$J$7) -> License No. ________ | I9: Location | J9: {=IF($J$6="","",IF(INDEX('Licences & Certificates'!$G$5:$G$73,$J$6)<>"",INDEX('Licences & Certificates'!$G$5:$G$73,$J$6),IFERROR(INDEX(Companies!$D$5:$D$74,MATCH(INDEX('Licences & Certificates'!$B$5:$B$73,$J$6),Companies!$A$5:$A$74,0))&"","")))} -> Monrovia, Liberia
I10: Date Issued | J10: {=IF($J$6="","",IF(INDEX('Licences & Certificates'!$L$5:$L$73,$J$6)="","",INDEX('Licences & Certificates'!$L$5:$L$73,$J$6)))} -> 46037
B11: CHEMICAL IMPORTATION LICENSE | I11: Expiry Date | J11: {=IF($J$6="","",IF(INDEX('Licences & Certificates'!$M$5:$M$73,$J$6)="","",INDEX('Licences & Certificates'!$M$5:$M$73,$J$6)))} -> 46387
B12: (Issued under Part II Section VI of the EPA Act) | I12: Chemical lines found | J12: =COUNTIF('Licence Chemicals'!$A$5:$A$167,$J$4) -> 0
I13: Signed by ▶ | J13: Executive Director
B14: This is to certify that | I14: How to use: pick the Licence Record ID in J4 and choose who signs. Add the chemicals for that licence on the 'Licence Chemicals' sheet. Then use the OUTPUT buttons on the right – empty table rows are left out automatically. Set 'Print letterhead' (J3) to No when printing on pre-printed EPA letterhead paper – the letterhead text and logos are left off, keeping the same space at the top.
B15: =UPPER($J$8) -> BEA MOUNTAIN MINING CORPORATION (BMMC)
B16: =IF($J$9="","","(Located at "&$J$9&")") -> (Located at Monrovia, Liberia)
B18: Is hereby granted this Chemical Importation License, pursuant to Part 5 Section 51-53 of the Environmental Protection and Management Laws of Liberia and Section 5.5 of the National Environmental Policy of Liberia, for the importation of the following chemical within the territorial boundaries of the Republic of Liberia subject to the EPA Act, the Chemical Guideline of Liberia and conditions specified in this license.
B20: PRODUCT INFORMATION
B21: No. | C21: Trade or IUPAC Name | D21: EPA / Registration #. | E21: Stipulated Qty (kg/L) | F21: Consignment Reference (BL/IPD No.) | L21: helper
B22: =IF($L22="","",ROWS($L$22:L22)) | C22: {=IF($L22="","",INDEX('Licence Chemicals'!$D$5:$D$167,$L22)&"")} | D22: {=IF($L22="","",INDEX('Licence Chemicals'!$E$5:$E$167,$L22)&"")} | E22: {=IF($L22="","",IF(INDEX('Licence Chemicals'!$G$5:$G$167,$L22)="","",TEXT(INDEX('Licence Chemicals'!$G$5:$G$167,$L22),"#,##0.##")&" "&INDEX('Licence Chemicals'!$H$5:$H$167,$L22)))} | F22: {=IF($L22="","",IF(INDEX('Licence Chemicals'!$I$5:$I$167,$L22)="","To Be Provided",INDEX('Licence Chemicals'!$I$5:$I$167,$L22)&""))} | L22: =IFERROR(__xludf.DUMMYFUNCTION("ARRAY_CONSTRAIN(ARRAYFORMULA(IFERROR(SMALL(FILTER((ROW('Licence Chemicals'!$A$5:$A$167)-ROW('Licence Chemicals'!$A$4:$I$4)),IFERROR(('Licence Chemicals'!$A$5:$A$167=$J$4),FALSE)),ROWS($L$22:L22)),"""")), 1, 1)"),"")
B23: =IF($L23="","",ROWS($L$22:L23)) | C23: {=IF($L23="","",INDEX('Licence Chemicals'!$D$5:$D$167,$L23)&"")} | D23: {=IF($L23="","",INDEX('Licence Chemicals'!$E$5:$E$167,$L23)&"")} | E23: {=IF($L23="","",IF(INDEX('Licence Chemicals'!$G$5:$G$167,$L23)="","",TEXT(INDEX('Licence Chemicals'!$G$5:$G$167,$L23),"#,##0.##")&" "&INDEX('Licence Chemicals'!$H$5:$H$167,$L23)))} | F23: {=IF($L23="","",IF(INDEX('Licence Chemicals'!$I$5:$I$167,$L23)="","To Be Provided",INDEX('Licence Chemicals'!$I$5:$I$167,$L23)&""))} | L23: =IFERROR(__xludf.DUMMYFUNCTION("ARRAY_CONSTRAIN(ARRAYFORMULA(IFERROR(SMALL(FILTER((ROW('Licence Chemicals'!$A$5:$A$167)-ROW('Licence Chemicals'!$A$4:$I$4)),IFERROR(('Licence Chemicals'!$A$5:$A$167=$J$4),FALSE)),ROWS($L$22:L23)),"""")), 1, 1)"),"")
B24: =IF($L24="","",ROWS($L$22:L24)) | C24: {=IF($L24="","",INDEX('Licence Chemicals'!$D$5:$D$167,$L24)&"")} | D24: {=IF($L24="","",INDEX('Licence Chemicals'!$E$5:$E$167,$L24)&"")} | E24: {=IF($L24="","",IF(INDEX('Licence Chemicals'!$G$5:$G$167,$L24)="","",TEXT(INDEX('Licence Chemicals'!$G$5:$G$167,$L24),"#,##0.##")&" "&INDEX('Licence Chemicals'!$H$5:$H$167,$L24)))} | F24: {=IF($L24="","",IF(INDEX('Licence Chemicals'!$I$5:$I$167,$L24)="","To Be Provided",INDEX('Licence Chemicals'!$I$5:$I$167,$L24)&""))} | L24: =IFERROR(__xludf.DUMMYFUNCTION("ARRAY_CONSTRAIN(ARRAYFORMULA(IFERROR(SMALL(FILTER((ROW('Licence Chemicals'!$A$5:$A$167)-ROW('Licence Chemicals'!$A$4:$I$4)),IFERROR(('Licence Chemicals'!$A$5:$A$167=$J$4),FALSE)),ROWS($L$22:L24)),"""")), 1, 1)"),"")
B25: =IF($L25="","",ROWS($L$22:L25)) | C25: {=IF($L25="","",INDEX('Licence Chemicals'!$D$5:$D$167,$L25)&"")} | D25: {=IF($L25="","",INDEX('Licence Chemicals'!$E$5:$E$167,$L25)&"")} | E25: {=IF($L25="","",IF(INDEX('Licence Chemicals'!$G$5:$G$167,$L25)="","",TEXT(INDEX('Licence Chemicals'!$G$5:$G$167,$L25),"#,##0.##")&" "&INDEX('Licence Chemicals'!$H$5:$H$167,$L25)))} | F25: {=IF($L25="","",IF(INDEX('Licence Chemicals'!$I$5:$I$167,$L25)="","To Be Provided",INDEX('Licence Chemicals'!$I$5:$I$167,$L25)&""))} | L25: =IFERROR(__xludf.DUMMYFUNCTION("ARRAY_CONSTRAIN(ARRAYFORMULA(IFERROR(SMALL(FILTER((ROW('Licence Chemicals'!$A$5:$A$167)-ROW('Licence Chemicals'!$A$4:$I$4)),IFERROR(('Licence Chemicals'!$A$5:$A$167=$J$4),FALSE)),ROWS($L$22:L25)),"""")), 1, 1)"),"")
B26: =IF($L26="","",ROWS($L$22:L26)) | C26: {=IF($L26="","",INDEX('Licence Chemicals'!$D$5:$D$167,$L26)&"")} | D26: {=IF($L26="","",INDEX('Licence Chemicals'!$E$5:$E$167,$L26)&"")} | E26: {=IF($L26="","",IF(INDEX('Licence Chemicals'!$G$5:$G$167,$L26)="","",TEXT(INDEX('Licence Chemicals'!$G$5:$G$167,$L26),"#,##0.##")&" "&INDEX('Licence Chemicals'!$H$5:$H$167,$L26)))} | F26: {=IF($L26="","",IF(INDEX('Licence Chemicals'!$I$5:$I$167,$L26)="","To Be Provided",INDEX('Licence Chemicals'!$I$5:$I$167,$L26)&""))} | L26: =IFERROR(__xludf.DUMMYFUNCTION("ARRAY_CONSTRAIN(ARRAYFORMULA(IFERROR(SMALL(FILTER((ROW('Licence Chemicals'!$A$5:$A$167)-ROW('Licence Chemicals'!$A$4:$I$4)),IFERROR(('Licence Chemicals'!$A$5:$A$167=$J$4),FALSE)),ROWS($L$22:L26)),"""")), 1, 1)"),"")
B27: =IF($L27="","",ROWS($L$22:L27)) | C27: {=IF($L27="","",INDEX('Licence Chemicals'!$D$5:$D$167,$L27)&"")} | D27: {=IF($L27="","",INDEX('Licence Chemicals'!$E$5:$E$167,$L27)&"")} | E27: {=IF($L27="","",IF(INDEX('Licence Chemicals'!$G$5:$G$167,$L27)="","",TEXT(INDEX('Licence Chemicals'!$G$5:$G$167,$L27),"#,##0.##")&" "&INDEX('Licence Chemicals'!$H$5:$H$167,$L27)))} | F27: {=IF($L27="","",IF(INDEX('Licence Chemicals'!$I$5:$I$167,$L27)="","To Be Provided",INDEX('Licence Chemicals'!$I$5:$I$167,$L27)&""))} | L27: =IFERROR(__xludf.DUMMYFUNCTION("ARRAY_CONSTRAIN(ARRAYFORMULA(IFERROR(SMALL(FILTER((ROW('Licence Chemicals'!$A$5:$A$167)-ROW('Licence Chemicals'!$A$4:$I$4)),IFERROR(('Licence Chemicals'!$A$5:$A$167=$J$4),FALSE)),ROWS($L$22:L27)),"""")), 1, 1)"),"")
B28: =IF($L28="","",ROWS($L$22:L28)) | C28: {=IF($L28="","",INDEX('Licence Chemicals'!$D$5:$D$167,$L28)&"")} | D28: {=IF($L28="","",INDEX('Licence Chemicals'!$E$5:$E$167,$L28)&"")} | E28: {=IF($L28="","",IF(INDEX('Licence Chemicals'!$G$5:$G$167,$L28)="","",TEXT(INDEX('Licence Chemicals'!$G$5:$G$167,$L28),"#,##0.##")&" "&INDEX('Licence Chemicals'!$H$5:$H$167,$L28)))} | F28: {=IF($L28="","",IF(INDEX('Licence Chemicals'!$I$5:$I$167,$L28)="","To Be Provided",INDEX('Licence Chemicals'!$I$5:$I$167,$L28)&""))} | L28: =IFERROR(__xludf.DUMMYFUNCTION("ARRAY_CONSTRAIN(ARRAYFORMULA(IFERROR(SMALL(FILTER((ROW('Licence Chemicals'!$A$5:$A$167)-ROW('Licence Chemicals'!$A$4:$I$4)),IFERROR(('Licence Chemicals'!$A$5:$A$167=$J$4),FALSE)),ROWS($L$22:L28)),"""")), 1, 1)"),"")
B29: =IF($L29="","",ROWS($L$22:L29)) | C29: {=IF($L29="","",INDEX('Licence Chemicals'!$D$5:$D$167,$L29)&"")} | D29: {=IF($L29="","",INDEX('Licence Chemicals'!$E$5:$E$167,$L29)&"")} | E29: {=IF($L29="","",IF(INDEX('Licence Chemicals'!$G$5:$G$167,$L29)="","",TEXT(INDEX('Licence Chemicals'!$G$5:$G$167,$L29),"#,##0.##")&" "&INDEX('Licence Chemicals'!$H$5:$H$167,$L29)))} | F29: {=IF($L29="","",IF(INDEX('Licence Chemicals'!$I$5:$I$167,$L29)="","To Be Provided",INDEX('Licence Chemicals'!$I$5:$I$167,$L29)&""))} | L29: =IFERROR(__xludf.DUMMYFUNCTION("ARRAY_CONSTRAIN(ARRAYFORMULA(IFERROR(SMALL(FILTER((ROW('Licence Chemicals'!$A$5:$A$167)-ROW('Licence Chemicals'!$A$4:$I$4)),IFERROR(('Licence Chemicals'!$A$5:$A$167=$J$4),FALSE)),ROWS($L$22:L29)),"""")), 1, 1)"),"")
B30: =IF($L30="","",ROWS($L$22:L30)) | C30: {=IF($L30="","",INDEX('Licence Chemicals'!$D$5:$D$167,$L30)&"")} | D30: {=IF($L30="","",INDEX('Licence Chemicals'!$E$5:$E$167,$L30)&"")} | E30: {=IF($L30="","",IF(INDEX('Licence Chemicals'!$G$5:$G$167,$L30)="","",TEXT(INDEX('Licence Chemicals'!$G$5:$G$167,$L30),"#,##0.##")&" "&INDEX('Licence Chemicals'!$H$5:$H$167,$L30)))} | F30: {=IF($L30="","",IF(INDEX('Licence Chemicals'!$I$5:$I$167,$L30)="","To Be Provided",INDEX('Licence Chemicals'!$I$5:$I$167,$L30)&""))} | L30: =IFERROR(__xludf.DUMMYFUNCTION("ARRAY_CONSTRAIN(ARRAYFORMULA(IFERROR(SMALL(FILTER((ROW('Licence Chemicals'!$A$5:$A$167)-ROW('Licence Chemicals'!$A$4:$I$4)),IFERROR(('Licence Chemicals'!$A$5:$A$167=$J$4),FALSE)),ROWS($L$22:L30)),"""")), 1, 1)"),"")
B31: =IF($L31="","",ROWS($L$22:L31)) | C31: {=IF($L31="","",INDEX('Licence Chemicals'!$D$5:$D$167,$L31)&"")} | D31: {=IF($L31="","",INDEX('Licence Chemicals'!$E$5:$E$167,$L31)&"")} | E31: {=IF($L31="","",IF(INDEX('Licence Chemicals'!$G$5:$G$167,$L31)="","",TEXT(INDEX('Licence Chemicals'!$G$5:$G$167,$L31),"#,##0.##")&" "&INDEX('Licence Chemicals'!$H$5:$H$167,$L31)))} | F31: {=IF($L31="","",IF(INDEX('Licence Chemicals'!$I$5:$I$167,$L31)="","To Be Provided",INDEX('Licence Chemicals'!$I$5:$I$167,$L31)&""))} | L31: =IFERROR(__xludf.DUMMYFUNCTION("ARRAY_CONSTRAIN(ARRAYFORMULA(IFERROR(SMALL(FILTER((ROW('Licence Chemicals'!$A$5:$A$167)-ROW('Licence Chemicals'!$A$4:$I$4)),IFERROR(('Licence Chemicals'!$A$5:$A$167=$J$4),FALSE)),ROWS($L$22:L31)),"""")), 1, 1)"),"")
B32: =IF($L32="","",ROWS($L$22:L32)) | C32: {=IF($L32="","",INDEX('Licence Chemicals'!$D$5:$D$167,$L32)&"")} | D32: {=IF($L32="","",INDEX('Licence Chemicals'!$E$5:$E$167,$L32)&"")} | E32: {=IF($L32="","",IF(INDEX('Licence Chemicals'!$G$5:$G$167,$L32)="","",TEXT(INDEX('Licence Chemicals'!$G$5:$G$167,$L32),"#,##0.##")&" "&INDEX('Licence Chemicals'!$H$5:$H$167,$L32)))} | F32: {=IF($L32="","",IF(INDEX('Licence Chemicals'!$I$5:$I$167,$L32)="","To Be Provided",INDEX('Licence Chemicals'!$I$5:$I$167,$L32)&""))} | L32: =IFERROR(__xludf.DUMMYFUNCTION("ARRAY_CONSTRAIN(ARRAYFORMULA(IFERROR(SMALL(FILTER((ROW('Licence Chemicals'!$A$5:$A$167)-ROW('Licence Chemicals'!$A$4:$I$4)),IFERROR(('Licence Chemicals'!$A$5:$A$167=$J$4),FALSE)),ROWS($L$22:L32)),"""")), 1, 1)"),"")
B33: =IF($L33="","",ROWS($L$22:L33)) | C33: {=IF($L33="","",INDEX('Licence Chemicals'!$D$5:$D$167,$L33)&"")} | D33: {=IF($L33="","",INDEX('Licence Chemicals'!$E$5:$E$167,$L33)&"")} | E33: {=IF($L33="","",IF(INDEX('Licence Chemicals'!$G$5:$G$167,$L33)="","",TEXT(INDEX('Licence Chemicals'!$G$5:$G$167,$L33),"#,##0.##")&" "&INDEX('Licence Chemicals'!$H$5:$H$167,$L33)))} | F33: {=IF($L33="","",IF(INDEX('Licence Chemicals'!$I$5:$I$167,$L33)="","To Be Provided",INDEX('Licence Chemicals'!$I$5:$I$167,$L33)&""))} | L33: =IFERROR(__xludf.DUMMYFUNCTION("ARRAY_CONSTRAIN(ARRAYFORMULA(IFERROR(SMALL(FILTER((ROW('Licence Chemicals'!$A$5:$A$167)-ROW('Licence Chemicals'!$A$4:$I$4)),IFERROR(('Licence Chemicals'!$A$5:$A$167=$J$4),FALSE)),ROWS($L$22:L33)),"""")), 1, 1)"),"")
B34: =IF($L34="","",ROWS($L$22:L34)) | C34: {=IF($L34="","",INDEX('Licence Chemicals'!$D$5:$D$167,$L34)&"")} | D34: {=IF($L34="","",INDEX('Licence Chemicals'!$E$5:$E$167,$L34)&"")} | E34: {=IF($L34="","",IF(INDEX('Licence Chemicals'!$G$5:$G$167,$L34)="","",TEXT(INDEX('Licence Chemicals'!$G$5:$G$167,$L34),"#,##0.##")&" "&INDEX('Licence Chemicals'!$H$5:$H$167,$L34)))} | F34: {=IF($L34="","",IF(INDEX('Licence Chemicals'!$I$5:$I$167,$L34)="","To Be Provided",INDEX('Licence Chemicals'!$I$5:$I$167,$L34)&""))} | L34: =IFERROR(__xludf.DUMMYFUNCTION("ARRAY_CONSTRAIN(ARRAYFORMULA(IFERROR(SMALL(FILTER((ROW('Licence Chemicals'!$A$5:$A$167)-ROW('Licence Chemicals'!$A$4:$I$4)),IFERROR(('Licence Chemicals'!$A$5:$A$167=$J$4),FALSE)),ROWS($L$22:L34)),"""")), 1, 1)"),"")
B35: =IF($L35="","",ROWS($L$22:L35)) | C35: {=IF($L35="","",INDEX('Licence Chemicals'!$D$5:$D$167,$L35)&"")} | D35: {=IF($L35="","",INDEX('Licence Chemicals'!$E$5:$E$167,$L35)&"")} | E35: {=IF($L35="","",IF(INDEX('Licence Chemicals'!$G$5:$G$167,$L35)="","",TEXT(INDEX('Licence Chemicals'!$G$5:$G$167,$L35),"#,##0.##")&" "&INDEX('Licence Chemicals'!$H$5:$H$167,$L35)))} | F35: {=IF($L35="","",IF(INDEX('Licence Chemicals'!$I$5:$I$167,$L35)="","To Be Provided",INDEX('Licence Chemicals'!$I$5:$I$167,$L35)&""))} | L35: =IFERROR(__xludf.DUMMYFUNCTION("ARRAY_CONSTRAIN(ARRAYFORMULA(IFERROR(SMALL(FILTER((ROW('Licence Chemicals'!$A$5:$A$167)-ROW('Licence Chemicals'!$A$4:$I$4)),IFERROR(('Licence Chemicals'!$A$5:$A$167=$J$4),FALSE)),ROWS($L$22:L35)),"""")), 1, 1)"),"")
B36: =IF($L36="","",ROWS($L$22:L36)) | C36: {=IF($L36="","",INDEX('Licence Chemicals'!$D$5:$D$167,$L36)&"")} | D36: {=IF($L36="","",INDEX('Licence Chemicals'!$E$5:$E$167,$L36)&"")} | E36: {=IF($L36="","",IF(INDEX('Licence Chemicals'!$G$5:$G$167,$L36)="","",TEXT(INDEX('Licence Chemicals'!$G$5:$G$167,$L36),"#,##0.##")&" "&INDEX('Licence Chemicals'!$H$5:$H$167,$L36)))} | F36: {=IF($L36="","",IF(INDEX('Licence Chemicals'!$I$5:$I$167,$L36)="","To Be Provided",INDEX('Licence Chemicals'!$I$5:$I$167,$L36)&""))} | L36: =IFERROR(__xludf.DUMMYFUNCTION("ARRAY_CONSTRAIN(ARRAYFORMULA(IFERROR(SMALL(FILTER((ROW('Licence Chemicals'!$A$5:$A$167)-ROW('Licence Chemicals'!$A$4:$I$4)),IFERROR(('Licence Chemicals'!$A$5:$A$167=$J$4),FALSE)),ROWS($L$22:L36)),"""")), 1, 1)"),"")
B37: =IF($L37="","",ROWS($L$22:L37)) | C37: {=IF($L37="","",INDEX('Licence Chemicals'!$D$5:$D$167,$L37)&"")} | D37: {=IF($L37="","",INDEX('Licence Chemicals'!$E$5:$E$167,$L37)&"")} | E37: {=IF($L37="","",IF(INDEX('Licence Chemicals'!$G$5:$G$167,$L37)="","",TEXT(INDEX('Licence Chemicals'!$G$5:$G$167,$L37),"#,##0.##")&" "&INDEX('Licence Chemicals'!$H$5:$H$167,$L37)))} | F37: {=IF($L37="","",IF(INDEX('Licence Chemicals'!$I$5:$I$167,$L37)="","To Be Provided",INDEX('Licence Chemicals'!$I$5:$I$167,$L37)&""))} | L37: =IFERROR(__xludf.DUMMYFUNCTION("ARRAY_CONSTRAIN(ARRAYFORMULA(IFERROR(SMALL(FILTER((ROW('Licence Chemicals'!$A$5:$A$167)-ROW('Licence Chemicals'!$A$4:$I$4)),IFERROR(('Licence Chemicals'!$A$5:$A$167=$J$4),FALSE)),ROWS($L$22:L37)),"""")), 1, 1)"),"")
B38: =IF($L38="","",ROWS($L$22:L38)) | C38: {=IF($L38="","",INDEX('Licence Chemicals'!$D$5:$D$167,$L38)&"")} | D38: {=IF($L38="","",INDEX('Licence Chemicals'!$E$5:$E$167,$L38)&"")} | E38: {=IF($L38="","",IF(INDEX('Licence Chemicals'!$G$5:$G$167,$L38)="","",TEXT(INDEX('Licence Chemicals'!$G$5:$G$167,$L38),"#,##0.##")&" "&INDEX('Licence Chemicals'!$H$5:$H$167,$L38)))} | F38: {=IF($L38="","",IF(INDEX('Licence Chemicals'!$I$5:$I$167,$L38)="","To Be Provided",INDEX('Licence Chemicals'!$I$5:$I$167,$L38)&""))} | L38: =IFERROR(__xludf.DUMMYFUNCTION("ARRAY_CONSTRAIN(ARRAYFORMULA(IFERROR(SMALL(FILTER((ROW('Licence Chemicals'!$A$5:$A$167)-ROW('Licence Chemicals'!$A$4:$I$4)),IFERROR(('Licence Chemicals'!$A$5:$A$167=$J$4),FALSE)),ROWS($L$22:L38)),"""")), 1, 1)"),"")
B39: =IF($L39="","",ROWS($L$22:L39)) | C39: {=IF($L39="","",INDEX('Licence Chemicals'!$D$5:$D$167,$L39)&"")} | D39: {=IF($L39="","",INDEX('Licence Chemicals'!$E$5:$E$167,$L39)&"")} | E39: {=IF($L39="","",IF(INDEX('Licence Chemicals'!$G$5:$G$167,$L39)="","",TEXT(INDEX('Licence Chemicals'!$G$5:$G$167,$L39),"#,##0.##")&" "&INDEX('Licence Chemicals'!$H$5:$H$167,$L39)))} | F39: {=IF($L39="","",IF(INDEX('Licence Chemicals'!$I$5:$I$167,$L39)="","To Be Provided",INDEX('Licence Chemicals'!$I$5:$I$167,$L39)&""))} | L39: =IFERROR(__xludf.DUMMYFUNCTION("ARRAY_CONSTRAIN(ARRAYFORMULA(IFERROR(SMALL(FILTER((ROW('Licence Chemicals'!$A$5:$A$167)-ROW('Licence Chemicals'!$A$4:$I$4)),IFERROR(('Licence Chemicals'!$A$5:$A$167=$J$4),FALSE)),ROWS($L$22:L39)),"""")), 1, 1)"),"")
B40: =IF($L40="","",ROWS($L$22:L40)) | C40: {=IF($L40="","",INDEX('Licence Chemicals'!$D$5:$D$167,$L40)&"")} | D40: {=IF($L40="","",INDEX('Licence Chemicals'!$E$5:$E$167,$L40)&"")} | E40: {=IF($L40="","",IF(INDEX('Licence Chemicals'!$G$5:$G$167,$L40)="","",TEXT(INDEX('Licence Chemicals'!$G$5:$G$167,$L40),"#,##0.##")&" "&INDEX('Licence Chemicals'!$H$5:$H$167,$L40)))} | F40: {=IF($L40="","",IF(INDEX('Licence Chemicals'!$I$5:$I$167,$L40)="","To Be Provided",INDEX('Licence Chemicals'!$I$5:$I$167,$L40)&""))} | L40: =IFERROR(__xludf.DUMMYFUNCTION("ARRAY_CONSTRAIN(ARRAYFORMULA(IFERROR(SMALL(FILTER((ROW('Licence Chemicals'!$A$5:$A$167)-ROW('Licence Chemicals'!$A$4:$I$4)),IFERROR(('Licence Chemicals'!$A$5:$A$167=$J$4),FALSE)),ROWS($L$22:L40)),"""")), 1, 1)"),"")
B41: =IF($L41="","",ROWS($L$22:L41)) | C41: {=IF($L41="","",INDEX('Licence Chemicals'!$D$5:$D$167,$L41)&"")} | D41: {=IF($L41="","",INDEX('Licence Chemicals'!$E$5:$E$167,$L41)&"")} | E41: {=IF($L41="","",IF(INDEX('Licence Chemicals'!$G$5:$G$167,$L41)="","",TEXT(INDEX('Licence Chemicals'!$G$5:$G$167,$L41),"#,##0.##")&" "&INDEX('Licence Chemicals'!$H$5:$H$167,$L41)))} | F41: {=IF($L41="","",IF(INDEX('Licence Chemicals'!$I$5:$I$167,$L41)="","To Be Provided",INDEX('Licence Chemicals'!$I$5:$I$167,$L41)&""))} | L41: =IFERROR(__xludf.DUMMYFUNCTION("ARRAY_CONSTRAIN(ARRAYFORMULA(IFERROR(SMALL(FILTER((ROW('Licence Chemicals'!$A$5:$A$167)-ROW('Licence Chemicals'!$A$4:$I$4)),IFERROR(('Licence Chemicals'!$A$5:$A$167=$J$4),FALSE)),ROWS($L$22:L41)),"""")), 1, 1)"),"")
B42: =IF($L42="","",ROWS($L$22:L42)) | C42: {=IF($L42="","",INDEX('Licence Chemicals'!$D$5:$D$167,$L42)&"")} | D42: {=IF($L42="","",INDEX('Licence Chemicals'!$E$5:$E$167,$L42)&"")} | E42: {=IF($L42="","",IF(INDEX('Licence Chemicals'!$G$5:$G$167,$L42)="","",TEXT(INDEX('Licence Chemicals'!$G$5:$G$167,$L42),"#,##0.##")&" "&INDEX('Licence Chemicals'!$H$5:$H$167,$L42)))} | F42: {=IF($L42="","",IF(INDEX('Licence Chemicals'!$I$5:$I$167,$L42)="","To Be Provided",INDEX('Licence Chemicals'!$I$5:$I$167,$L42)&""))} | L42: =IFERROR(__xludf.DUMMYFUNCTION("ARRAY_CONSTRAIN(ARRAYFORMULA(IFERROR(SMALL(FILTER((ROW('Licence Chemicals'!$A$5:$A$167)-ROW('Licence Chemicals'!$A$4:$I$4)),IFERROR(('Licence Chemicals'!$A$5:$A$167=$J$4),FALSE)),ROWS($L$22:L42)),"""")), 1, 1)"),"")
B43: =IF($L43="","",ROWS($L$22:L43)) | C43: {=IF($L43="","",INDEX('Licence Chemicals'!$D$5:$D$167,$L43)&"")} | D43: {=IF($L43="","",INDEX('Licence Chemicals'!$E$5:$E$167,$L43)&"")} | E43: {=IF($L43="","",IF(INDEX('Licence Chemicals'!$G$5:$G$167,$L43)="","",TEXT(INDEX('Licence Chemicals'!$G$5:$G$167,$L43),"#,##0.##")&" "&INDEX('Licence Chemicals'!$H$5:$H$167,$L43)))} | F43: {=IF($L43="","",IF(INDEX('Licence Chemicals'!$I$5:$I$167,$L43)="","To Be Provided",INDEX('Licence Chemicals'!$I$5:$I$167,$L43)&""))} | L43: =IFERROR(__xludf.DUMMYFUNCTION("ARRAY_CONSTRAIN(ARRAYFORMULA(IFERROR(SMALL(FILTER((ROW('Licence Chemicals'!$A$5:$A$167)-ROW('Licence Chemicals'!$A$4:$I$4)),IFERROR(('Licence Chemicals'!$A$5:$A$167=$J$4),FALSE)),ROWS($L$22:L43)),"""")), 1, 1)"),"")
B44: =IF($L44="","",ROWS($L$22:L44)) | C44: {=IF($L44="","",INDEX('Licence Chemicals'!$D$5:$D$167,$L44)&"")} | D44: {=IF($L44="","",INDEX('Licence Chemicals'!$E$5:$E$167,$L44)&"")} | E44: {=IF($L44="","",IF(INDEX('Licence Chemicals'!$G$5:$G$167,$L44)="","",TEXT(INDEX('Licence Chemicals'!$G$5:$G$167,$L44),"#,##0.##")&" "&INDEX('Licence Chemicals'!$H$5:$H$167,$L44)))} | F44: {=IF($L44="","",IF(INDEX('Licence Chemicals'!$I$5:$I$167,$L44)="","To Be Provided",INDEX('Licence Chemicals'!$I$5:$I$167,$L44)&""))} | L44: =IFERROR(__xludf.DUMMYFUNCTION("ARRAY_CONSTRAIN(ARRAYFORMULA(IFERROR(SMALL(FILTER((ROW('Licence Chemicals'!$A$5:$A$167)-ROW('Licence Chemicals'!$A$4:$I$4)),IFERROR(('Licence Chemicals'!$A$5:$A$167=$J$4),FALSE)),ROWS($L$22:L44)),"""")), 1, 1)"),"")
B45: =IF($L45="","",ROWS($L$22:L45)) | C45: {=IF($L45="","",INDEX('Licence Chemicals'!$D$5:$D$167,$L45)&"")} | D45: {=IF($L45="","",INDEX('Licence Chemicals'!$E$5:$E$167,$L45)&"")} | E45: {=IF($L45="","",IF(INDEX('Licence Chemicals'!$G$5:$G$167,$L45)="","",TEXT(INDEX('Licence Chemicals'!$G$5:$G$167,$L45),"#,##0.##")&" "&INDEX('Licence Chemicals'!$H$5:$H$167,$L45)))} | F45: {=IF($L45="","",IF(INDEX('Licence Chemicals'!$I$5:$I$167,$L45)="","To Be Provided",INDEX('Licence Chemicals'!$I$5:$I$167,$L45)&""))} | L45: =IFERROR(__xludf.DUMMYFUNCTION("ARRAY_CONSTRAIN(ARRAYFORMULA(IFERROR(SMALL(FILTER((ROW('Licence Chemicals'!$A$5:$A$167)-ROW('Licence Chemicals'!$A$4:$I$4)),IFERROR(('Licence Chemicals'!$A$5:$A$167=$J$4),FALSE)),ROWS($L$22:L45)),"""")), 1, 1)"),"")
B46: =IF($L46="","",ROWS($L$22:L46)) | C46: {=IF($L46="","",INDEX('Licence Chemicals'!$D$5:$D$167,$L46)&"")} | D46: {=IF($L46="","",INDEX('Licence Chemicals'!$E$5:$E$167,$L46)&"")} | E46: {=IF($L46="","",IF(INDEX('Licence Chemicals'!$G$5:$G$167,$L46)="","",TEXT(INDEX('Licence Chemicals'!$G$5:$G$167,$L46),"#,##0.##")&" "&INDEX('Licence Chemicals'!$H$5:$H$167,$L46)))} | F46: {=IF($L46="","",IF(INDEX('Licence Chemicals'!$I$5:$I$167,$L46)="","To Be Provided",INDEX('Licence Chemicals'!$I$5:$I$167,$L46)&""))} | L46: =IFERROR(__xludf.DUMMYFUNCTION("ARRAY_CONSTRAIN(ARRAYFORMULA(IFERROR(SMALL(FILTER((ROW('Licence Chemicals'!$A$5:$A$167)-ROW('Licence Chemicals'!$A$4:$I$4)),IFERROR(('Licence Chemicals'!$A$5:$A$167=$J$4),FALSE)),ROWS($L$22:L46)),"""")), 1, 1)"),"")
B47: =IF($L47="","",ROWS($L$22:L47)) | C47: {=IF($L47="","",INDEX('Licence Chemicals'!$D$5:$D$167,$L47)&"")} | D47: {=IF($L47="","",INDEX('Licence Chemicals'!$E$5:$E$167,$L47)&"")} | E47: {=IF($L47="","",IF(INDEX('Licence Chemicals'!$G$5:$G$167,$L47)="","",TEXT(INDEX('Licence Chemicals'!$G$5:$G$167,$L47),"#,##0.##")&" "&INDEX('Licence Chemicals'!$H$5:$H$167,$L47)))} | F47: {=IF($L47="","",IF(INDEX('Licence Chemicals'!$I$5:$I$167,$L47)="","To Be Provided",INDEX('Licence Chemicals'!$I$5:$I$167,$L47)&""))} | L47: =IFERROR(__xludf.DUMMYFUNCTION("ARRAY_CONSTRAIN(ARRAYFORMULA(IFERROR(SMALL(FILTER((ROW('Licence Chemicals'!$A$5:$A$167)-ROW('Licence Chemicals'!$A$4:$I$4)),IFERROR(('Licence Chemicals'!$A$5:$A$167=$J$4),FALSE)),ROWS($L$22:L47)),"""")), 1, 1)"),"")
B48: =IF($L48="","",ROWS($L$22:L48)) | C48: {=IF($L48="","",INDEX('Licence Chemicals'!$D$5:$D$167,$L48)&"")} | D48: {=IF($L48="","",INDEX('Licence Chemicals'!$E$5:$E$167,$L48)&"")} | E48: {=IF($L48="","",IF(INDEX('Licence Chemicals'!$G$5:$G$167,$L48)="","",TEXT(INDEX('Licence Chemicals'!$G$5:$G$167,$L48),"#,##0.##")&" "&INDEX('Licence Chemicals'!$H$5:$H$167,$L48)))} | F48: {=IF($L48="","",IF(INDEX('Licence Chemicals'!$I$5:$I$167,$L48)="","To Be Provided",INDEX('Licence Chemicals'!$I$5:$I$167,$L48)&""))} | L48: =IFERROR(__xludf.DUMMYFUNCTION("ARRAY_CONSTRAIN(ARRAYFORMULA(IFERROR(SMALL(FILTER((ROW('Licence Chemicals'!$A$5:$A$167)-ROW('Licence Chemicals'!$A$4:$I$4)),IFERROR(('Licence Chemicals'!$A$5:$A$167=$J$4),FALSE)),ROWS($L$22:L48)),"""")), 1, 1)"),"")
B49: =IF($L49="","",ROWS($L$22:L49)) | C49: {=IF($L49="","",INDEX('Licence Chemicals'!$D$5:$D$167,$L49)&"")} | D49: {=IF($L49="","",INDEX('Licence Chemicals'!$E$5:$E$167,$L49)&"")} | E49: {=IF($L49="","",IF(INDEX('Licence Chemicals'!$G$5:$G$167,$L49)="","",TEXT(INDEX('Licence Chemicals'!$G$5:$G$167,$L49),"#,##0.##")&" "&INDEX('Licence Chemicals'!$H$5:$H$167,$L49)))} | F49: {=IF($L49="","",IF(INDEX('Licence Chemicals'!$I$5:$I$167,$L49)="","To Be Provided",INDEX('Licence Chemicals'!$I$5:$I$167,$L49)&""))} | L49: =IFERROR(__xludf.DUMMYFUNCTION("ARRAY_CONSTRAIN(ARRAYFORMULA(IFERROR(SMALL(FILTER((ROW('Licence Chemicals'!$A$5:$A$167)-ROW('Licence Chemicals'!$A$4:$I$4)),IFERROR(('Licence Chemicals'!$A$5:$A$167=$J$4),FALSE)),ROWS($L$22:L49)),"""")), 1, 1)"),"")
B50: =IF($L50="","",ROWS($L$22:L50)) | C50: {=IF($L50="","",INDEX('Licence Chemicals'!$D$5:$D$167,$L50)&"")} | D50: {=IF($L50="","",INDEX('Licence Chemicals'!$E$5:$E$167,$L50)&"")} | E50: {=IF($L50="","",IF(INDEX('Licence Chemicals'!$G$5:$G$167,$L50)="","",TEXT(INDEX('Licence Chemicals'!$G$5:$G$167,$L50),"#,##0.##")&" "&INDEX('Licence Chemicals'!$H$5:$H$167,$L50)))} | F50: {=IF($L50="","",IF(INDEX('Licence Chemicals'!$I$5:$I$167,$L50)="","To Be Provided",INDEX('Licence Chemicals'!$I$5:$I$167,$L50)&""))} | L50: =IFERROR(__xludf.DUMMYFUNCTION("ARRAY_CONSTRAIN(ARRAYFORMULA(IFERROR(SMALL(FILTER((ROW('Licence Chemicals'!$A$5:$A$167)-ROW('Licence Chemicals'!$A$4:$I$4)),IFERROR(('Licence Chemicals'!$A$5:$A$167=$J$4),FALSE)),ROWS($L$22:L50)),"""")), 1, 1)"),"")
B51: =IF($L51="","",ROWS($L$22:L51)) | C51: {=IF($L51="","",INDEX('Licence Chemicals'!$D$5:$D$167,$L51)&"")} | D51: {=IF($L51="","",INDEX('Licence Chemicals'!$E$5:$E$167,$L51)&"")} | E51: {=IF($L51="","",IF(INDEX('Licence Chemicals'!$G$5:$G$167,$L51)="","",TEXT(INDEX('Licence Chemicals'!$G$5:$G$167,$L51),"#,##0.##")&" "&INDEX('Licence Chemicals'!$H$5:$H$167,$L51)))} | F51: {=IF($L51="","",IF(INDEX('Licence Chemicals'!$I$5:$I$167,$L51)="","To Be Provided",INDEX('Licence Chemicals'!$I$5:$I$167,$L51)&""))} | L51: =IFERROR(__xludf.DUMMYFUNCTION("ARRAY_CONSTRAIN(ARRAYFORMULA(IFERROR(SMALL(FILTER((ROW('Licence Chemicals'!$A$5:$A$167)-ROW('Licence Chemicals'!$A$4:$I$4)),IFERROR(('Licence Chemicals'!$A$5:$A$167=$J$4),FALSE)),ROWS($L$22:L51)),"""")), 1, 1)"),"")
B52: =IF($L52="","",ROWS($L$22:L52)) | C52: {=IF($L52="","",INDEX('Licence Chemicals'!$D$5:$D$167,$L52)&"")} | D52: {=IF($L52="","",INDEX('Licence Chemicals'!$E$5:$E$167,$L52)&"")} | E52: {=IF($L52="","",IF(INDEX('Licence Chemicals'!$G$5:$G$167,$L52)="","",TEXT(INDEX('Licence Chemicals'!$G$5:$G$167,$L52),"#,##0.##")&" "&INDEX('Licence Chemicals'!$H$5:$H$167,$L52)))} | F52: {=IF($L52="","",IF(INDEX('Licence Chemicals'!$I$5:$I$167,$L52)="","To Be Provided",INDEX('Licence Chemicals'!$I$5:$I$167,$L52)&""))} | L52: =IFERROR(__xludf.DUMMYFUNCTION("ARRAY_CONSTRAIN(ARRAYFORMULA(IFERROR(SMALL(FILTER((ROW('Licence Chemicals'!$A$5:$A$167)-ROW('Licence Chemicals'!$A$4:$I$4)),IFERROR(('Licence Chemicals'!$A$5:$A$167=$J$4),FALSE)),ROWS($L$22:L52)),"""")), 1, 1)"),"")
B53: =IF($L53="","",ROWS($L$22:L53)) | C53: {=IF($L53="","",INDEX('Licence Chemicals'!$D$5:$D$167,$L53)&"")} | D53: {=IF($L53="","",INDEX('Licence Chemicals'!$E$5:$E$167,$L53)&"")} | E53: {=IF($L53="","",IF(INDEX('Licence Chemicals'!$G$5:$G$167,$L53)="","",TEXT(INDEX('Licence Chemicals'!$G$5:$G$167,$L53),"#,##0.##")&" "&INDEX('Licence Chemicals'!$H$5:$H$167,$L53)))} | F53: {=IF($L53="","",IF(INDEX('Licence Chemicals'!$I$5:$I$167,$L53)="","To Be Provided",INDEX('Licence Chemicals'!$I$5:$I$167,$L53)&""))} | L53: =IFERROR(__xludf.DUMMYFUNCTION("ARRAY_CONSTRAIN(ARRAYFORMULA(IFERROR(SMALL(FILTER((ROW('Licence Chemicals'!$A$5:$A$167)-ROW('Licence Chemicals'!$A$4:$I$4)),IFERROR(('Licence Chemicals'!$A$5:$A$167=$J$4),FALSE)),ROWS($L$22:L53)),"""")), 1, 1)"),"")
B54: =IF($L54="","",ROWS($L$22:L54)) | C54: {=IF($L54="","",INDEX('Licence Chemicals'!$D$5:$D$167,$L54)&"")} | D54: {=IF($L54="","",INDEX('Licence Chemicals'!$E$5:$E$167,$L54)&"")} | E54: {=IF($L54="","",IF(INDEX('Licence Chemicals'!$G$5:$G$167,$L54)="","",TEXT(INDEX('Licence Chemicals'!$G$5:$G$167,$L54),"#,##0.##")&" "&INDEX('Licence Chemicals'!$H$5:$H$167,$L54)))} | F54: {=IF($L54="","",IF(INDEX('Licence Chemicals'!$I$5:$I$167,$L54)="","To Be Provided",INDEX('Licence Chemicals'!$I$5:$I$167,$L54)&""))} | L54: =IFERROR(__xludf.DUMMYFUNCTION("ARRAY_CONSTRAIN(ARRAYFORMULA(IFERROR(SMALL(FILTER((ROW('Licence Chemicals'!$A$5:$A$167)-ROW('Licence Chemicals'!$A$4:$I$4)),IFERROR(('Licence Chemicals'!$A$5:$A$167=$J$4),FALSE)),ROWS($L$22:L54)),"""")), 1, 1)"),"")
B55: =IF($L55="","",ROWS($L$22:L55)) | C55: {=IF($L55="","",INDEX('Licence Chemicals'!$D$5:$D$167,$L55)&"")} | D55: {=IF($L55="","",INDEX('Licence Chemicals'!$E$5:$E$167,$L55)&"")} | E55: {=IF($L55="","",IF(INDEX('Licence Chemicals'!$G$5:$G$167,$L55)="","",TEXT(INDEX('Licence Chemicals'!$G$5:$G$167,$L55),"#,##0.##")&" "&INDEX('Licence Chemicals'!$H$5:$H$167,$L55)))} | F55: {=IF($L55="","",IF(INDEX('Licence Chemicals'!$I$5:$I$167,$L55)="","To Be Provided",INDEX('Licence Chemicals'!$I$5:$I$167,$L55)&""))} | L55: =IFERROR(__xludf.DUMMYFUNCTION("ARRAY_CONSTRAIN(ARRAYFORMULA(IFERROR(SMALL(FILTER((ROW('Licence Chemicals'!$A$5:$A$167)-ROW('Licence Chemicals'!$A$4:$I$4)),IFERROR(('Licence Chemicals'!$A$5:$A$167=$J$4),FALSE)),ROWS($L$22:L55)),"""")), 1, 1)"),"")
B56: =IF($L56="","",ROWS($L$22:L56)) | C56: {=IF($L56="","",INDEX('Licence Chemicals'!$D$5:$D$167,$L56)&"")} | D56: {=IF($L56="","",INDEX('Licence Chemicals'!$E$5:$E$167,$L56)&"")} | E56: {=IF($L56="","",IF(INDEX('Licence Chemicals'!$G$5:$G$167,$L56)="","",TEXT(INDEX('Licence Chemicals'!$G$5:$G$167,$L56),"#,##0.##")&" "&INDEX('Licence Chemicals'!$H$5:$H$167,$L56)))} | F56: {=IF($L56="","",IF(INDEX('Licence Chemicals'!$I$5:$I$167,$L56)="","To Be Provided",INDEX('Licence Chemicals'!$I$5:$I$167,$L56)&""))} | L56: =IFERROR(__xludf.DUMMYFUNCTION("ARRAY_CONSTRAIN(ARRAYFORMULA(IFERROR(SMALL(FILTER((ROW('Licence Chemicals'!$A$5:$A$167)-ROW('Licence Chemicals'!$A$4:$I$4)),IFERROR(('Licence Chemicals'!$A$5:$A$167=$J$4),FALSE)),ROWS($L$22:L56)),"""")), 1, 1)"),"")
B57: =IF($L57="","",ROWS($L$22:L57)) | C57: {=IF($L57="","",INDEX('Licence Chemicals'!$D$5:$D$167,$L57)&"")} | D57: {=IF($L57="","",INDEX('Licence Chemicals'!$E$5:$E$167,$L57)&"")} | E57: {=IF($L57="","",IF(INDEX('Licence Chemicals'!$G$5:$G$167,$L57)="","",TEXT(INDEX('Licence Chemicals'!$G$5:$G$167,$L57),"#,##0.##")&" "&INDEX('Licence Chemicals'!$H$5:$H$167,$L57)))} | F57: {=IF($L57="","",IF(INDEX('Licence Chemicals'!$I$5:$I$167,$L57)="","To Be Provided",INDEX('Licence Chemicals'!$I$5:$I$167,$L57)&""))} | L57: =IFERROR(__xludf.DUMMYFUNCTION("ARRAY_CONSTRAIN(ARRAYFORMULA(IFERROR(SMALL(FILTER((ROW('Licence Chemicals'!$A$5:$A$167)-ROW('Licence Chemicals'!$A$4:$I$4)),IFERROR(('Licence Chemicals'!$A$5:$A$167=$J$4),FALSE)),ROWS($L$22:L57)),"""")), 1, 1)"),"")
B58: =IF($L58="","",ROWS($L$22:L58)) | C58: {=IF($L58="","",INDEX('Licence Chemicals'!$D$5:$D$167,$L58)&"")} | D58: {=IF($L58="","",INDEX('Licence Chemicals'!$E$5:$E$167,$L58)&"")} | E58: {=IF($L58="","",IF(INDEX('Licence Chemicals'!$G$5:$G$167,$L58)="","",TEXT(INDEX('Licence Chemicals'!$G$5:$G$167,$L58),"#,##0.##")&" "&INDEX('Licence Chemicals'!$H$5:$H$167,$L58)))} | F58: {=IF($L58="","",IF(INDEX('Licence Chemicals'!$I$5:$I$167,$L58)="","To Be Provided",INDEX('Licence Chemicals'!$I$5:$I$167,$L58)&""))} | L58: =IFERROR(__xludf.DUMMYFUNCTION("ARRAY_CONSTRAIN(ARRAYFORMULA(IFERROR(SMALL(FILTER((ROW('Licence Chemicals'!$A$5:$A$167)-ROW('Licence Chemicals'!$A$4:$I$4)),IFERROR(('Licence Chemicals'!$A$5:$A$167=$J$4),FALSE)),ROWS($L$22:L58)),"""")), 1, 1)"),"")
B59: =IF($L59="","",ROWS($L$22:L59)) | C59: {=IF($L59="","",INDEX('Licence Chemicals'!$D$5:$D$167,$L59)&"")} | D59: {=IF($L59="","",INDEX('Licence Chemicals'!$E$5:$E$167,$L59)&"")} | E59: {=IF($L59="","",IF(INDEX('Licence Chemicals'!$G$5:$G$167,$L59)="","",TEXT(INDEX('Licence Chemicals'!$G$5:$G$167,$L59),"#,##0.##")&" "&INDEX('Licence Chemicals'!$H$5:$H$167,$L59)))} | F59: {=IF($L59="","",IF(INDEX('Licence Chemicals'!$I$5:$I$167,$L59)="","To Be Provided",INDEX('Licence Chemicals'!$I$5:$I$167,$L59)&""))} | L59: =IFERROR(__xludf.DUMMYFUNCTION("ARRAY_CONSTRAIN(ARRAYFORMULA(IFERROR(SMALL(FILTER((ROW('Licence Chemicals'!$A$5:$A$167)-ROW('Licence Chemicals'!$A$4:$I$4)),IFERROR(('Licence Chemicals'!$A$5:$A$167=$J$4),FALSE)),ROWS($L$22:L59)),"""")), 1, 1)"),"")
B60: =IF($L60="","",ROWS($L$22:L60)) | C60: {=IF($L60="","",INDEX('Licence Chemicals'!$D$5:$D$167,$L60)&"")} | D60: {=IF($L60="","",INDEX('Licence Chemicals'!$E$5:$E$167,$L60)&"")} | E60: {=IF($L60="","",IF(INDEX('Licence Chemicals'!$G$5:$G$167,$L60)="","",TEXT(INDEX('Licence Chemicals'!$G$5:$G$167,$L60),"#,##0.##")&" "&INDEX('Licence Chemicals'!$H$5:$H$167,$L60)))} | F60: {=IF($L60="","",IF(INDEX('Licence Chemicals'!$I$5:$I$167,$L60)="","To Be Provided",INDEX('Licence Chemicals'!$I$5:$I$167,$L60)&""))} | L60: =IFERROR(__xludf.DUMMYFUNCTION("ARRAY_CONSTRAIN(ARRAYFORMULA(IFERROR(SMALL(FILTER((ROW('Licence Chemicals'!$A$5:$A$167)-ROW('Licence Chemicals'!$A$4:$I$4)),IFERROR(('Licence Chemicals'!$A$5:$A$167=$J$4),FALSE)),ROWS($L$22:L60)),"""")), 1, 1)"),"")
B61: =IF($L61="","",ROWS($L$22:L61)) | C61: {=IF($L61="","",INDEX('Licence Chemicals'!$D$5:$D$167,$L61)&"")} | D61: {=IF($L61="","",INDEX('Licence Chemicals'!$E$5:$E$167,$L61)&"")} | E61: {=IF($L61="","",IF(INDEX('Licence Chemicals'!$G$5:$G$167,$L61)="","",TEXT(INDEX('Licence Chemicals'!$G$5:$G$167,$L61),"#,##0.##")&" "&INDEX('Licence Chemicals'!$H$5:$H$167,$L61)))} | F61: {=IF($L61="","",IF(INDEX('Licence Chemicals'!$I$5:$I$167,$L61)="","To Be Provided",INDEX('Licence Chemicals'!$I$5:$I$167,$L61)&""))} | L61: =IFERROR(__xludf.DUMMYFUNCTION("ARRAY_CONSTRAIN(ARRAYFORMULA(IFERROR(SMALL(FILTER((ROW('Licence Chemicals'!$A$5:$A$167)-ROW('Licence Chemicals'!$A$4:$I$4)),IFERROR(('Licence Chemicals'!$A$5:$A$167=$J$4),FALSE)),ROWS($L$22:L61)),"""")), 1, 1)"),"")
B63: CONDITIONS
B64: 1 | C64: The importation must not exceed the quantity stipulated in this license; any exceedance of this quantity without prior approval from the Agency is a violation of this license condition and will incur a penalty;
B65: 2 | C65: A written notification should be made with importation documents and details of the consignment at least two weeks before the arrival and transportation of the consignment;
B66: 3 | C66: Ensure that the quality of the chemical complies with the information in the attached label and with the literature and specifications published in the MSDS by the manufacturer;
B67: 4 | C67: Notify the EPA immediately in case of any significant change to the information in the application;
B68: 5 | C68: Undertake adequate safety and security measures while transporting the consignment from the port of entry to the storage site. No person shall handle, offer for transport, or transport chemicals unless he/she is trained or certified by the EPA; a list of certified transporters can be obtained from the Agency;
B69: 6 | C69: Notify the Agency within 24 hours in case of emergency or accidental release to the environment;
B70: 7 | C70: This license only applies to the chemicals specified in this license. It does not include the importation of narcotics drugs or any chemicals banned under international conventions;
B71: 8 | C71: This license is valid for importation through authorized custom entry points into Liberia only;
B72: 9 | C72: This license is valid until the end of the year, however, expires immediately after the clearance of the stipulated consignments and quantities from the port of entry.
B73: 10 | C73: Any violation of this license condition will incur a penalty consistent with Section 112 of the Environmental Protection and Management Law of Liberia;
B75: ="Issued Date: "&IF($J$10="","________",DAY($J$10)&IF(AND(DAY($J$10)>=11,DAY($J$10)<=13),"th",CHOOSE(MIN(MOD(DAY($J$10),10)+1,5),"th","st","nd","rd","th"))&" "&TEXT($J$10,"mmmm, yyyy")) -> Issued Date: 15th January, 2026 | D75: ="Expired Date: "&IF($J$11="","________",DAY($J$11)&IF(AND(DAY($J$11)>=11,DAY($J$11)<=13),"th",CHOOSE(MIN(MOD(DAY($J$11),10)+1,5),"th","st","nd","rd","th"))&" "&TEXT($J$11,"mmmm, yyyy")) -> Expired Date: 31st December, 2026
B77: _____________________________________________
B78: {=IFERROR(INDEX(Lists!$U$5:$U$7,MATCH($J$13,Lists!$T$5:$T$7,0)),"")} -> Dr. Emmanuel K. Urey Yarkpawolo
B79: {=IFERROR(INDEX(Lists!$V$5:$V$7,MATCH($J$13,Lists!$T$5:$T$7,0)),"")} -> EXECUTIVE DIRECTOR/CEO

Sheet Print EDL
B2: =IF($J$3="No","",setLetterhead_1) -> REPUBLIC OF LIBERIA | I2: PRINT – ANNUAL EFFLUENT DISCHARGE LICENSE
B3: =IF($J$3="No","",setLetterhead_2) -> ENVIRONMENTAL PROTECTION AGENCY | I3: Print letterhead ▶ | J3: Yes
B4: =IF($J$3="No","",setLetterhead_3) -> P.O. Box 4024 | I4: Licence Record ID ▶ | J4: LIC-017
B5: =IF($J$3="No","",setLetterhead_4) -> Bright Building 302-A, Sekou Toure Avenue, Mamba Point | I5: Check | J5: {=IF($J$4="","Choose a licence record",IF($J$6="","⚠ Record not found",IF(ISERROR(SEARCH("EDL",INDEX('Licences & Certificates'!$E$5:$E$73,$J$6))),"⚠ This record is "&INDEX('Licences & Certificates'!$E$5:$E$73,$J$6),IF(ISERROR(SEARCH("Retention",INDEX('Licences & Certificates'!$F$5:$F$73,$J$6))),IF(INDEX('Licences & Certificates'!$K$5:$K$73,$J$6)="","⚠ No licence number yet","✔ Ready to print"),"⚠ Retention Pond licence – use Print EDL RP"))))} -> ⚠ This record is Chemical Registration (CRL)
B6: =IF($J$3="No","",setLetterhead_5) -> 1000 Monrovia, 10 Liberia | I6: (row in register) | J6: =IFERROR(MATCH($J$4,'Licences & Certificates'!$A$5:$A$73,0),"") -> 16
I7: Licence No. | J7: {=IF($J$6="","",INDEX('Licences & Certificates'!$K$5:$K$73,$J$6)&"")}
B8: =IF($J$7="","License No. ________","License No. "&$J$7) -> License No. ________ | I8: Company | J8: {=IF($J$6="","",INDEX('Licences & Certificates'!$C$5:$C$73,$J$6))} -> Fouani Brothers
I9: Location | J9: {=IF($J$6="","",IF(INDEX('Licences & Certificates'!$G$5:$G$73,$J$6)<>"",INDEX('Licences & Certificates'!$G$5:$G$73,$J$6),IFERROR(INDEX(Companies!$D$5:$D$74,MATCH(INDEX('Licences & Certificates'!$B$5:$B$73,$J$6),Companies!$A$5:$A$74,0))&"","")))}
B10: ANNUAL EFFLUENT DISCHARGE LICENSE | I10: Date Issued | J10: {=IF($J$6="","",IF(INDEX('Licences & Certificates'!$L$5:$L$73,$J$6)="","",INDEX('Licences & Certificates'!$L$5:$L$73,$J$6)))}
B11: (Issued under Part II Section VI of the EPA Act) | I11: Expiry Date | J11: {=IF($J$6="","",IF(INDEX('Licences & Certificates'!$M$5:$M$73,$J$6)="","",INDEX('Licences & Certificates'!$M$5:$M$73,$J$6)))}
I12: Signed by ▶ | J12: Executive Director
B13: LICENSEE | I13: Receiving water ▶ | J13: {=IFERROR(INDEX('Licence Effluent'!$G$5:$G$6,MATCH(UPPER($J$4)&"|Setting|1",'Licence Effluent'!$L$5:$L$6,0))&"","")}
B14: =UPPER($J$8) -> FOUANI BROTHERS | I14: Max. volume (m³/day) ▶ | J14: {=IFERROR(INDEX('Licence Effluent'!$G$5:$G$6,MATCH(UPPER($J$4)&"|Setting|2",'Licence Effluent'!$L$5:$L$6,0))&"","")}
I15: Discharge point ▶ | J15: {=IFERROR(INDEX('Licence Effluent'!$G$5:$G$6,MATCH(UPPER($J$4)&"|Setting|3",'Licence Effluent'!$L$5:$L$6,0))&"","")}
B16: LOCATION | I16: ⇄ Switch to Print EDL RP (Retention Pond)
B17: =$J$9 | I17: How to use: pick the EDL Record ID in J4 and choose who signs in J12. Receiving water, volume, discharge point and the discharge-limits table come from the EFFLUENT DETAILS section of the Licence Form (saved on the Licence Effluent sheet). Only the parameters entered for this licence print; empty table rows are left out. Then use the OUTPUT buttons on the right. Set 'Print letterhead' (J3) to No when printing on pre-printed EPA letterhead paper – the letterhead text and logos are left off, keeping the same space at the top.
B19: In pursuant to Part 5 Section 56-60 of the Environmental Protection and Management Law of Liberia, this annual Effluent Discharge License is hereby issued for the discharge of treated effluent subject to the Act of the Environmental Protection Agency of Liberia, the Environmental Protection and Management Law of Liberia, the Liberia Water Quality Standards and the conditions specified in this license.
B21: CONDITIONS
B22: 1. | C22: ="This license refers to the discharge of treated trade effluent from only the proposed development of "&$J$8&IF($J$9="",""," at "&$J$9)&IF($J$15="",""," "&$J$15)&";" -> This license refers to the discharge of treated trade effluent from only the proposed development of Fouani Brothers;
B23: 2. | C23: ="The total volume of the treated trade effluent discharged to "&IF($J$13="","________",$J$13)&" shall not exceed "&IF($J$14="","____",$J$14)&"m³/day;" -> The total volume of the treated trade effluent discharged to ________ shall not exceed ____m³/day;
B24: 3. | C24: Part V Section 61 of EPML strictly prohibits the pollution of any water body in any form and manner. Any violation against this provision is punishable by fine and/or other legal action consistent with the EPML. This license does not cover the discharge in whatsoever form of untreated effluent from the licensee’s facility to any water course or wetland;
B25: 4. | C25: All effluent shall be treated to meet the following sewerage discharge limits:
C26: Parameter | D26: Unit | E26: Limit | F26: Testing Schedule
C27: {=IFERROR(INDEX('Licence Effluent'!$F$5:$F$6,MATCH(UPPER($J$4)&"|Limit|"&ROWS(C$27:C27),'Licence Effluent'!$L$5:$L$6,0))&"","")} | D27: {=IFERROR(INDEX('Licence Effluent'!$G$5:$G$6,MATCH(UPPER($J$4)&"|Limit|"&ROWS(C$27:C27),'Licence Effluent'!$L$5:$L$6,0))&"","")} | E27: {=IFERROR(INDEX('Licence Effluent'!$H$5:$H$6,MATCH(UPPER($J$4)&"|Limit|"&ROWS(C$27:C27),'Licence Effluent'!$L$5:$L$6,0))&"","")} | F27: {=IFERROR(INDEX('Licence Effluent'!$J$5:$J$6,MATCH(UPPER($J$4)&"|Limit|"&ROWS(C$27:C27),'Licence Effluent'!$L$5:$L$6,0))&"","")}
C28: {=IFERROR(INDEX('Licence Effluent'!$F$5:$F$6,MATCH(UPPER($J$4)&"|Limit|"&ROWS(C$27:C28),'Licence Effluent'!$L$5:$L$6,0))&"","")} | D28: {=IFERROR(INDEX('Licence Effluent'!$G$5:$G$6,MATCH(UPPER($J$4)&"|Limit|"&ROWS(C$27:C28),'Licence Effluent'!$L$5:$L$6,0))&"","")} | E28: {=IFERROR(INDEX('Licence Effluent'!$H$5:$H$6,MATCH(UPPER($J$4)&"|Limit|"&ROWS(C$27:C28),'Licence Effluent'!$L$5:$L$6,0))&"","")} | F28: {=IFERROR(INDEX('Licence Effluent'!$J$5:$J$6,MATCH(UPPER($J$4)&"|Limit|"&ROWS(C$27:C28),'Licence Effluent'!$L$5:$L$6,0))&"","")}
C29: {=IFERROR(INDEX('Licence Effluent'!$F$5:$F$6,MATCH(UPPER($J$4)&"|Limit|"&ROWS(C$27:C29),'Licence Effluent'!$L$5:$L$6,0))&"","")} | D29: {=IFERROR(INDEX('Licence Effluent'!$G$5:$G$6,MATCH(UPPER($J$4)&"|Limit|"&ROWS(C$27:C29),'Licence Effluent'!$L$5:$L$6,0))&"","")} | E29: {=IFERROR(INDEX('Licence Effluent'!$H$5:$H$6,MATCH(UPPER($J$4)&"|Limit|"&ROWS(C$27:C29),'Licence Effluent'!$L$5:$L$6,0))&"","")} | F29: {=IFERROR(INDEX('Licence Effluent'!$J$5:$J$6,MATCH(UPPER($J$4)&"|Limit|"&ROWS(C$27:C29),'Licence Effluent'!$L$5:$L$6,0))&"","")}
C30: {=IFERROR(INDEX('Licence Effluent'!$F$5:$F$6,MATCH(UPPER($J$4)&"|Limit|"&ROWS(C$27:C30),'Licence Effluent'!$L$5:$L$6,0))&"","")} | D30: {=IFERROR(INDEX('Licence Effluent'!$G$5:$G$6,MATCH(UPPER($J$4)&"|Limit|"&ROWS(C$27:C30),'Licence Effluent'!$L$5:$L$6,0))&"","")} | E30: {=IFERROR(INDEX('Licence Effluent'!$H$5:$H$6,MATCH(UPPER($J$4)&"|Limit|"&ROWS(C$27:C30),'Licence Effluent'!$L$5:$L$6,0))&"","")} | F30: {=IFERROR(INDEX('Licence Effluent'!$J$5:$J$6,MATCH(UPPER($J$4)&"|Limit|"&ROWS(C$27:C30),'Licence Effluent'!$L$5:$L$6,0))&"","")}
C31: {=IFERROR(INDEX('Licence Effluent'!$F$5:$F$6,MATCH(UPPER($J$4)&"|Limit|"&ROWS(C$27:C31),'Licence Effluent'!$L$5:$L$6,0))&"","")} | D31: {=IFERROR(INDEX('Licence Effluent'!$G$5:$G$6,MATCH(UPPER($J$4)&"|Limit|"&ROWS(C$27:C31),'Licence Effluent'!$L$5:$L$6,0))&"","")} | E31: {=IFERROR(INDEX('Licence Effluent'!$H$5:$H$6,MATCH(UPPER($J$4)&"|Limit|"&ROWS(C$27:C31),'Licence Effluent'!$L$5:$L$6,0))&"","")} | F31: {=IFERROR(INDEX('Licence Effluent'!$J$5:$J$6,MATCH(UPPER($J$4)&"|Limit|"&ROWS(C$27:C31),'Licence Effluent'!$L$5:$L$6,0))&"","")}
C32: {=IFERROR(INDEX('Licence Effluent'!$F$5:$F$6,MATCH(UPPER($J$4)&"|Limit|"&ROWS(C$27:C32),'Licence Effluent'!$L$5:$L$6,0))&"","")} | D32: {=IFERROR(INDEX('Licence Effluent'!$G$5:$G$6,MATCH(UPPER($J$4)&"|Limit|"&ROWS(C$27:C32),'Licence Effluent'!$L$5:$L$6,0))&"","")} | E32: {=IFERROR(INDEX('Licence Effluent'!$H$5:$H$6,MATCH(UPPER($J$4)&"|Limit|"&ROWS(C$27:C32),'Licence Effluent'!$L$5:$L$6,0))&"","")} | F32: {=IFERROR(INDEX('Licence Effluent'!$J$5:$J$6,MATCH(UPPER($J$4)&"|Limit|"&ROWS(C$27:C32),'Licence Effluent'!$L$5:$L$6,0))&"","")}
C33: {=IFERROR(INDEX('Licence Effluent'!$F$5:$F$6,MATCH(UPPER($J$4)&"|Limit|"&ROWS(C$27:C33),'Licence Effluent'!$L$5:$L$6,0))&"","")} | D33: {=IFERROR(INDEX('Licence Effluent'!$G$5:$G$6,MATCH(UPPER($J$4)&"|Limit|"&ROWS(C$27:C33),'Licence Effluent'!$L$5:$L$6,0))&"","")} | E33: {=IFERROR(INDEX('Licence Effluent'!$H$5:$H$6,MATCH(UPPER($J$4)&"|Limit|"&ROWS(C$27:C33),'Licence Effluent'!$L$5:$L$6,0))&"","")} | F33: {=IFERROR(INDEX('Licence Effluent'!$J$5:$J$6,MATCH(UPPER($J$4)&"|Limit|"&ROWS(C$27:C33),'Licence Effluent'!$L$5:$L$6,0))&"","")}
C34: {=IFERROR(INDEX('Licence Effluent'!$F$5:$F$6,MATCH(UPPER($J$4)&"|Limit|"&ROWS(C$27:C34),'Licence Effluent'!$L$5:$L$6,0))&"","")} | D34: {=IFERROR(INDEX('Licence Effluent'!$G$5:$G$6,MATCH(UPPER($J$4)&"|Limit|"&ROWS(C$27:C34),'Licence Effluent'!$L$5:$L$6,0))&"","")} | E34: {=IFERROR(INDEX('Licence Effluent'!$H$5:$H$6,MATCH(UPPER($J$4)&"|Limit|"&ROWS(C$27:C34),'Licence Effluent'!$L$5:$L$6,0))&"","")} | F34: {=IFERROR(INDEX('Licence Effluent'!$J$5:$J$6,MATCH(UPPER($J$4)&"|Limit|"&ROWS(C$27:C34),'Licence Effluent'!$L$5:$L$6,0))&"","")}
C35: {=IFERROR(INDEX('Licence Effluent'!$F$5:$F$6,MATCH(UPPER($J$4)&"|Limit|"&ROWS(C$27:C35),'Licence Effluent'!$L$5:$L$6,0))&"","")} | D35: {=IFERROR(INDEX('Licence Effluent'!$G$5:$G$6,MATCH(UPPER($J$4)&"|Limit|"&ROWS(C$27:C35),'Licence Effluent'!$L$5:$L$6,0))&"","")} | E35: {=IFERROR(INDEX('Licence Effluent'!$H$5:$H$6,MATCH(UPPER($J$4)&"|Limit|"&ROWS(C$27:C35),'Licence Effluent'!$L$5:$L$6,0))&"","")} | F35: {=IFERROR(INDEX('Licence Effluent'!$J$5:$J$6,MATCH(UPPER($J$4)&"|Limit|"&ROWS(C$27:C35),'Licence Effluent'!$L$5:$L$6,0))&"","")}
C36: {=IFERROR(INDEX('Licence Effluent'!$F$5:$F$6,MATCH(UPPER($J$4)&"|Limit|"&ROWS(C$27:C36),'Licence Effluent'!$L$5:$L$6,0))&"","")} | D36: {=IFERROR(INDEX('Licence Effluent'!$G$5:$G$6,MATCH(UPPER($J$4)&"|Limit|"&ROWS(C$27:C36),'Licence Effluent'!$L$5:$L$6,0))&"","")} | E36: {=IFERROR(INDEX('Licence Effluent'!$H$5:$H$6,MATCH(UPPER($J$4)&"|Limit|"&ROWS(C$27:C36),'Licence Effluent'!$L$5:$L$6,0))&"","")} | F36: {=IFERROR(INDEX('Licence Effluent'!$J$5:$J$6,MATCH(UPPER($J$4)&"|Limit|"&ROWS(C$27:C36),'Licence Effluent'!$L$5:$L$6,0))&"","")}
C37: {=IFERROR(INDEX('Licence Effluent'!$F$5:$F$6,MATCH(UPPER($J$4)&"|Limit|"&ROWS(C$27:C37),'Licence Effluent'!$L$5:$L$6,0))&"","")} | D37: {=IFERROR(INDEX('Licence Effluent'!$G$5:$G$6,MATCH(UPPER($J$4)&"|Limit|"&ROWS(C$27:C37),'Licence Effluent'!$L$5:$L$6,0))&"","")} | E37: {=IFERROR(INDEX('Licence Effluent'!$H$5:$H$6,MATCH(UPPER($J$4)&"|Limit|"&ROWS(C$27:C37),'Licence Effluent'!$L$5:$L$6,0))&"","")} | F37: {=IFERROR(INDEX('Licence Effluent'!$J$5:$J$6,MATCH(UPPER($J$4)&"|Limit|"&ROWS(C$27:C37),'Licence Effluent'!$L$5:$L$6,0))&"","")}
C38: {=IFERROR(INDEX('Licence Effluent'!$F$5:$F$6,MATCH(UPPER($J$4)&"|Limit|"&ROWS(C$27:C38),'Licence Effluent'!$L$5:$L$6,0))&"","")} | D38: {=IFERROR(INDEX('Licence Effluent'!$G$5:$G$6,MATCH(UPPER($J$4)&"|Limit|"&ROWS(C$27:C38),'Licence Effluent'!$L$5:$L$6,0))&"","")} | E38: {=IFERROR(INDEX('Licence Effluent'!$H$5:$H$6,MATCH(UPPER($J$4)&"|Limit|"&ROWS(C$27:C38),'Licence Effluent'!$L$5:$L$6,0))&"","")} | F38: {=IFERROR(INDEX('Licence Effluent'!$J$5:$J$6,MATCH(UPPER($J$4)&"|Limit|"&ROWS(C$27:C38),'Licence Effluent'!$L$5:$L$6,0))&"","")}
... C46: {=IFERROR(INDEX('Licence Effluent'!$F$5:$F$6,MATCH(UPPER($J$4)&"|Limit|"&ROWS(C$27:C46),'Licence Effluent'!$L$5:$L$6,0))&"","")} | D46: {=IFERROR(INDEX('Licence Effluent'!$G$5:$G$6,MATCH(UPPER($J$4)&"|Limit|"&ROWS(C$27:C46),'Licence Effluent'!$L$5:$L$6,0))&"","")} | E46: {=IFERROR(INDEX('Licence Effluent'!$H$5:$H$6,MATCH(UPPER($J$4)&"|Limit|"&ROWS(C$27:C46),'Licence Effluent'!$L$5:$L$6,0))&"","")} | F46: {=IFERROR(INDEX('Licence Effluent'!$J$5:$J$6,MATCH(UPPER($J$4)&"|Limit|"&ROWS(C$27:C46),'Licence Effluent'!$L$5:$L$6,0))&"","")}
B48: 5. | C48: The Licensee must monitor and ensure discharges from its facility meet the limits as specified in the above table. The figure represents permissible effluent limits and the licensee must comply with the effluent limits in the tables unless otherwise indicated, regardless of the frequency of monitoring or reporting requirement;
B49: 6. | C49: A comprehensive effluent analysis report should be presented to the Agency quarterly by the Licensee. The Licensee shall hire an EPA accredited third party Laboratory to collect and test effluent samples to gage adherence to the license for all parameters mentioned herein.
B50: 7. | C50: The licensee shall keep all results submitted by third party Laboratory as per the reporting schedule and include same in monitoring reports submitted to the Agency (if applicable) or submit same when requested by inspectors of the Agency;
B51: 8. | C51: In the event that a test result by the third party Laboratory records an exceedance of any of the parameters in the Table, the Licensee shall discontinue discharging into the stream and notify the Agency immediately;
B52: 9. | C52: This license does not cover the discharge of mineral oil, diesel and any other pollutant into the stream; all hazardous waste shall be handled by an EPA certified hazardous waste handler. The licensee shall keep all records of the name, address and permit number of the waste service contractor hired, the date on which the waste was transported offsite, the type and quantity of waste transported (in m³), and the location of disposal;
B53: 10. | C53: All over ground storage tanks areas and drums storage areas which contain oils, chemicals, or other substances which are or could be harmful to the aquatic environment shall be rendered impervious to the material stored therein. Additionally, these areas shall be bunded and designed in order to give protection to sewer, surface water and groundwater on spillage or seepage of the materials;
B54: 11. | C54: Storm water shall be separately collected and discharged to the water drain via an oil interceptor. A readily and safely accessible monitoring chamber shall be constructed on the storm water pipeline to allow for inspection and sampling of the storm water being discharged;
B55: 12. | C55: The wastewater/effluent treatment equipment and facility at the premises shall be operational and in use at all times when effluent is being discharged. The Agency shall be notified, through writing, about any malfunction of the equipment;
B56: 13. | C56: The licensee shall conduct visual inspection of the effluent discharge and storm water discharge points on a weekly basis. Records of all inspections shall be kept in a logbook. If it appears that there is any abnormalities, the Licensee shall notify the Agency through writing, and initial an investigation into the possible cause(s) of the abnormalities;
B57: 14. | C57: The Licensee shall immediately notify the Agency, through writing, after occurrence of any accidental discharge, spillage or deposit of any pollutants or potential pollutant which enters or is likely to enter the water or cause pollution;
B58: 15. | C58: The Licensee shall notify the Agency, through writing, immediately prior to the commencement of the licensed discharge;
B59: 16. | C59: The Licensee shall notify the Agency, through writing, within 72 hours of any environmental emergency onsite and off-site, including all measures taken to remedy the situation;
... B65: 22. | C65: The Agency reserves itself the right to conduct routine documentary and compliance monitoring at all time without any hindrance from the licensee or any of its employees or associates.
B67: ="Issued Date: "&IF($J$10="","________",DAY($J$10)&IF(AND(DAY($J$10)>=11,DAY($J$10)<=13),"th",CHOOSE(MIN(MOD(DAY($J$10),10)+1,5),"th","st","nd","rd","th"))&" "&TEXT($J$10,"mmmm, yyyy")) -> Issued Date: ________ | D67: ="Expired Date: "&IF($J$11="","________",DAY($J$11)&IF(AND(DAY($J$11)>=11,DAY($J$11)<=13),"th",CHOOSE(MIN(MOD(DAY($J$11),10)+1,5),"th","st","nd","rd","th"))&" "&TEXT($J$11,"mmmm, yyyy")) -> Expired Date: ________
B70: _____________________________________________
B71: {=IFERROR(INDEX(Lists!$U$5:$U$7,MATCH($J$12,Lists!$T$5:$T$7,0)),"")} -> Dr. Emmanuel K. Urey Yarkpawolo
B72: {=UPPER(IFERROR(INDEX(Lists!$V$5:$V$7,MATCH($J$12,Lists!$T$5:$T$7,0)),""))} -> EXECUTIVE DIRECTOR/CEO

Sheet Print EDL RP
B2: =IF($J$3="No","",setLetterhead_1) -> REPUBLIC OF LIBERIA | I2: PRINT – EFFLUENT DISCHARGE & RETENTION POND LICENSE
B3: =IF($J$3="No","",setLetterhead_2) -> ENVIRONMENTAL PROTECTION AGENCY | I3: Print letterhead ▶ | J3: Yes
B4: =IF($J$3="No","",setLetterhead_3) -> P.O. Box 4024 | I4: Licence Record ID ▶ | J4: LIC-005
B5: =IF($J$3="No","",setLetterhead_4) -> Bright Building 302-A, Sekou Toure Avenue, Mamba Point | I5: Check | J5: {=IF($J$4="","Choose a licence record",IF($J$6="","⚠ Record not found",IF(ISERROR(SEARCH("EDL",INDEX('Licences & Certificates'!$E$5:$E$73,$J$6))),"⚠ This record is "&INDEX('Licences & Certificates'!$E$5:$E$73,$J$6),IF(ISNUMBER(SEARCH("Retention",INDEX('Licences & Certificates'!$F$5:$F$73,$J$6))),IF(INDEX('Licences & Certificates'!$K$5:$K$73,$J$6)="","⚠ No licence number yet","✔ Ready to print"),"⚠ Standard EDL – use Print EDL"))))} -> ⚠ This record is Chemical Registration (CRL)
B6: =IF($J$3="No","",setLetterhead_5) -> 1000 Monrovia, 10 Liberia | I6: (row in register) | J6: =IFERROR(MATCH($J$4,'Licences & Certificates'!$A$5:$A$73,0),"") -> 4
I7: Licence No. | J7: {=IF($J$6="","",INDEX('Licences & Certificates'!$K$5:$K$73,$J$6)&"")} -> EPA/CRL-CI-001/2026
B8: =IF($J$7="","License No. ________","License No. "&$J$7) -> License No. EPA/CRL-CI-001/2026 | I8: Company | J8: {=IF($J$6="","",INDEX('Licences & Certificates'!$C$5:$C$73,$J$6))} -> Tanmay Hardware Center
I9: Location | J9: {=IF($J$6="","",IF(INDEX('Licences & Certificates'!$G$5:$G$73,$J$6)<>"",INDEX('Licences & Certificates'!$G$5:$G$73,$J$6),IFERROR(INDEX(Companies!$D$5:$D$74,MATCH(INDEX('Licences & Certificates'!$B$5:$B$73,$J$6),Companies!$A$5:$A$74,0))&"","")))} -> Monrovia, Liberia
B10: EFFLUENT DISCHARGE & RETENTION POND LICENSE | I10: Date Issued | J10: {=IF($J$6="","",IF(INDEX('Licences & Certificates'!$L$5:$L$73,$J$6)="","",INDEX('Licences & Certificates'!$L$5:$L$73,$J$6)))} -> 46023
B11: (Issued under Part II Section VI of the EPA Act) | I11: Expiry Date | J11: {=IF($J$6="","",IF(INDEX('Licences & Certificates'!$M$5:$M$73,$J$6)="","",INDEX('Licences & Certificates'!$M$5:$M$73,$J$6)))} -> 46387
I12: Signed by ▶ | J12: Executive Director
B13: LICENSEE | I13: Receiving water ▶ | J13: {=IFERROR(INDEX('Licence Effluent'!$G$5:$G$6,MATCH(UPPER($J$4)&"|Setting|1",'Licence Effluent'!$L$5:$L$6,0))&"","")}
B14: =UPPER($J$8) -> TANMAY HARDWARE CENTER | I14: Max. volume (m³/day) ▶ | J14: {=IFERROR(INDEX('Licence Effluent'!$G$5:$G$6,MATCH(UPPER($J$4)&"|Setting|2",'Licence Effluent'!$L$5:$L$6,0))&"","")}
I15: Discharge point ▶ | J15: {=IFERROR(INDEX('Licence Effluent'!$G$5:$G$6,MATCH(UPPER($J$4)&"|Setting|3",'Licence Effluent'!$L$5:$L$6,0))&"","")}
B16: LOCATION | I16: ⇄ Switch to Print EDL (standard)
B17: =$J$9 -> Monrovia, Liberia | I17: How to use: pick the Retention Pond licence Record ID in J4 and choose who signs in J12. Coordinates, discharge sources, receiving water/volume and the limits table (with stage) come from the EFFLUENT DETAILS section of the Licence Form. Empty table rows are left out when printing. Section 3.3 uses the standard EDL conditions – edit them here if your Retention Pond licence differs. Set 'Print letterhead' (J3) to No when printing on pre-printed EPA letterhead paper – the letterhead text and logos are left off, keeping the same space at the top.
B19: ="In pursuant to Part 5 Section 56-60 of the Environmental Protection and Management Law of Liberia (EPML), this Effluent Discharge & Retention Pond License is hereby issued to "&$J$8&" (hereafter called the licensee) for the discharge of treated effluents subject to the Act of the Environmental Protection Agency of Liberia, the Liberia Water Quality Standards and all other conditions specified in this license." -> In pursuant to Part 5 Section 56-60 of the Environmental Protection and Management Law of Liberia (EPML), this Effluent Discharge & Retention Pond License is hereby issued to Tanmay Hardware Center (hereafter called the licensee) for the discharge of treated effluents subject to the Act of the Environmental Protection Agency of Liberia, the Liberia Water Quality Standards and all other conditions specified in this license.
N20: Stage | O20: StageNo | P20: StageIdx | Q20: StageKey | T20: CoordGrp | U20: CoordKey
B21: 1. Project Geo-reference | N21: {=IF(IFERROR(INDEX('Licence Effluent'!$F$5:$F$6,MATCH(UPPER($J$4)&"|Limit|"&1,'Licence Effluent'!$L$5:$L$6,0))&"","")="","",IF(IFERROR(INDEX('Licence Effluent'!$K$5:$K$6,MATCH(UPPER($J$4)&"|Limit|"&1,'Licence Effluent'!$L$5:$L$6,0))&"","")="","(none)",IFERROR(INDEX('Licence Effluent'!$K$5:$K$6,MATCH(UPPER($J$4)&"|Limit|"&1,'Licence Effluent'!$L$5:$L$6,0))&"","")))} | O21: =IF(N21="","",IF(COUNTIF(N$21:N21,N21)=1,MAX(O$20:O20)+1,"")) | P21: =IF(N21="","",INDEX(O$21:O$40,MATCH(N21,N$21:N$40,0))) | Q21: =IF(N21="","",P21&"|"&COUNTIF(N$21:N21,N21)) | T21: {=IF(ISNA(MATCH(UPPER($J$4)&"|Coordinate|"&1,'Licence Effluent'!$L$5:$L$6,0)),"",IF(ISNUMBER(SEARCH("1A",IFERROR(INDEX('Licence Effluent'!$F$5:$F$6,MATCH(UPPER($J$4)&"|Coordinate|"&1,'Licence Effluent'!$L$5:$L$6,0))&"",""))),"A","B"))} | U21: =IF(T21="","",T21&"|"&COUNTIF(T$21:T21,T21)) | V21: =IF(ISNA(MATCH(UPPER($J$4)&"|Source|"&1,'Licence Effluent'!$L$5:$L$6,0)),"",IF(1>6,"","S"))
C22: The project for which this permit is issued bears the following geographical coordinates: | N22: {=IF(IFERROR(INDEX('Licence Effluent'!$F$5:$F$6,MATCH(UPPER($J$4)&"|Limit|"&2,'Licence Effluent'!$L$5:$L$6,0))&"","")="","",IF(IFERROR(INDEX('Licence Effluent'!$K$5:$K$6,MATCH(UPPER($J$4)&"|Limit|"&2,'Licence Effluent'!$L$5:$L$6,0))&"","")="","(none)",IFERROR(INDEX('Licence Effluent'!$K$5:$K$6,MATCH(UPPER($J$4)&"|Limit|"&2,'Licence Effluent'!$L$5:$L$6,0))&"","")))} | O22: =IF(N22="","",IF(COUNTIF(N$21:N22,N22)=1,MAX(O$20:O21)+1,"")) | P22: =IF(N22="","",INDEX(O$21:O$40,MATCH(N22,N$21:N$40,0))) | Q22: =IF(N22="","",P22&"|"&COUNTIF(N$21:N22,N22)) | T22: {=IF(ISNA(MATCH(UPPER($J$4)&"|Coordinate|"&2,'Licence Effluent'!$L$5:$L$6,0)),"",IF(ISNUMBER(SEARCH("1A",IFERROR(INDEX('Licence Effluent'!$F$5:$F$6,MATCH(UPPER($J$4)&"|Coordinate|"&2,'Licence Effluent'!$L$5:$L$6,0))&"",""))),"A","B"))} | U22: =IF(T22="","",T22&"|"&COUNTIF(T$21:T22,T22)) | V22: =IF(ISNA(MATCH(UPPER($J$4)&"|Source|"&2,'Licence Effluent'!$L$5:$L$6,0)),"",IF(2>6,"","S"))
C23: Table 1A: Metes and bounds of the discharge sources | L23: =IF(COUNTIF($T$21:$T$40,"A")=0,"H","") -> H | N23: {=IF(IFERROR(INDEX('Licence Effluent'!$F$5:$F$6,MATCH(UPPER($J$4)&"|Limit|"&3,'Licence Effluent'!$L$5:$L$6,0))&"","")="","",IF(IFERROR(INDEX('Licence Effluent'!$K$5:$K$6,MATCH(UPPER($J$4)&"|Limit|"&3,'Licence Effluent'!$L$5:$L$6,0))&"","")="","(none)",IFERROR(INDEX('Licence Effluent'!$K$5:$K$6,MATCH(UPPER($J$4)&"|Limit|"&3,'Licence Effluent'!$L$5:$L$6,0))&"","")))} | O23: =IF(N23="","",IF(COUNTIF(N$21:N23,N23)=1,MAX(O$20:O22)+1,"")) | P23: =IF(N23="","",INDEX(O$21:O$40,MATCH(N23,N$21:N$40,0))) | Q23: =IF(N23="","",P23&"|"&COUNTIF(N$21:N23,N23)) | T23: {=IF(ISNA(MATCH(UPPER($J$4)&"|Coordinate|"&3,'Licence Effluent'!$L$5:$L$6,0)),"",IF(ISNUMBER(SEARCH("1A",IFERROR(INDEX('Licence Effluent'!$F$5:$F$6,MATCH(UPPER($J$4)&"|Coordinate|"&3,'Licence Effluent'!$L$5:$L$6,0))&"",""))),"A","B"))} | U23: =IF(T23="","",T23&"|"&COUNTIF(T$21:T23,T23)) | V23: =IF(ISNA(MATCH(UPPER($J$4)&"|Source|"&3,'Licence Effluent'!$L$5:$L$6,0)),"",IF(3>6,"","S"))
C24: Vertex | E24: Eastern | G24: Northern | L24: =L23 -> H | N24: {=IF(IFERROR(INDEX('Licence Effluent'!$F$5:$F$6,MATCH(UPPER($J$4)&"|Limit|"&4,'Licence Effluent'!$L$5:$L$6,0))&"","")="","",IF(IFERROR(INDEX('Licence Effluent'!$K$5:$K$6,MATCH(UPPER($J$4)&"|Limit|"&4,'Licence Effluent'!$L$5:$L$6,0))&"","")="","(none)",IFERROR(INDEX('Licence Effluent'!$K$5:$K$6,MATCH(UPPER($J$4)&"|Limit|"&4,'Licence Effluent'!$L$5:$L$6,0))&"","")))} | O24: =IF(N24="","",IF(COUNTIF(N$21:N24,N24)=1,MAX(O$20:O23)+1,"")) | P24: =IF(N24="","",INDEX(O$21:O$40,MATCH(N24,N$21:N$40,0))) | Q24: =IF(N24="","",P24&"|"&COUNTIF(N$21:N24,N24)) | T24: {=IF(ISNA(MATCH(UPPER($J$4)&"|Coordinate|"&4,'Licence Effluent'!$L$5:$L$6,0)),"",IF(ISNUMBER(SEARCH("1A",IFERROR(INDEX('Licence Effluent'!$F$5:$F$6,MATCH(UPPER($J$4)&"|Coordinate|"&4,'Licence Effluent'!$L$5:$L$6,0))&"",""))),"A","B"))} | U24: =IF(T24="","",T24&"|"&COUNTIF(T$21:T24,T24)) | V24: =IF(ISNA(MATCH(UPPER($J$4)&"|Source|"&4,'Licence Effluent'!$L$5:$L$6,0)),"",IF(4>6,"","S"))
C25: {=IFERROR(INDEX('Licence Effluent'!$G$5:$G$6,MATCH(UPPER($J$4)&"|Coordinate|"&MATCH("A|1",$U$21:$U$40,0),'Licence Effluent'!$L$5:$L$6,0))&"","")} | E25: {=IFERROR(INDEX('Licence Effluent'!$H$5:$H$6,MATCH(UPPER($J$4)&"|Coordinate|"&MATCH("A|1",$U$21:$U$40,0),'Licence Effluent'!$L$5:$L$6,0))&"","")} | G25: {=IFERROR(INDEX('Licence Effluent'!$I$5:$I$6,MATCH(UPPER($J$4)&"|Coordinate|"&MATCH("A|1",$U$21:$U$40,0),'Licence Effluent'!$L$5:$L$6,0))&"","")} | L25: =IF(C25&E25&G25="","H","") -> H | N25: {=IF(IFERROR(INDEX('Licence Effluent'!$F$5:$F$6,MATCH(UPPER($J$4)&"|Limit|"&5,'Licence Effluent'!$L$5:$L$6,0))&"","")="","",IF(IFERROR(INDEX('Licence Effluent'!$K$5:$K$6,MATCH(UPPER($J$4)&"|Limit|"&5,'Licence Effluent'!$L$5:$L$6,0))&"","")="","(none)",IFERROR(INDEX('Licence Effluent'!$K$5:$K$6,MATCH(UPPER($J$4)&"|Limit|"&5,'Licence Effluent'!$L$5:$L$6,0))&"","")))} | O25: =IF(N25="","",IF(COUNTIF(N$21:N25,N25)=1,MAX(O$20:O24)+1,"")) | P25: =IF(N25="","",INDEX(O$21:O$40,MATCH(N25,N$21:N$40,0))) | Q25: =IF(N25="","",P25&"|"&COUNTIF(N$21:N25,N25)) | T25: {=IF(ISNA(MATCH(UPPER($J$4)&"|Coordinate|"&5,'Licence Effluent'!$L$5:$L$6,0)),"",IF(ISNUMBER(SEARCH("1A",IFERROR(INDEX('Licence Effluent'!$F$5:$F$6,MATCH(UPPER($J$4)&"|Coordinate|"&5,'Licence Effluent'!$L$5:$L$6,0))&"",""))),"A","B"))} | U25: =IF(T25="","",T25&"|"&COUNTIF(T$21:T25,T25)) | V25: =IF(ISNA(MATCH(UPPER($J$4)&"|Source|"&5,'Licence Effluent'!$L$5:$L$6,0)),"",IF(5>6,"","S"))
C26: {=IFERROR(INDEX('Licence Effluent'!$G$5:$G$6,MATCH(UPPER($J$4)&"|Coordinate|"&MATCH("A|2",$U$21:$U$40,0),'Licence Effluent'!$L$5:$L$6,0))&"","")} | E26: {=IFERROR(INDEX('Licence Effluent'!$H$5:$H$6,MATCH(UPPER($J$4)&"|Coordinate|"&MATCH("A|2",$U$21:$U$40,0),'Licence Effluent'!$L$5:$L$6,0))&"","")} | G26: {=IFERROR(INDEX('Licence Effluent'!$I$5:$I$6,MATCH(UPPER($J$4)&"|Coordinate|"&MATCH("A|2",$U$21:$U$40,0),'Licence Effluent'!$L$5:$L$6,0))&"","")} | L26: =IF(C26&E26&G26="","H","") -> H | N26: {=IF(IFERROR(INDEX('Licence Effluent'!$F$5:$F$6,MATCH(UPPER($J$4)&"|Limit|"&6,'Licence Effluent'!$L$5:$L$6,0))&"","")="","",IF(IFERROR(INDEX('Licence Effluent'!$K$5:$K$6,MATCH(UPPER($J$4)&"|Limit|"&6,'Licence Effluent'!$L$5:$L$6,0))&"","")="","(none)",IFERROR(INDEX('Licence Effluent'!$K$5:$K$6,MATCH(UPPER($J$4)&"|Limit|"&6,'Licence Effluent'!$L$5:$L$6,0))&"","")))} | O26: =IF(N26="","",IF(COUNTIF(N$21:N26,N26)=1,MAX(O$20:O25)+1,"")) | P26: =IF(N26="","",INDEX(O$21:O$40,MATCH(N26,N$21:N$40,0))) | Q26: =IF(N26="","",P26&"|"&COUNTIF(N$21:N26,N26)) | T26: {=IF(ISNA(MATCH(UPPER($J$4)&"|Coordinate|"&6,'Licence Effluent'!$L$5:$L$6,0)),"",IF(ISNUMBER(SEARCH("1A",IFERROR(INDEX('Licence Effluent'!$F$5:$F$6,MATCH(UPPER($J$4)&"|Coordinate|"&6,'Licence Effluent'!$L$5:$L$6,0))&"",""))),"A","B"))} | U26: =IF(T26="","",T26&"|"&COUNTIF(T$21:T26,T26)) | V26: =IF(ISNA(MATCH(UPPER($J$4)&"|Source|"&6,'Licence Effluent'!$L$5:$L$6,0)),"",IF(6>6,"","S"))
C27: {=IFERROR(INDEX('Licence Effluent'!$G$5:$G$6,MATCH(UPPER($J$4)&"|Coordinate|"&MATCH("A|3",$U$21:$U$40,0),'Licence Effluent'!$L$5:$L$6,0))&"","")} | E27: {=IFERROR(INDEX('Licence Effluent'!$H$5:$H$6,MATCH(UPPER($J$4)&"|Coordinate|"&MATCH("A|3",$U$21:$U$40,0),'Licence Effluent'!$L$5:$L$6,0))&"","")} | G27: {=IFERROR(INDEX('Licence Effluent'!$I$5:$I$6,MATCH(UPPER($J$4)&"|Coordinate|"&MATCH("A|3",$U$21:$U$40,0),'Licence Effluent'!$L$5:$L$6,0))&"","")} | L27: =IF(C27&E27&G27="","H","") -> H | N27: {=IF(IFERROR(INDEX('Licence Effluent'!$F$5:$F$6,MATCH(UPPER($J$4)&"|Limit|"&7,'Licence Effluent'!$L$5:$L$6,0))&"","")="","",IF(IFERROR(INDEX('Licence Effluent'!$K$5:$K$6,MATCH(UPPER($J$4)&"|Limit|"&7,'Licence Effluent'!$L$5:$L$6,0))&"","")="","(none)",IFERROR(INDEX('Licence Effluent'!$K$5:$K$6,MATCH(UPPER($J$4)&"|Limit|"&7,'Licence Effluent'!$L$5:$L$6,0))&"","")))} | O27: =IF(N27="","",IF(COUNTIF(N$21:N27,N27)=1,MAX(O$20:O26)+1,"")) | P27: =IF(N27="","",INDEX(O$21:O$40,MATCH(N27,N$21:N$40,0))) | Q27: =IF(N27="","",P27&"|"&COUNTIF(N$21:N27,N27)) | T27: {=IF(ISNA(MATCH(UPPER($J$4)&"|Coordinate|"&7,'Licence Effluent'!$L$5:$L$6,0)),"",IF(ISNUMBER(SEARCH("1A",IFERROR(INDEX('Licence Effluent'!$F$5:$F$6,MATCH(UPPER($J$4)&"|Coordinate|"&7,'Licence Effluent'!$L$5:$L$6,0))&"",""))),"A","B"))} | U27: =IF(T27="","",T27&"|"&COUNTIF(T$21:T27,T27)) | V27: =IF(ISNA(MATCH(UPPER($J$4)&"|Source|"&7,'Licence Effluent'!$L$5:$L$6,0)),"",IF(7>6,"","S"))
C28: {=IFERROR(INDEX('Licence Effluent'!$G$5:$G$6,MATCH(UPPER($J$4)&"|Coordinate|"&MATCH("A|4",$U$21:$U$40,0),'Licence Effluent'!$L$5:$L$6,0))&"","")} | E28: {=IFERROR(INDEX('Licence Effluent'!$H$5:$H$6,MATCH(UPPER($J$4)&"|Coordinate|"&MATCH("A|4",$U$21:$U$40,0),'Licence Effluent'!$L$5:$L$6,0))&"","")} | G28: {=IFERROR(INDEX('Licence Effluent'!$I$5:$I$6,MATCH(UPPER($J$4)&"|Coordinate|"&MATCH("A|4",$U$21:$U$40,0),'Licence Effluent'!$L$5:$L$6,0))&"","")} | L28: =IF(C28&E28&G28="","H","") -> H | N28: {=IF(IFERROR(INDEX('Licence Effluent'!$F$5:$F$6,MATCH(UPPER($J$4)&"|Limit|"&8,'Licence Effluent'!$L$5:$L$6,0))&"","")="","",IF(IFERROR(INDEX('Licence Effluent'!$K$5:$K$6,MATCH(UPPER($J$4)&"|Limit|"&8,'Licence Effluent'!$L$5:$L$6,0))&"","")="","(none)",IFERROR(INDEX('Licence Effluent'!$K$5:$K$6,MATCH(UPPER($J$4)&"|Limit|"&8,'Licence Effluent'!$L$5:$L$6,0))&"","")))} | O28: =IF(N28="","",IF(COUNTIF(N$21:N28,N28)=1,MAX(O$20:O27)+1,"")) | P28: =IF(N28="","",INDEX(O$21:O$40,MATCH(N28,N$21:N$40,0))) | Q28: =IF(N28="","",P28&"|"&COUNTIF(N$21:N28,N28)) | T28: {=IF(ISNA(MATCH(UPPER($J$4)&"|Coordinate|"&8,'Licence Effluent'!$L$5:$L$6,0)),"",IF(ISNUMBER(SEARCH("1A",IFERROR(INDEX('Licence Effluent'!$F$5:$F$6,MATCH(UPPER($J$4)&"|Coordinate|"&8,'Licence Effluent'!$L$5:$L$6,0))&"",""))),"A","B"))} | U28: =IF(T28="","",T28&"|"&COUNTIF(T$21:T28,T28)) | V28: =IF(ISNA(MATCH(UPPER($J$4)&"|Source|"&8,'Licence Effluent'!$L$5:$L$6,0)),"",IF(8>6,"","S"))
C29: {=IFERROR(INDEX('Licence Effluent'!$G$5:$G$6,MATCH(UPPER($J$4)&"|Coordinate|"&MATCH("A|5",$U$21:$U$40,0),'Licence Effluent'!$L$5:$L$6,0))&"","")} | E29: {=IFERROR(INDEX('Licence Effluent'!$H$5:$H$6,MATCH(UPPER($J$4)&"|Coordinate|"&MATCH("A|5",$U$21:$U$40,0),'Licence Effluent'!$L$5:$L$6,0))&"","")} | G29: {=IFERROR(INDEX('Licence Effluent'!$I$5:$I$6,MATCH(UPPER($J$4)&"|Coordinate|"&MATCH("A|5",$U$21:$U$40,0),'Licence Effluent'!$L$5:$L$6,0))&"","")} | L29: =IF(C29&E29&G29="","H","") -> H | N29: {=IF(IFERROR(INDEX('Licence Effluent'!$F$5:$F$6,MATCH(UPPER($J$4)&"|Limit|"&9,'Licence Effluent'!$L$5:$L$6,0))&"","")="","",IF(IFERROR(INDEX('Licence Effluent'!$K$5:$K$6,MATCH(UPPER($J$4)&"|Limit|"&9,'Licence Effluent'!$L$5:$L$6,0))&"","")="","(none)",IFERROR(INDEX('Licence Effluent'!$K$5:$K$6,MATCH(UPPER($J$4)&"|Limit|"&9,'Licence Effluent'!$L$5:$L$6,0))&"","")))} | O29: =IF(N29="","",IF(COUNTIF(N$21:N29,N29)=1,MAX(O$20:O28)+1,"")) | P29: =IF(N29="","",INDEX(O$21:O$40,MATCH(N29,N$21:N$40,0))) | Q29: =IF(N29="","",P29&"|"&COUNTIF(N$21:N29,N29)) | T29: {=IF(ISNA(MATCH(UPPER($J$4)&"|Coordinate|"&9,'Licence Effluent'!$L$5:$L$6,0)),"",IF(ISNUMBER(SEARCH("1A",IFERROR(INDEX('Licence Effluent'!$F$5:$F$6,MATCH(UPPER($J$4)&"|Coordinate|"&9,'Licence Effluent'!$L$5:$L$6,0))&"",""))),"A","B"))} | U29: =IF(T29="","",T29&"|"&COUNTIF(T$21:T29,T29)) | V29: =IF(ISNA(MATCH(UPPER($J$4)&"|Source|"&9,'Licence Effluent'!$L$5:$L$6,0)),"",IF(9>6,"","S"))
C30: {=IFERROR(INDEX('Licence Effluent'!$G$5:$G$6,MATCH(UPPER($J$4)&"|Coordinate|"&MATCH("A|6",$U$21:$U$40,0),'Licence Effluent'!$L$5:$L$6,0))&"","")} | E30: {=IFERROR(INDEX('Licence Effluent'!$H$5:$H$6,MATCH(UPPER($J$4)&"|Coordinate|"&MATCH("A|6",$U$21:$U$40,0),'Licence Effluent'!$L$5:$L$6,0))&"","")} | G30: {=IFERROR(INDEX('Licence Effluent'!$I$5:$I$6,MATCH(UPPER($J$4)&"|Coordinate|"&MATCH("A|6",$U$21:$U$40,0),'Licence Effluent'!$L$5:$L$6,0))&"","")} | L30: =IF(C30&E30&G30="","H","") -> H | N30: {=IF(IFERROR(INDEX('Licence Effluent'!$F$5:$F$6,MATCH(UPPER($J$4)&"|Limit|"&10,'Licence Effluent'!$L$5:$L$6,0))&"","")="","",IF(IFERROR(INDEX('Licence Effluent'!$K$5:$K$6,MATCH(UPPER($J$4)&"|Limit|"&10,'Licence Effluent'!$L$5:$L$6,0))&"","")="","(none)",IFERROR(INDEX('Licence Effluent'!$K$5:$K$6,MATCH(UPPER($J$4)&"|Limit|"&10,'Licence Effluent'!$L$5:$L$6,0))&"","")))} | O30: =IF(N30="","",IF(COUNTIF(N$21:N30,N30)=1,MAX(O$20:O29)+1,"")) | P30: =IF(N30="","",INDEX(O$21:O$40,MATCH(N30,N$21:N$40,0))) | Q30: =IF(N30="","",P30&"|"&COUNTIF(N$21:N30,N30)) | T30: {=IF(ISNA(MATCH(UPPER($J$4)&"|Coordinate|"&10,'Licence Effluent'!$L$5:$L$6,0)),"",IF(ISNUMBER(SEARCH("1A",IFERROR(INDEX('Licence Effluent'!$F$5:$F$6,MATCH(UPPER($J$4)&"|Coordinate|"&10,'Licence Effluent'!$L$5:$L$6,0))&"",""))),"A","B"))} | U30: =IF(T30="","",T30&"|"&COUNTIF(T$21:T30,T30)) | V30: =IF(ISNA(MATCH(UPPER($J$4)&"|Source|"&10,'Licence Effluent'!$L$5:$L$6,0)),"",IF(10>6,"","S"))
C31: {=IFERROR(INDEX('Licence Effluent'!$G$5:$G$6,MATCH(UPPER($J$4)&"|Coordinate|"&MATCH("A|7",$U$21:$U$40,0),'Licence Effluent'!$L$5:$L$6,0))&"","")} | E31: {=IFERROR(INDEX('Licence Effluent'!$H$5:$H$6,MATCH(UPPER($J$4)&"|Coordinate|"&MATCH("A|7",$U$21:$U$40,0),'Licence Effluent'!$L$5:$L$6,0))&"","")} | G31: {=IFERROR(INDEX('Licence Effluent'!$I$5:$I$6,MATCH(UPPER($J$4)&"|Coordinate|"&MATCH("A|7",$U$21:$U$40,0),'Licence Effluent'!$L$5:$L$6,0))&"","")} | L31: =IF(C31&E31&G31="","H","") -> H | N31: {=IF(IFERROR(INDEX('Licence Effluent'!$F$5:$F$6,MATCH(UPPER($J$4)&"|Limit|"&11,'Licence Effluent'!$L$5:$L$6,0))&"","")="","",IF(IFERROR(INDEX('Licence Effluent'!$K$5:$K$6,MATCH(UPPER($J$4)&"|Limit|"&11,'Licence Effluent'!$L$5:$L$6,0))&"","")="","(none)",IFERROR(INDEX('Licence Effluent'!$K$5:$K$6,MATCH(UPPER($J$4)&"|Limit|"&11,'Licence Effluent'!$L$5:$L$6,0))&"","")))} | O31: =IF(N31="","",IF(COUNTIF(N$21:N31,N31)=1,MAX(O$20:O30)+1,"")) | P31: =IF(N31="","",INDEX(O$21:O$40,MATCH(N31,N$21:N$40,0))) | Q31: =IF(N31="","",P31&"|"&COUNTIF(N$21:N31,N31)) | T31: {=IF(ISNA(MATCH(UPPER($J$4)&"|Coordinate|"&11,'Licence Effluent'!$L$5:$L$6,0)),"",IF(ISNUMBER(SEARCH("1A",IFERROR(INDEX('Licence Effluent'!$F$5:$F$6,MATCH(UPPER($J$4)&"|Coordinate|"&11,'Licence Effluent'!$L$5:$L$6,0))&"",""))),"A","B"))} | U31: =IF(T31="","",T31&"|"&COUNTIF(T$21:T31,T31)) | V31: =IF(ISNA(MATCH(UPPER($J$4)&"|Source|"&11,'Licence Effluent'!$L$5:$L$6,0)),"",IF(11>6,"","S"))
C32: {=IFERROR(INDEX('Licence Effluent'!$G$5:$G$6,MATCH(UPPER($J$4)&"|Coordinate|"&MATCH("A|8",$U$21:$U$40,0),'Licence Effluent'!$L$5:$L$6,0))&"","")} | E32: {=IFERROR(INDEX('Licence Effluent'!$H$5:$H$6,MATCH(UPPER($J$4)&"|Coordinate|"&MATCH("A|8",$U$21:$U$40,0),'Licence Effluent'!$L$5:$L$6,0))&"","")} | G32: {=IFERROR(INDEX('Licence Effluent'!$I$5:$I$6,MATCH(UPPER($J$4)&"|Coordinate|"&MATCH("A|8",$U$21:$U$40,0),'Licence Effluent'!$L$5:$L$6,0))&"","")} | L32: =IF(C32&E32&G32="","H","") -> H | N32: {=IF(IFERROR(INDEX('Licence Effluent'!$F$5:$F$6,MATCH(UPPER($J$4)&"|Limit|"&12,'Licence Effluent'!$L$5:$L$6,0))&"","")="","",IF(IFERROR(INDEX('Licence Effluent'!$K$5:$K$6,MATCH(UPPER($J$4)&"|Limit|"&12,'Licence Effluent'!$L$5:$L$6,0))&"","")="","(none)",IFERROR(INDEX('Licence Effluent'!$K$5:$K$6,MATCH(UPPER($J$4)&"|Limit|"&12,'Licence Effluent'!$L$5:$L$6,0))&"","")))} | O32: =IF(N32="","",IF(COUNTIF(N$21:N32,N32)=1,MAX(O$20:O31)+1,"")) | P32: =IF(N32="","",INDEX(O$21:O$40,MATCH(N32,N$21:N$40,0))) | Q32: =IF(N32="","",P32&"|"&COUNTIF(N$21:N32,N32)) | T32: {=IF(ISNA(MATCH(UPPER($J$4)&"|Coordinate|"&12,'Licence Effluent'!$L$5:$L$6,0)),"",IF(ISNUMBER(SEARCH("1A",IFERROR(INDEX('Licence Effluent'!$F$5:$F$6,MATCH(UPPER($J$4)&"|Coordinate|"&12,'Licence Effluent'!$L$5:$L$6,0))&"",""))),"A","B"))} | U32: =IF(T32="","",T32&"|"&COUNTIF(T$21:T32,T32)) | V32: =IF(ISNA(MATCH(UPPER($J$4)&"|Source|"&12,'Licence Effluent'!$L$5:$L$6,0)),"",IF(12>6,"","S"))
C33: {=IFERROR(INDEX('Licence Effluent'!$G$5:$G$6,MATCH(UPPER($J$4)&"|Coordinate|"&MATCH("A|9",$U$21:$U$40,0),'Licence Effluent'!$L$5:$L$6,0))&"","")} | E33: {=IFERROR(INDEX('Licence Effluent'!$H$5:$H$6,MATCH(UPPER($J$4)&"|Coordinate|"&MATCH("A|9",$U$21:$U$40,0),'Licence Effluent'!$L$5:$L$6,0))&"","")} | G33: {=IFERROR(INDEX('Licence Effluent'!$I$5:$I$6,MATCH(UPPER($J$4)&"|Coordinate|"&MATCH("A|9",$U$21:$U$40,0),'Licence Effluent'!$L$5:$L$6,0))&"","")} | L33: =IF(C33&E33&G33="","H","") -> H | N33: {=IF(IFERROR(INDEX('Licence Effluent'!$F$5:$F$6,MATCH(UPPER($J$4)&"|Limit|"&13,'Licence Effluent'!$L$5:$L$6,0))&"","")="","",IF(IFERROR(INDEX('Licence Effluent'!$K$5:$K$6,MATCH(UPPER($J$4)&"|Limit|"&13,'Licence Effluent'!$L$5:$L$6,0))&"","")="","(none)",IFERROR(INDEX('Licence Effluent'!$K$5:$K$6,MATCH(UPPER($J$4)&"|Limit|"&13,'Licence Effluent'!$L$5:$L$6,0))&"","")))} | O33: =IF(N33="","",IF(COUNTIF(N$21:N33,N33)=1,MAX(O$20:O32)+1,"")) | P33: =IF(N33="","",INDEX(O$21:O$40,MATCH(N33,N$21:N$40,0))) | Q33: =IF(N33="","",P33&"|"&COUNTIF(N$21:N33,N33)) | T33: {=IF(ISNA(MATCH(UPPER($J$4)&"|Coordinate|"&13,'Licence Effluent'!$L$5:$L$6,0)),"",IF(ISNUMBER(SEARCH("1A",IFERROR(INDEX('Licence Effluent'!$F$5:$F$6,MATCH(UPPER($J$4)&"|Coordinate|"&13,'Licence Effluent'!$L$5:$L$6,0))&"",""))),"A","B"))} | U33: =IF(T33="","",T33&"|"&COUNTIF(T$21:T33,T33)) | V33: =IF(ISNA(MATCH(UPPER($J$4)&"|Source|"&13,'Licence Effluent'!$L$5:$L$6,0)),"",IF(13>6,"","S"))
C34: {=IFERROR(INDEX('Licence Effluent'!$G$5:$G$6,MATCH(UPPER($J$4)&"|Coordinate|"&MATCH("A|10",$U$21:$U$40,0),'Licence Effluent'!$L$5:$L$6,0))&"","")} | E34: {=IFERROR(INDEX('Licence Effluent'!$H$5:$H$6,MATCH(UPPER($J$4)&"|Coordinate|"&MATCH("A|10",$U$21:$U$40,0),'Licence Effluent'!$L$5:$L$6,0))&"","")} | G34: {=IFERROR(INDEX('Licence Effluent'!$I$5:$I$6,MATCH(UPPER($J$4)&"|Coordinate|"&MATCH("A|10",$U$21:$U$40,0),'Licence Effluent'!$L$5:$L$6,0))&"","")} | L34: =IF(C34&E34&G34="","H","") -> H | N34: {=IF(IFERROR(INDEX('Licence Effluent'!$F$5:$F$6,MATCH(UPPER($J$4)&"|Limit|"&14,'Licence Effluent'!$L$5:$L$6,0))&"","")="","",IF(IFERROR(INDEX('Licence Effluent'!$K$5:$K$6,MATCH(UPPER($J$4)&"|Limit|"&14,'Licence Effluent'!$L$5:$L$6,0))&"","")="","(none)",IFERROR(INDEX('Licence Effluent'!$K$5:$K$6,MATCH(UPPER($J$4)&"|Limit|"&14,'Licence Effluent'!$L$5:$L$6,0))&"","")))} | O34: =IF(N34="","",IF(COUNTIF(N$21:N34,N34)=1,MAX(O$20:O33)+1,"")) | P34: =IF(N34="","",INDEX(O$21:O$40,MATCH(N34,N$21:N$40,0))) | Q34: =IF(N34="","",P34&"|"&COUNTIF(N$21:N34,N34)) | T34: {=IF(ISNA(MATCH(UPPER($J$4)&"|Coordinate|"&14,'Licence Effluent'!$L$5:$L$6,0)),"",IF(ISNUMBER(SEARCH("1A",IFERROR(INDEX('Licence Effluent'!$F$5:$F$6,MATCH(UPPER($J$4)&"|Coordinate|"&14,'Licence Effluent'!$L$5:$L$6,0))&"",""))),"A","B"))} | U34: =IF(T34="","",T34&"|"&COUNTIF(T$21:T34,T34)) | V34: =IF(ISNA(MATCH(UPPER($J$4)&"|Source|"&14,'Licence Effluent'!$L$5:$L$6,0)),"",IF(14>6,"","S"))
C35: Table 1B: Metes and bounds of the discharge sources | L35: =IF(COUNTIF($T$21:$T$40,"B")+COUNTIF($V$21:$V$40,"S")=0,"H","") -> H | N35: {=IF(IFERROR(INDEX('Licence Effluent'!$F$5:$F$6,MATCH(UPPER($J$4)&"|Limit|"&15,'Licence Effluent'!$L$5:$L$6,0))&"","")="","",IF(IFERROR(INDEX('Licence Effluent'!$K$5:$K$6,MATCH(UPPER($J$4)&"|Limit|"&15,'Licence Effluent'!$L$5:$L$6,0))&"","")="","(none)",IFERROR(INDEX('Licence Effluent'!$K$5:$K$6,MATCH(UPPER($J$4)&"|Limit|"&15,'Licence Effluent'!$L$5:$L$6,0))&"","")))} | O35: =IF(N35="","",IF(COUNTIF(N$21:N35,N35)=1,MAX(O$20:O34)+1,"")) | P35: =IF(N35="","",INDEX(O$21:O$40,MATCH(N35,N$21:N$40,0))) | Q35: =IF(N35="","",P35&"|"&COUNTIF(N$21:N35,N35)) | T35: {=IF(ISNA(MATCH(UPPER($J$4)&"|Coordinate|"&15,'Licence Effluent'!$L$5:$L$6,0)),"",IF(ISNUMBER(SEARCH("1A",IFERROR(INDEX('Licence Effluent'!$F$5:$F$6,MATCH(UPPER($J$4)&"|Coordinate|"&15,'Licence Effluent'!$L$5:$L$6,0))&"",""))),"A","B"))} | U35: =IF(T35="","",T35&"|"&COUNTIF(T$21:T35,T35)) | V35: =IF(ISNA(MATCH(UPPER($J$4)&"|Source|"&15,'Licence Effluent'!$L$5:$L$6,0)),"",IF(15>6,"","S"))
C36: Discharge source | E36: X | G36: Y | L36: =IF(COUNTIF($V$21:$V$40,"S")=0,"H","") -> H | N36: {=IF(IFERROR(INDEX('Licence Effluent'!$F$5:$F$6,MATCH(UPPER($J$4)&"|Limit|"&16,'Licence Effluent'!$L$5:$L$6,0))&"","")="","",IF(IFERROR(INDEX('Licence Effluent'!$K$5:$K$6,MATCH(UPPER($J$4)&"|Limit|"&16,'Licence Effluent'!$L$5:$L$6,0))&"","")="","(none)",IFERROR(INDEX('Licence Effluent'!$K$5:$K$6,MATCH(UPPER($J$4)&"|Limit|"&16,'Licence Effluent'!$L$5:$L$6,0))&"","")))} | O36: =IF(N36="","",IF(COUNTIF(N$21:N36,N36)=1,MAX(O$20:O35)+1,"")) | P36: =IF(N36="","",INDEX(O$21:O$40,MATCH(N36,N$21:N$40,0))) | Q36: =IF(N36="","",P36&"|"&COUNTIF(N$21:N36,N36)) | T36: {=IF(ISNA(MATCH(UPPER($J$4)&"|Coordinate|"&16,'Licence Effluent'!$L$5:$L$6,0)),"",IF(ISNUMBER(SEARCH("1A",IFERROR(INDEX('Licence Effluent'!$F$5:$F$6,MATCH(UPPER($J$4)&"|Coordinate|"&16,'Licence Effluent'!$L$5:$L$6,0))&"",""))),"A","B"))} | U36: =IF(T36="","",T36&"|"&COUNTIF(T$21:T36,T36)) | V36: =IF(ISNA(MATCH(UPPER($J$4)&"|Source|"&16,'Licence Effluent'!$L$5:$L$6,0)),"",IF(16>6,"","S"))
C37: {=IFERROR(INDEX('Licence Effluent'!$F$5:$F$6,MATCH(UPPER($J$4)&"|Source|"&1,'Licence Effluent'!$L$5:$L$6,0))&"","")} | E37: {=IFERROR(INDEX('Licence Effluent'!$H$5:$H$6,MATCH(UPPER($J$4)&"|Source|"&1,'Licence Effluent'!$L$5:$L$6,0))&"","")} | G37: {=IFERROR(INDEX('Licence Effluent'!$I$5:$I$6,MATCH(UPPER($J$4)&"|Source|"&1,'Licence Effluent'!$L$5:$L$6,0))&"","")} | L37: =IF(C37="","H","") -> H | N37: {=IF(IFERROR(INDEX('Licence Effluent'!$F$5:$F$6,MATCH(UPPER($J$4)&"|Limit|"&17,'Licence Effluent'!$L$5:$L$6,0))&"","")="","",IF(IFERROR(INDEX('Licence Effluent'!$K$5:$K$6,MATCH(UPPER($J$4)&"|Limit|"&17,'Licence Effluent'!$L$5:$L$6,0))&"","")="","(none)",IFERROR(INDEX('Licence Effluent'!$K$5:$K$6,MATCH(UPPER($J$4)&"|Limit|"&17,'Licence Effluent'!$L$5:$L$6,0))&"","")))} | O37: =IF(N37="","",IF(COUNTIF(N$21:N37,N37)=1,MAX(O$20:O36)+1,"")) | P37: =IF(N37="","",INDEX(O$21:O$40,MATCH(N37,N$21:N$40,0))) | Q37: =IF(N37="","",P37&"|"&COUNTIF(N$21:N37,N37)) | T37: {=IF(ISNA(MATCH(UPPER($J$4)&"|Coordinate|"&17,'Licence Effluent'!$L$5:$L$6,0)),"",IF(ISNUMBER(SEARCH("1A",IFERROR(INDEX('Licence Effluent'!$F$5:$F$6,MATCH(UPPER($J$4)&"|Coordinate|"&17,'Licence Effluent'!$L$5:$L$6,0))&"",""))),"A","B"))} | U37: =IF(T37="","",T37&"|"&COUNTIF(T$21:T37,T37)) | V37: =IF(ISNA(MATCH(UPPER($J$4)&"|Source|"&17,'Licence Effluent'!$L$5:$L$6,0)),"",IF(17>6,"","S"))
C38: {=IFERROR(INDEX('Licence Effluent'!$F$5:$F$6,MATCH(UPPER($J$4)&"|Source|"&2,'Licence Effluent'!$L$5:$L$6,0))&"","")} | E38: {=IFERROR(INDEX('Licence Effluent'!$H$5:$H$6,MATCH(UPPER($J$4)&"|Source|"&2,'Licence Effluent'!$L$5:$L$6,0))&"","")} | G38: {=IFERROR(INDEX('Licence Effluent'!$I$5:$I$6,MATCH(UPPER($J$4)&"|Source|"&2,'Licence Effluent'!$L$5:$L$6,0))&"","")} | L38: =IF(C38="","H","") -> H | N38: {=IF(IFERROR(INDEX('Licence Effluent'!$F$5:$F$6,MATCH(UPPER($J$4)&"|Limit|"&18,'Licence Effluent'!$L$5:$L$6,0))&"","")="","",IF(IFERROR(INDEX('Licence Effluent'!$K$5:$K$6,MATCH(UPPER($J$4)&"|Limit|"&18,'Licence Effluent'!$L$5:$L$6,0))&"","")="","(none)",IFERROR(INDEX('Licence Effluent'!$K$5:$K$6,MATCH(UPPER($J$4)&"|Limit|"&18,'Licence Effluent'!$L$5:$L$6,0))&"","")))} | O38: =IF(N38="","",IF(COUNTIF(N$21:N38,N38)=1,MAX(O$20:O37)+1,"")) | P38: =IF(N38="","",INDEX(O$21:O$40,MATCH(N38,N$21:N$40,0))) | Q38: =IF(N38="","",P38&"|"&COUNTIF(N$21:N38,N38)) | T38: {=IF(ISNA(MATCH(UPPER($J$4)&"|Coordinate|"&18,'Licence Effluent'!$L$5:$L$6,0)),"",IF(ISNUMBER(SEARCH("1A",IFERROR(INDEX('Licence Effluent'!$F$5:$F$6,MATCH(UPPER($J$4)&"|Coordinate|"&18,'Licence Effluent'!$L$5:$L$6,0))&"",""))),"A","B"))} | U38: =IF(T38="","",T38&"|"&COUNTIF(T$21:T38,T38)) | V38: =IF(ISNA(MATCH(UPPER($J$4)&"|Source|"&18,'Licence Effluent'!$L$5:$L$6,0)),"",IF(18>6,"","S"))
C39: {=IFERROR(INDEX('Licence Effluent'!$F$5:$F$6,MATCH(UPPER($J$4)&"|Source|"&3,'Licence Effluent'!$L$5:$L$6,0))&"","")} | E39: {=IFERROR(INDEX('Licence Effluent'!$H$5:$H$6,MATCH(UPPER($J$4)&"|Source|"&3,'Licence Effluent'!$L$5:$L$6,0))&"","")} | G39: {=IFERROR(INDEX('Licence Effluent'!$I$5:$I$6,MATCH(UPPER($J$4)&"|Source|"&3,'Licence Effluent'!$L$5:$L$6,0))&"","")} | L39: =IF(C39="","H","") -> H | N39: {=IF(IFERROR(INDEX('Licence Effluent'!$F$5:$F$6,MATCH(UPPER($J$4)&"|Limit|"&19,'Licence Effluent'!$L$5:$L$6,0))&"","")="","",IF(IFERROR(INDEX('Licence Effluent'!$K$5:$K$6,MATCH(UPPER($J$4)&"|Limit|"&19,'Licence Effluent'!$L$5:$L$6,0))&"","")="","(none)",IFERROR(INDEX('Licence Effluent'!$K$5:$K$6,MATCH(UPPER($J$4)&"|Limit|"&19,'Licence Effluent'!$L$5:$L$6,0))&"","")))} | O39: =IF(N39="","",IF(COUNTIF(N$21:N39,N39)=1,MAX(O$20:O38)+1,"")) | P39: =IF(N39="","",INDEX(O$21:O$40,MATCH(N39,N$21:N$40,0))) | Q39: =IF(N39="","",P39&"|"&COUNTIF(N$21:N39,N39)) | T39: {=IF(ISNA(MATCH(UPPER($J$4)&"|Coordinate|"&19,'Licence Effluent'!$L$5:$L$6,0)),"",IF(ISNUMBER(SEARCH("1A",IFERROR(INDEX('Licence Effluent'!$F$5:$F$6,MATCH(UPPER($J$4)&"|Coordinate|"&19,'Licence Effluent'!$L$5:$L$6,0))&"",""))),"A","B"))} | U39: =IF(T39="","",T39&"|"&COUNTIF(T$21:T39,T39)) | V39: =IF(ISNA(MATCH(UPPER($J$4)&"|Source|"&19,'Licence Effluent'!$L$5:$L$6,0)),"",IF(19>6,"","S"))
C40: {=IFERROR(INDEX('Licence Effluent'!$F$5:$F$6,MATCH(UPPER($J$4)&"|Source|"&4,'Licence Effluent'!$L$5:$L$6,0))&"","")} | E40: {=IFERROR(INDEX('Licence Effluent'!$H$5:$H$6,MATCH(UPPER($J$4)&"|Source|"&4,'Licence Effluent'!$L$5:$L$6,0))&"","")} | G40: {=IFERROR(INDEX('Licence Effluent'!$I$5:$I$6,MATCH(UPPER($J$4)&"|Source|"&4,'Licence Effluent'!$L$5:$L$6,0))&"","")} | L40: =IF(C40="","H","") -> H | N40: {=IF(IFERROR(INDEX('Licence Effluent'!$F$5:$F$6,MATCH(UPPER($J$4)&"|Limit|"&20,'Licence Effluent'!$L$5:$L$6,0))&"","")="","",IF(IFERROR(INDEX('Licence Effluent'!$K$5:$K$6,MATCH(UPPER($J$4)&"|Limit|"&20,'Licence Effluent'!$L$5:$L$6,0))&"","")="","(none)",IFERROR(INDEX('Licence Effluent'!$K$5:$K$6,MATCH(UPPER($J$4)&"|Limit|"&20,'Licence Effluent'!$L$5:$L$6,0))&"","")))} | O40: =IF(N40="","",IF(COUNTIF(N$21:N40,N40)=1,MAX(O$20:O39)+1,"")) | P40: =IF(N40="","",INDEX(O$21:O$40,MATCH(N40,N$21:N$40,0))) | Q40: =IF(N40="","",P40&"|"&COUNTIF(N$21:N40,N40)) | T40: {=IF(ISNA(MATCH(UPPER($J$4)&"|Coordinate|"&20,'Licence Effluent'!$L$5:$L$6,0)),"",IF(ISNUMBER(SEARCH("1A",IFERROR(INDEX('Licence Effluent'!$F$5:$F$6,MATCH(UPPER($J$4)&"|Coordinate|"&20,'Licence Effluent'!$L$5:$L$6,0))&"",""))),"A","B"))} | U40: =IF(T40="","",T40&"|"&COUNTIF(T$21:T40,T40)) | V40: =IF(ISNA(MATCH(UPPER($J$4)&"|Source|"&20,'Licence Effluent'!$L$5:$L$6,0)),"",IF(20>6,"","S"))
C41: {=IFERROR(INDEX('Licence Effluent'!$F$5:$F$6,MATCH(UPPER($J$4)&"|Source|"&5,'Licence Effluent'!$L$5:$L$6,0))&"","")} | E41: {=IFERROR(INDEX('Licence Effluent'!$H$5:$H$6,MATCH(UPPER($J$4)&"|Source|"&5,'Licence Effluent'!$L$5:$L$6,0))&"","")} | G41: {=IFERROR(INDEX('Licence Effluent'!$I$5:$I$6,MATCH(UPPER($J$4)&"|Source|"&5,'Licence Effluent'!$L$5:$L$6,0))&"","")} | L41: =IF(C41="","H","") -> H
C42: {=IFERROR(INDEX('Licence Effluent'!$F$5:$F$6,MATCH(UPPER($J$4)&"|Source|"&6,'Licence Effluent'!$L$5:$L$6,0))&"","")} | E42: {=IFERROR(INDEX('Licence Effluent'!$H$5:$H$6,MATCH(UPPER($J$4)&"|Source|"&6,'Licence Effluent'!$L$5:$L$6,0))&"","")} | G42: {=IFERROR(INDEX('Licence Effluent'!$I$5:$I$6,MATCH(UPPER($J$4)&"|Source|"&6,'Licence Effluent'!$L$5:$L$6,0))&"","")} | L42: =IF(C42="","H","") -> H | N42: Stage names
C43: Vertex | E43: Eastern | G43: Northern | L43: =IF(COUNTIF($T$21:$T$40,"B")=0,"H","") -> H | N43: {=IFERROR(INDEX(N$21:N$40,MATCH(1,O$21:O$40,0)),"")}
C44: {=IFERROR(INDEX('Licence Effluent'!$G$5:$G$6,MATCH(UPPER($J$4)&"|Coordinate|"&MATCH("B|1",$U$21:$U$40,0),'Licence Effluent'!$L$5:$L$6,0))&"","")} | E44: {=IFERROR(INDEX('Licence Effluent'!$H$5:$H$6,MATCH(UPPER($J$4)&"|Coordinate|"&MATCH("B|1",$U$21:$U$40,0),'Licence Effluent'!$L$5:$L$6,0))&"","")} | G44: {=IFERROR(INDEX('Licence Effluent'!$I$5:$I$6,MATCH(UPPER($J$4)&"|Coordinate|"&MATCH("B|1",$U$21:$U$40,0),'Licence Effluent'!$L$5:$L$6,0))&"","")} | L44: =IF(C44&E44&G44="","H","") -> H | N44: {=IFERROR(INDEX(N$21:N$40,MATCH(2,O$21:O$40,0)),"")}
C45: {=IFERROR(INDEX('Licence Effluent'!$G$5:$G$6,MATCH(UPPER($J$4)&"|Coordinate|"&MATCH("B|2",$U$21:$U$40,0),'Licence Effluent'!$L$5:$L$6,0))&"","")} | E45: {=IFERROR(INDEX('Licence Effluent'!$H$5:$H$6,MATCH(UPPER($J$4)&"|Coordinate|"&MATCH("B|2",$U$21:$U$40,0),'Licence Effluent'!$L$5:$L$6,0))&"","")} | G45: {=IFERROR(INDEX('Licence Effluent'!$I$5:$I$6,MATCH(UPPER($J$4)&"|Coordinate|"&MATCH("B|2",$U$21:$U$40,0),'Licence Effluent'!$L$5:$L$6,0))&"","")} | L45: =IF(C45&E45&G45="","H","") -> H | N45: {=IFERROR(INDEX(N$21:N$40,MATCH(3,O$21:O$40,0)),"")}
C46: {=IFERROR(INDEX('Licence Effluent'!$G$5:$G$6,MATCH(UPPER($J$4)&"|Coordinate|"&MATCH("B|3",$U$21:$U$40,0),'Licence Effluent'!$L$5:$L$6,0))&"","")} | E46: {=IFERROR(INDEX('Licence Effluent'!$H$5:$H$6,MATCH(UPPER($J$4)&"|Coordinate|"&MATCH("B|3",$U$21:$U$40,0),'Licence Effluent'!$L$5:$L$6,0))&"","")} | G46: {=IFERROR(INDEX('Licence Effluent'!$I$5:$I$6,MATCH(UPPER($J$4)&"|Coordinate|"&MATCH("B|3",$U$21:$U$40,0),'Licence Effluent'!$L$5:$L$6,0))&"","")} | L46: =IF(C46&E46&G46="","H","") -> H | N46: =MAX(O21:O40) -> 0
C47: {=IFERROR(INDEX('Licence Effluent'!$G$5:$G$6,MATCH(UPPER($J$4)&"|Coordinate|"&MATCH("B|4",$U$21:$U$40,0),'Licence Effluent'!$L$5:$L$6,0))&"","")} | E47: {=IFERROR(INDEX('Licence Effluent'!$H$5:$H$6,MATCH(UPPER($J$4)&"|Coordinate|"&MATCH("B|4",$U$21:$U$40,0),'Licence Effluent'!$L$5:$L$6,0))&"","")} | G47: {=IFERROR(INDEX('Licence Effluent'!$I$5:$I$6,MATCH(UPPER($J$4)&"|Coordinate|"&MATCH("B|4",$U$21:$U$40,0),'Licence Effluent'!$L$5:$L$6,0))&"","")} | L47: =IF(C47&E47&G47="","H","") -> H
C48: {=IFERROR(INDEX('Licence Effluent'!$G$5:$G$6,MATCH(UPPER($J$4)&"|Coordinate|"&MATCH("B|5",$U$21:$U$40,0),'Licence Effluent'!$L$5:$L$6,0))&"","")} | E48: {=IFERROR(INDEX('Licence Effluent'!$H$5:$H$6,MATCH(UPPER($J$4)&"|Coordinate|"&MATCH("B|5",$U$21:$U$40,0),'Licence Effluent'!$L$5:$L$6,0))&"","")} | G48: {=IFERROR(INDEX('Licence Effluent'!$I$5:$I$6,MATCH(UPPER($J$4)&"|Coordinate|"&MATCH("B|5",$U$21:$U$40,0),'Licence Effluent'!$L$5:$L$6,0))&"","")} | L48: =IF(C48&E48&G48="","H","") -> H
C49: {=IFERROR(INDEX('Licence Effluent'!$G$5:$G$6,MATCH(UPPER($J$4)&"|Coordinate|"&MATCH("B|6",$U$21:$U$40,0),'Licence Effluent'!$L$5:$L$6,0))&"","")} | E49: {=IFERROR(INDEX('Licence Effluent'!$H$5:$H$6,MATCH(UPPER($J$4)&"|Coordinate|"&MATCH("B|6",$U$21:$U$40,0),'Licence Effluent'!$L$5:$L$6,0))&"","")} | G49: {=IFERROR(INDEX('Licence Effluent'!$I$5:$I$6,MATCH(UPPER($J$4)&"|Coordinate|"&MATCH("B|6",$U$21:$U$40,0),'Licence Effluent'!$L$5:$L$6,0))&"","")} | L49: =IF(C49&E49&G49="","H","") -> H
C50: {=IFERROR(INDEX('Licence Effluent'!$G$5:$G$6,MATCH(UPPER($J$4)&"|Coordinate|"&MATCH("B|7",$U$21:$U$40,0),'Licence Effluent'!$L$5:$L$6,0))&"","")} | E50: {=IFERROR(INDEX('Licence Effluent'!$H$5:$H$6,MATCH(UPPER($J$4)&"|Coordinate|"&MATCH("B|7",$U$21:$U$40,0),'Licence Effluent'!$L$5:$L$6,0))&"","")} | G50: {=IFERROR(INDEX('Licence Effluent'!$I$5:$I$6,MATCH(UPPER($J$4)&"|Coordinate|"&MATCH("B|7",$U$21:$U$40,0),'Licence Effluent'!$L$5:$L$6,0))&"","")} | L50: =IF(C50&E50&G50="","H","") -> H
C51: {=IFERROR(INDEX('Licence Effluent'!$G$5:$G$6,MATCH(UPPER($J$4)&"|Coordinate|"&MATCH("B|8",$U$21:$U$40,0),'Licence Effluent'!$L$5:$L$6,0))&"","")} | E51: {=IFERROR(INDEX('Licence Effluent'!$H$5:$H$6,MATCH(UPPER($J$4)&"|Coordinate|"&MATCH("B|8",$U$21:$U$40,0),'Licence Effluent'!$L$5:$L$6,0))&"","")} | G51: {=IFERROR(INDEX('Licence Effluent'!$I$5:$I$6,MATCH(UPPER($J$4)&"|Coordinate|"&MATCH("B|8",$U$21:$U$40,0),'Licence Effluent'!$L$5:$L$6,0))&"","")} | L51: =IF(C51&E51&G51="","H","") -> H
C52: {=IFERROR(INDEX('Licence Effluent'!$G$5:$G$6,MATCH(UPPER($J$4)&"|Coordinate|"&MATCH("B|9",$U$21:$U$40,0),'Licence Effluent'!$L$5:$L$6,0))&"","")} | E52: {=IFERROR(INDEX('Licence Effluent'!$H$5:$H$6,MATCH(UPPER($J$4)&"|Coordinate|"&MATCH("B|9",$U$21:$U$40,0),'Licence Effluent'!$L$5:$L$6,0))&"","")} | G52: {=IFERROR(INDEX('Licence Effluent'!$I$5:$I$6,MATCH(UPPER($J$4)&"|Coordinate|"&MATCH("B|9",$U$21:$U$40,0),'Licence Effluent'!$L$5:$L$6,0))&"","")} | L52: =IF(C52&E52&G52="","H","") -> H
C53: {=IFERROR(INDEX('Licence Effluent'!$G$5:$G$6,MATCH(UPPER($J$4)&"|Coordinate|"&MATCH("B|10",$U$21:$U$40,0),'Licence Effluent'!$L$5:$L$6,0))&"","")} | E53: {=IFERROR(INDEX('Licence Effluent'!$H$5:$H$6,MATCH(UPPER($J$4)&"|Coordinate|"&MATCH("B|10",$U$21:$U$40,0),'Licence Effluent'!$L$5:$L$6,0))&"","")} | G53: {=IFERROR(INDEX('Licence Effluent'!$I$5:$I$6,MATCH(UPPER($J$4)&"|Coordinate|"&MATCH("B|10",$U$21:$U$40,0),'Licence Effluent'!$L$5:$L$6,0))&"","")} | L53: =IF(C53&E53&G53="","H","") -> H
C54: {=IFERROR(INDEX('Licence Effluent'!$G$5:$G$6,MATCH(UPPER($J$4)&"|Coordinate|"&MATCH("B|11",$U$21:$U$40,0),'Licence Effluent'!$L$5:$L$6,0))&"","")} | E54: {=IFERROR(INDEX('Licence Effluent'!$H$5:$H$6,MATCH(UPPER($J$4)&"|Coordinate|"&MATCH("B|11",$U$21:$U$40,0),'Licence Effluent'!$L$5:$L$6,0))&"","")} | G54: {=IFERROR(INDEX('Licence Effluent'!$I$5:$I$6,MATCH(UPPER($J$4)&"|Coordinate|"&MATCH("B|11",$U$21:$U$40,0),'Licence Effluent'!$L$5:$L$6,0))&"","")} | L54: =IF(C54&E54&G54="","H","") -> H
C55: {=IFERROR(INDEX('Licence Effluent'!$G$5:$G$6,MATCH(UPPER($J$4)&"|Coordinate|"&MATCH("B|12",$U$21:$U$40,0),'Licence Effluent'!$L$5:$L$6,0))&"","")} | E55: {=IFERROR(INDEX('Licence Effluent'!$H$5:$H$6,MATCH(UPPER($J$4)&"|Coordinate|"&MATCH("B|12",$U$21:$U$40,0),'Licence Effluent'!$L$5:$L$6,0))&"","")} | G55: {=IFERROR(INDEX('Licence Effluent'!$I$5:$I$6,MATCH(UPPER($J$4)&"|Coordinate|"&MATCH("B|12",$U$21:$U$40,0),'Licence Effluent'!$L$5:$L$6,0))&"","")} | L55: =IF(C55&E55&G55="","H","") -> H
C56: {=IFERROR(INDEX('Licence Effluent'!$G$5:$G$6,MATCH(UPPER($J$4)&"|Coordinate|"&MATCH("B|13",$U$21:$U$40,0),'Licence Effluent'!$L$5:$L$6,0))&"","")} | E56: {=IFERROR(INDEX('Licence Effluent'!$H$5:$H$6,MATCH(UPPER($J$4)&"|Coordinate|"&MATCH("B|13",$U$21:$U$40,0),'Licence Effluent'!$L$5:$L$6,0))&"","")} | G56: {=IFERROR(INDEX('Licence Effluent'!$I$5:$I$6,MATCH(UPPER($J$4)&"|Coordinate|"&MATCH("B|13",$U$21:$U$40,0),'Licence Effluent'!$L$5:$L$6,0))&"","")} | L56: =IF(C56&E56&G56="","H","") -> H
C57: {=IFERROR(INDEX('Licence Effluent'!$G$5:$G$6,MATCH(UPPER($J$4)&"|Coordinate|"&MATCH("B|14",$U$21:$U$40,0),'Licence Effluent'!$L$5:$L$6,0))&"","")} | E57: {=IFERROR(INDEX('Licence Effluent'!$H$5:$H$6,MATCH(UPPER($J$4)&"|Coordinate|"&MATCH("B|14",$U$21:$U$40,0),'Licence Effluent'!$L$5:$L$6,0))&"","")} | G57: {=IFERROR(INDEX('Licence Effluent'!$I$5:$I$6,MATCH(UPPER($J$4)&"|Coordinate|"&MATCH("B|14",$U$21:$U$40,0),'Licence Effluent'!$L$5:$L$6,0))&"","")} | L57: =IF(C57&E57&G57="","H","") -> H
C58: {=IFERROR(INDEX('Licence Effluent'!$G$5:$G$6,MATCH(UPPER($J$4)&"|Coordinate|"&MATCH("B|15",$U$21:$U$40,0),'Licence Effluent'!$L$5:$L$6,0))&"","")} | E58: {=IFERROR(INDEX('Licence Effluent'!$H$5:$H$6,MATCH(UPPER($J$4)&"|Coordinate|"&MATCH("B|15",$U$21:$U$40,0),'Licence Effluent'!$L$5:$L$6,0))&"","")} | G58: {=IFERROR(INDEX('Licence Effluent'!$I$5:$I$6,MATCH(UPPER($J$4)&"|Coordinate|"&MATCH("B|15",$U$21:$U$40,0),'Licence Effluent'!$L$5:$L$6,0))&"","")} | L58: =IF(C58&E58&G58="","H","") -> H
C59: {=IFERROR(INDEX('Licence Effluent'!$G$5:$G$6,MATCH(UPPER($J$4)&"|Coordinate|"&MATCH("B|16",$U$21:$U$40,0),'Licence Effluent'!$L$5:$L$6,0))&"","")} | E59: {=IFERROR(INDEX('Licence Effluent'!$H$5:$H$6,MATCH(UPPER($J$4)&"|Coordinate|"&MATCH("B|16",$U$21:$U$40,0),'Licence Effluent'!$L$5:$L$6,0))&"","")} | G59: {=IFERROR(INDEX('Licence Effluent'!$I$5:$I$6,MATCH(UPPER($J$4)&"|Coordinate|"&MATCH("B|16",$U$21:$U$40,0),'Licence Effluent'!$L$5:$L$6,0))&"","")} | L59: =IF(C59&E59&G59="","H","") -> H
C60: {=IFERROR(INDEX('Licence Effluent'!$G$5:$G$6,MATCH(UPPER($J$4)&"|Coordinate|"&MATCH("B|17",$U$21:$U$40,0),'Licence Effluent'!$L$5:$L$6,0))&"","")} | E60: {=IFERROR(INDEX('Licence Effluent'!$H$5:$H$6,MATCH(UPPER($J$4)&"|Coordinate|"&MATCH("B|17",$U$21:$U$40,0),'Licence Effluent'!$L$5:$L$6,0))&"","")} | G60: {=IFERROR(INDEX('Licence Effluent'!$I$5:$I$6,MATCH(UPPER($J$4)&"|Coordinate|"&MATCH("B|17",$U$21:$U$40,0),'Licence Effluent'!$L$5:$L$6,0))&"","")} | L60: =IF(C60&E60&G60="","H","") -> H
C61: {=IFERROR(INDEX('Licence Effluent'!$G$5:$G$6,MATCH(UPPER($J$4)&"|Coordinate|"&MATCH("B|18",$U$21:$U$40,0),'Licence Effluent'!$L$5:$L$6,0))&"","")} | E61: {=IFERROR(INDEX('Licence Effluent'!$H$5:$H$6,MATCH(UPPER($J$4)&"|Coordinate|"&MATCH("B|18",$U$21:$U$40,0),'Licence Effluent'!$L$5:$L$6,0))&"","")} | G61: {=IFERROR(INDEX('Licence Effluent'!$I$5:$I$6,MATCH(UPPER($J$4)&"|Coordinate|"&MATCH("B|18",$U$21:$U$40,0),'Licence Effluent'!$L$5:$L$6,0))&"","")} | L61: =IF(C61&E61&G61="","H","") -> H
C62: {=IFERROR(INDEX('Licence Effluent'!$G$5:$G$6,MATCH(UPPER($J$4)&"|Coordinate|"&MATCH("B|19",$U$21:$U$40,0),'Licence Effluent'!$L$5:$L$6,0))&"","")} | E62: {=IFERROR(INDEX('Licence Effluent'!$H$5:$H$6,MATCH(UPPER($J$4)&"|Coordinate|"&MATCH("B|19",$U$21:$U$40,0),'Licence Effluent'!$L$5:$L$6,0))&"","")} | G62: {=IFERROR(INDEX('Licence Effluent'!$I$5:$I$6,MATCH(UPPER($J$4)&"|Coordinate|"&MATCH("B|19",$U$21:$U$40,0),'Licence Effluent'!$L$5:$L$6,0))&"","")} | L62: =IF(C62&E62&G62="","H","") -> H
C63: {=IFERROR(INDEX('Licence Effluent'!$G$5:$G$6,MATCH(UPPER($J$4)&"|Coordinate|"&MATCH("B|20",$U$21:$U$40,0),'Licence Effluent'!$L$5:$L$6,0))&"","")} | E63: {=IFERROR(INDEX('Licence Effluent'!$H$5:$H$6,MATCH(UPPER($J$4)&"|Coordinate|"&MATCH("B|20",$U$21:$U$40,0),'Licence Effluent'!$L$5:$L$6,0))&"","")} | G63: {=IFERROR(INDEX('Licence Effluent'!$I$5:$I$6,MATCH(UPPER($J$4)&"|Coordinate|"&MATCH("B|20",$U$21:$U$40,0),'Licence Effluent'!$L$5:$L$6,0))&"","")} | L63: =IF(C63&E63&G63="","H","") -> H
C64: The use of this license is solely restricted to the aforementioned metes and bounds. Any change in the project location without prior notification and approval of the agency is a violation.
B66: 2.0 EFFLUENT DISCHARGE
C67: ="In pursuance of the Environment Protection & Management Law of Liberia, 2003 Part III Sections 8 (1), 13 and based on the Submitted Project Brief and Audit Report for Effluent Discharge, "&$J$8&" is hereby issued this License to discharge treated effluent water as per the applicable Class of the Liberia Water Quality Standards/Guide (1987), Liberia Effluent Guideline Values and IFC Effluent guidelines as indicated below:" -> In pursuance of the Environment Protection & Management Law of Liberia, 2003 Part III Sections 8 (1), 13 and based on the Submitted Project Brief and Audit Report for Effluent Discharge, Tanmay Hardware Center is hereby issued this License to discharge treated effluent water as per the applicable Class of the Liberia Water Quality Standards/Guide (1987), Liberia Effluent Guideline Values and IFC Effluent guidelines as indicated below:
C68: Table 2: Effluent discharge sources and receiving units.
C69: Discharge source | F69: Receiving unit
C70: {=IFERROR(INDEX('Licence Effluent'!$F$5:$F$6,MATCH(UPPER($J$4)&"|Source|"&1,'Licence Effluent'!$L$5:$L$6,0))&"","")} | F70: {=IFERROR(INDEX('Licence Effluent'!$G$5:$G$6,MATCH(UPPER($J$4)&"|Source|"&1,'Licence Effluent'!$L$5:$L$6,0))&"","")} | L70: =IF(C70="","H","") -> H
C71: {=IFERROR(INDEX('Licence Effluent'!$F$5:$F$6,MATCH(UPPER($J$4)&"|Source|"&2,'Licence Effluent'!$L$5:$L$6,0))&"","")} | F71: {=IFERROR(INDEX('Licence Effluent'!$G$5:$G$6,MATCH(UPPER($J$4)&"|Source|"&2,'Licence Effluent'!$L$5:$L$6,0))&"","")} | L71: =IF(C71="","H","") -> H
C72: {=IFERROR(INDEX('Licence Effluent'!$F$5:$F$6,MATCH(UPPER($J$4)&"|Source|"&3,'Licence Effluent'!$L$5:$L$6,0))&"","")} | F72: {=IFERROR(INDEX('Licence Effluent'!$G$5:$G$6,MATCH(UPPER($J$4)&"|Source|"&3,'Licence Effluent'!$L$5:$L$6,0))&"","")} | L72: =IF(C72="","H","") -> H
C73: {=IFERROR(INDEX('Licence Effluent'!$F$5:$F$6,MATCH(UPPER($J$4)&"|Source|"&4,'Licence Effluent'!$L$5:$L$6,0))&"","")} | F73: {=IFERROR(INDEX('Licence Effluent'!$G$5:$G$6,MATCH(UPPER($J$4)&"|Source|"&4,'Licence Effluent'!$L$5:$L$6,0))&"","")} | L73: =IF(C73="","H","") -> H
C74: {=IFERROR(INDEX('Licence Effluent'!$F$5:$F$6,MATCH(UPPER($J$4)&"|Source|"&5,'Licence Effluent'!$L$5:$L$6,0))&"","")} | F74: {=IFERROR(INDEX('Licence Effluent'!$G$5:$G$6,MATCH(UPPER($J$4)&"|Source|"&5,'Licence Effluent'!$L$5:$L$6,0))&"","")} | L74: =IF(C74="","H","") -> H
C75: {=IFERROR(INDEX('Licence Effluent'!$F$5:$F$6,MATCH(UPPER($J$4)&"|Source|"&6,'Licence Effluent'!$L$5:$L$6,0))&"","")} | F75: {=IFERROR(INDEX('Licence Effluent'!$G$5:$G$6,MATCH(UPPER($J$4)&"|Source|"&6,'Licence Effluent'!$L$5:$L$6,0))&"","")} | L75: =IF(C75="","H","") -> H
B77: 3.0 CONDITIONS OF LICENSE
B78: 3.1 COMPLY WITH THE FOLLOWING MITIGATION MEASURES:
C79: ="During the effective period of this license, "&$J$8&" is authorized to discharge its effluent "&IF($J$15="","________",$J$15)&" to "&IF($J$13="","________",$J$13)&IF($J$14="",""," (not exceeding "&$J$14&" m³/day)")&" within the specific limits and subject to the condition set forth herein." -> During the effective period of this license, Tanmay Hardware Center is authorized to discharge its effluent ________ to ________ within the specific limits and subject to the condition set forth herein.
C80: The license authorizes the discharge of only those pollutants resulting from the facility processes, TSF and operations that have been clearly identified in the license application process.
B81: =IF($N$43="","","3.2 EFFLUENT LIMITATION AND MONITORING"&IF(IF($N$43="(none)","",$N$43)="",""," – "&IF($N$43="(none)","",$N$43))) | L81: =IF($N$43="","H","") -> H
C82: =IF($N$43="","",$J$8&" must limit and monitor discharges"&IF(IF($N$43="(none)","",$N$43)="",""," from "&IF($N$43="(none)","",$N$43))&" as specified in Table 3. The figure represents maximum effluent limits unless otherwise indicated. The licensee must comply with the effluent limits in the tables unless otherwise indicated, regardless of the frequency of monitoring or reporting required"," by other provisions of this license.") -> #N/A | L82: =IF($N$43="","H","") -> H
C83: =IF($N$43="","","Table 3. "&IF(IF($N$43="(none)","",$N$43)="","Effluent discharge limits","Effluent from "&IF($N$43="(none)","",$N$43))) | L83: =IF($N$43="","H","") -> H
C84: Parameter | D84: Unit | E84: Maximum Discharge Limit | F84: Sample Type | G84: Testing Schedule | L84: =IF($N$43="","H","") -> H
